Workbook

Sheet Tesla Company Analysis
B9: Tesla
B10: Company analysis

Sheet Drivers
B1: Drivers
B3: Selected case | C3: 1
B4: Company | C4: Tesla
B5: Currency | C5: USD
B6: Domestic country | C6: United States
B7: 10-year treasury yield (Sep 18 2020) | C7: 0.00697
B8: Market risk premium US | C8: 0.05
B9: Company beta (Dec 15 2020) | C9: 2.15
B10: Tesla share price (Dec 15 2020) | C10: 639.83
B11: Bond Yield (Sep 18 2020) | C11: 0.04324
B12: Corporate tax rate | C12: 0.21
B13: Expected inflation | C13: 0.02

Sheet Input --->
B13: Input --->

Sheet P&L Input
B1: P&L Input
B3: (in thousands) | C3: 2015 Act | D3: 2016 Act | E3: 2017 Act | F3: 2018 Act | G3: 2019 Act
B4: Automotive revenues | C4: 3740973 | D4: 6350766 | E4: 9641300 | F4: 18514983 | G4: 20821000
B5: Energy generation and storage | C5: 14477 | D5: 181394 | E5: 1116266 | F5: 1555244 | G5: 1531000
B6: Services and other | C6: 290575 | D6: 467972 | E6: 1001185 | F6: 1391041 | G6: 2226000
B7: Total revenues | C7: =SUM(C4:C6) -> 4046025 | D7: =SUM(D4:D6) -> 7000132 | E7: =SUM(E4:E6) -> 11758751 | F7: =SUM(F4:F6) -> 21461268 | G7: =SUM(G4:G6) -> 24578000
B8: Automotive cost of revenues | C8: -2823302 | D8: -4750081 | E8: -7432704 | F8: -14173997 | G8: -16398000
B9: Energy generation and storage cost of revenues | C9: -12287 | D9: -178332 | E9: -874538 | F9: -1364896 | G9: -1341000
B10: Services and other cost of revenues | C10: -286933 | D10: -472462 | E10: -1229022 | F10: -1880354 | G10: -2770000
B11: Gross profit | C11: =SUM(C7:C10) -> 923503 | D11: =SUM(D7:D10) -> 1599257 | E11: =SUM(E7:E10) -> 2222487 | F11: =SUM(F7:F10) -> 4042021 | G11: =SUM(G7:G10) -> 4069000
B12: Research and development | C12: -717900 | D12: -834408 | E12: -1378073 | F12: -1460370 | G12: -1343000
B13: Selling, general and administrative | C13: -922232 | D13: -1432189 | E13: -2476500 | F13: -2834491 | G13: -2646000
B14: Restructuring and other | F14: -135233 | G14: -149000
B15: EBIT | C15: =SUM(C11:C14) -> -716629 | D15: =SUM(D11:D14) -> -667340 | E15: =SUM(E11:E14) -> -1632086 | F15: =SUM(F11:F14) -> -388073 | G15: =SUM(G11:G14) -> -69000
B16: Interest income | C16: 1508 | D16: 8530 | E16: 19686 | F16: 24533 | G16: 44000
B17: Interest expense | C17: -118851 | D17: -198810 | E17: -471259 | F17: -663071 | G17: -685000
B18: Other income (expense), net | C18: -41652 | D18: 111272 | E18: -125373 | F18: 21866 | G18: 45000
B19: EBT | C19: =SUM(C15:C18) -> -875624 | D19: =SUM(D15:D18) -> -746348 | E19: =SUM(E15:E18) -> -2209032 | F19: =SUM(F15:F18) -> -1004745 | G19: =SUM(G15:G18) -> -665000
B20: Provision for income taxes | C20: -13039 | D20: -26698 | E20: -31546 | F20: -57837 | G20: -110000
B21: Net loss incl. minority interests | C21: =SUM(C19:C20) -> -888663 | D21: =SUM(D19:D20) -> -773046 | E21: =SUM(E19:E20) -> -2240578 | F21: =SUM(F19:F20) -> -1062582 | G21: =SUM(G19:G20) -> -775000
B22: Minority interests | C22: 0 | D22: 98132 | E22: 279178 | F22: 86491 | G22: -87000
B23: Net loss | C23: =SUM(C21:C22) -> -888663 | D23: =SUM(D21:D22) -> -674914 | E23: =SUM(E21:E22) -> -1961400 | F23: =SUM(F21:F22) -> -976091 | G23: =SUM(G21:G22) -> -862000
B25: KPIs
B26: Revenue % automotive y-o-y | D26: =D4/C4-1 -> 0.69762412 | E26: =E4/D4-1 -> 0.51813183 | F26: =F4/E4-1 -> 0.92038242 | G26: =G4/F4-1 -> 0.1245487
B27: Revenue % generation y-o-y | D27: =D5/C5-1 -> 11.529806 | E27: =E5/D5-1 -> 5.1538199 | F27: =F5/E5-1 -> 0.39325573 | G27: =G5/F5-1 -> -0.015588551
B28: Revenue % services y-o-y | D28: =D6/C6-1 -> 0.61050331 | E28: =E6/D6-1 -> 1.1394122 | F28: =F6/E6-1 -> 0.38939457 | G28: =G6/F6-1 -> 0.6002404
B29: GP% automotive | C29: =(C4+C8)/C4 -> 0.24530276 | D29: =(D4+D8)/D4 -> 0.25204597 | E29: =(E4+E8)/E4 -> 0.22907658 | F29: =(F4+F8)/F4 -> 0.23445801 | G29: =(G4+G8)/G4 -> 0.21242976
B30: GP% energy generation and automotive | C30: =(C5+C9)/C5 -> 0.15127444 | D30: =(D5+D9)/D5 -> 0.016880382 | E30: =(E5+E9)/E5 -> 0.21655054 | F30: =(F5+F9)/F5 -> 0.12239108 | G30: =(G5+G9)/G5 -> 0.12410189
B31: GP% services and other | C31: =(C6+C10)/C6 -> 0.012533769 | D31: =(D6+D10)/D6 -> -0.0095945911 | E31: =(E6+E10)/E6 -> -0.22756733 | F31: =(F6+F10)/F6 -> -0.3517603 | G31: =(G6+G10)/G6 -> -0.24438455
B32: Overall GP% | C32: {=SUM((C4:C6)+SUM(C8:C10))/SUM(C4:C6)} -> -1.3152516 | D32: {=SUM((D4:D6)+SUM(D8:D10))/SUM(D4:D6)} -> -1.3146171 | E32: {=SUM((E4:E6)+SUM(E8:E10))/SUM(E4:E6)} -> -1.4329788 | F32: {=SUM((F4:F6)+SUM(F8:F10))/SUM(F4:F6)} -> -1.4349792 | G32: {=SUM((G4:G6)+SUM(G8:G10))/SUM(G4:G6)} -> -1.5033363
B33: EBIT % | C33: =C15/C7 -> -0.17711927 | D33: =D15/D7 -> -0.095332488 | E33: =E15/E7 -> -0.13879756 | F33: =F15/F7 -> -0.018082482 | G33: =G15/G7 -> -0.0028073887
B34: Net loss % | C34: =C23/C7 -> -0.21963853 | D34: =D23/D7 -> -0.096414468 | E34: =E23/E7 -> -0.16680343 | F34: =F23/F7 -> -0.045481516 | G34: =G23/G7 -> -0.035072016
B35: ROA
B36: ROE

Sheet Balance Sheet Input
B1: Balance Sheet Input
B3: (in thousands) | C3: 31 Dec 2015 | D3: 31 Dec 2016 | E3: 31 Dec 2017 | F3: 31 Dec 2018 | G3: 31 Dec 2019
B4: Cash and cash equivalents | C4: 1196908 | D4: 3393216 | E4: 3367914 | F4: 3685618 | G4: 6268000
B5: Restricted cash and marketable securities | C5: 22628 | D5: 105519 | E5: 155323 | F5: 192551 | G5: 246000
B6: Accounts receivable, net | C6: 168965 | D6: 499142 | E6: 515381 | F6: 949022 | G6: 1324000
B7: Inventory | C7: 1277838 | D7: 2067454 | E7: 2263537 | F7: 3113446 | G7: 3552000
B8: Prepaid expenses and other current assets | C8: 115667 | D8: 194465 | E8: 268365 | F8: 365671 | G8: 713000
B9: Total current assets | C9: =SUM(C4:C8) -> 2782006 | D9: =SUM(D4:D8) -> 6259796 | E9: =SUM(E4:E8) -> 6570520 | F9: =SUM(F4:F8) -> 8306308 | G9: =SUM(G4:G8) -> 12103000
B10: Operating lease vehicles, net | C10: 1791403 | D10: 3134080 | E10: 4116604 | F10: 2089758 | G10: 2447000
B11: Solar energy systems, leased and to be leased, net | C11: 0 | D11: 5919880 | E11: 6347490 | F11: 6271396 | G11: 6138000
B12: Property, plant and equipment, net | C12: 3403334 | D12: 5982957 | E12: 10027522 | F12: 11330077 | G12: 10396000
B13: Operating lease right-of-use assets | C13: 0 | D13: 0 | E13: 0 | F13: 0 | G13: 1218000
B14: Intangible assets, net | C14: 12816 | D14: 376145 | E14: 361502 | F14: 282492 | G14: 339000
B15: portion | C15: 0 | D15: 506302 | E15: =456652+60237 -> 516889 | F15: 489707 | G15: 591000
B16: Restricted cash, net of current portion | C16: 31522 | D16: 268165 | E16: 441722 | F16: 398219 | G16: 269000
B17: Other assets | C17: 46858 | D17: 216751 | E17: 273123 | F17: 571657 | G17: 808000
B18: Total assets | C18: =SUM(C9:C17) -> 8067939 | D18: =SUM(D9:D17) -> 22664076 | E18: =SUM(E9:E17) -> 28655372 | F18: =SUM(F9:F17) -> 29739614 | G18: =SUM(G9:G17) -> 34309000
B19: Accounts payable | C19: 916148 | D19: 1860341 | E19: 2390250 | F19: 3404451 | G19: 3771000
B20: Accrued liabilities | C20: 422798 | D20: 1210028 | E20: 1731366 | F20: 2094253 | G20: 2905000
B21: Deferred revenue | C21: 423961 | D21: 763126 | E21: 1015253 | F21: 630292 | G21: 1163000
B22: Resale value guarantees | C22: 136831 | D22: 179504 | E22: 787333 | F22: 502840 | G22: 317000
B23: Customer deposits | C23: 283370 | D23: 663859 | E23: 853919 | F23: 792601 | G23: 726000
B24: Current portion of long-term debt and capital leases | C24: 627927 | D24: 984211 | E24: 796549 | F24: 2567699 | G24: 1785000
B25: Current portion of solar bonds issued to related
B26: parties | C26: 0 | D26: 165936 | E26: 100000 | F26: 0 | G26: 0
B27: Total current liabilities | C27: 2811035 | D27: 5827005 | E27: =SUM(E19:E26) -> 7674670 | F27: =SUM(F19:F26) -> 9992136 | G27: =SUM(G19:G26) -> 10667000
B28: Long-term debt and capital leases, net of current
B29: portion | C29: 2021093 | D29: 5860049 | E29: 9415700 | F29: 9403672 | G29: 11634000
B30: Other liabilities | C30: 2152107 | D30: 5438936 | E30: 6330414 | F30: 4586166 | G30: 4541000
B31: Total liabilities | C31: =SUM(C27:C30) -> 6984235 | D31: =SUM(D27:D30) -> 17125990 | E31: =SUM(E27:E30) -> 23420784 | F31: =SUM(F27:F30) -> 23981974 | G31: =SUM(G27:G30) -> 26842000
B32: Total stockholders' equity | C32: 1083704 | D32: 4752911 | E32: 4237242 | F32: 4923243 | G32: 6618000
B33: Noncontrolling interests in subsidiaries | C33: 0 | D33: 785175 | E33: 997346 | F33: 834397 | G33: 849000
B34: Total liabilities and equity | C34: =C31+C32+C33 -> 8067939 | D34: =D31+D32+D33 -> 22664076 | E34: =E31+E32+E33 -> 28655372 | F34: =F31+F32+F33 -> 29739614 | G34: =G31+G32+G33 -> 34309000
B36: KPIs
B37: Liquidity ratios
B38: Quick ratio | C38: =(C4+C5)/C27 -> 0.43383878 | D38: =(D4+D5)/D27 -> 0.60043453 | E38: =(E4+E5)/E27 -> 0.45907342 | F38: =(F4+F5)/F27 -> 0.38812212 | G38: =(G4+G5)/G27 -> 0.61066842
B39: Current ratio | C39: =C9/C27 -> 0.9896732 | D39: =D9/D27 -> 1.0742733 | E39: =E9/E27 -> 0.85613062 | F39: =F9/F27 -> 0.83128452 | G39: =G9/G27 -> 1.1346208
B40: DSO | C40: =C6/'P&L Input'!C7*360 -> 15.033867 | D40: =D6/'P&L Input'!D7*360 -> 25.669676 | E40: =E6/'P&L Input'!E7*360 -> 15.778645 | F40: =F6/'P&L Input'!F7*360 -> 15.919279 | G40: =G6/'P&L Input'!G7*360 -> 19.392953
B41: DIO | C41: =-C7/SUM('P&L Input'!C8:C10)*360 -> 147.32376 | D41: =-D7/SUM('P&L Input'!D8:D10)*360 -> 137.80794 | E41: =-E7/SUM('P&L Input'!E8:E10)*360 -> 85.449954 | F41: =-F7/SUM('P&L Input'!F8:F10)*360 -> 64.344949 | G41: =-G7/SUM('P&L Input'!G8:G10)*360 -> 62.349213
B42: DPO | C42: =-C19/SUM('P&L Input'!C8:C10)*360 -> 105.62401 | D42: =-D19/SUM('P&L Input'!D8:D10)*360 -> 124.00264 | E42: =-E19/SUM('P&L Input'!E8:E10)*360 -> 90.23345 | F42: =-F19/SUM('P&L Input'!F8:F10)*360 -> 70.35909 | G42: =-G19/SUM('P&L Input'!G8:G10)*360 -> 66.193379
B43: Net Trading Cycle | C43: =C40+C41-C42 -> 56.733621 | D43: =D40+D41-D42 -> 39.474972 | E43: =E40+E41-E42 -> 10.995149 | F43: =F40+F41-F42 -> 9.9051388 | G43: =G40+G41-G42 -> 15.548787
B44: Solvency ratios
B45: Debt ratio | C45: =C31/C18 -> 0.86567772 | D45: =D31/D18 -> 0.75564475 | E45: =E31/E18 -> 0.81732612 | F45: =F31/F18 -> 0.80639829 | G45: =G31/G18 -> 0.78236031
B46: Interest coverage | C46: <0 | D46: <0 | E46: <0 | F46: <0 | G46: <0

Sheet Income Statement Items --->
B13: Income Statement Items --->

Sheet 1. Automotive
B13: 1. Automotive

Sheet Tesla Automotive Deliveries
B1: Tesla Automotive Deliveries
B3: Tesla Deliveries
B4: Vehicle | C4: 2015 Act | D4: 2016 Act | E4: 2017 Act | F4: 2018 Act | G4: 2019 Act | H4: 2020 Fcst | I4: 2021 Fcst | J4: 2022 Fcst | K4: 2023 Fcst | L4: 2024 Fcst | M4: 2025 Fcst | N4: 2026 Fcst | O4: 2027 Fcst | P4: 2028 Fcst | Q4: 2029 Fcst
B5: Tesla Model 3 | C5: 0 | D5: 0 | E5: 1764 | F5: 146055 | G5: 300815 | H5: =G5*(1+H15) -> 481304 | I5: =H5*(1+I15) -> 529434.4 | J5: =I5*(1+J15) -> 582377.84 | K5: =J5*(1+K15) -> 628968.07 | L5: =K5*(1+L15) -> 679285.51 | M5: =L5*(1+M15) -> 706456.93 | N5: =M5*(1+N15) -> 734715.21 | O5: =N5*(1+O15) -> 764103.82 | ... Q5: =P5*(1+Q15) -> 826454.69
B6: Tesla Model S and X | C6: 50580 | D6: 76230 | E6: 101312 | F6: 98865 | G6: 66385 | H6: =G6*(1+H16) -> 69040.4 | I6: =H6*(1+I16) -> 71802.016 | J6: =I6*(1+J16) -> 74674.097 | K6: =J6*(1+K16) -> 77661.061 | L6: =K6*(1+L16) -> 80767.503 | M6: =L6*(1+M16) -> 83998.203 | N6: =M6*(1+N16) -> 87358.131 | O6: =N6*(1+O16) -> 90852.456 | ... Q6: =P6*(1+Q16) -> 98266.017
B7: Tesla Model Y | C7: 0 | D7: 0 | E7: 0 | F7: 0 | G7: 0 | H7: =E5 -> 1764 | I7: =F5 -> 146055 | J7: =G5 -> 300815 | K7: =J7*(1+K17) -> 481304 | L7: =K7*(1+L17) -> 529434.4 | M7: =L7*(1+M17) -> 582377.84 | N7: =M7*(1+N17) -> 628968.07 | O7: =N7*(1+O17) -> 679285.51 | P7: =O7*(1+P17) -> 706456.93 | Q7: =P7*(1+Q17) -> 734715.21
B8: Tesla Roadster 2 | C8: 0 | D8: 0 | E8: 0 | F8: 0 | G8: 0 | H8: - | I8: - | J8: 500 | K8: =J8*(1+K18) -> 1000 | L8: =K8*(1+L18) -> 1500 | M8: =L8*(1+M18) -> 1650 | N8: =M8*(1+N18) -> 1815 | O8: =N8*(1+O18) -> 1960.2 | P8: =O8*(1+P18) -> 2117.016 | Q8: =P8*(1+Q18) -> 2201.6966
B9: Tesla Pickup | C9: 0 | D9: 0 | E9: 0 | F9: 0 | G9: 0 | H9: - | I9: 250 | J9: =I9*(1+J19) -> 20699.405 | K9: =J9*(1+K19) -> 42632.511 | L9: =K9*(1+L19) -> 68212.018 | M9: =L9*(1+M19) -> 75033.22 | N9: =M9*(1+N19) -> 82536.542 | O9: =N9*(1+O19) -> 89139.465 | P9: =O9*(1+P19) -> 96270.623 | Q9: =P9*(1+Q19) -> 100121.45
B10: Tesla Semi | C10: 0 | D10: 0 | E10: 0 | F10: 0 | G10: 0 | H10: - | I10: 250 | J10: =I10*(1+J20) -> 20699.405 | K10: =J10*(1+K20) -> 42632.511 | L10: =K10*(1+L20) -> 68212.018 | M10: =L10*(1+M20) -> 75033.22 | N10: =M10*(1+N20) -> 82536.542 | O10: =N10*(1+O20) -> 89139.465 | P10: =O10*(1+P20) -> 96270.623 | Q10: =P10*(1+Q20) -> 100121.45
B11: Total | C11: =SUM(C5:C10) -> 50580 | D11: =SUM(D5:D10) -> 76230 | E11: =SUM(E5:E10) -> 103076 | F11: =SUM(F5:F10) -> 244920 | G11: =SUM(G5:G10) -> 367200 | H11: =SUM(H5:H10) -> 552108.4 | I11: =SUM(I5:I10) -> 747791.42 | J11: =SUM(J5:J10) -> 999765.75 | ... Q11: =SUM(Q5:Q10) -> 1861880.5
B13: y-o-y growth %
B15: Tesla Model 3 | C15: n.a. | D15: n.a. | E15: n.a. | F15: =F5/E5-1 -> 81.797619 | G15: =G5/F5-1 -> 1.0596008 | H15: 0.6 | I15: =$C$25 -> 0.1 | J15: =$C$25 -> 0.1 | K15: =$C$26 -> 0.08 | L15: =$C$26 -> 0.08 | M15: =$C$27 -> 0.04 | N15: =$C$27 -> 0.04 | O15: =$C$27 -> 0.04 | P15: =$C$27 -> 0.04 | Q15: =$C$27 -> 0.04
B16: Tesla Model S and X | C16: n.a. | D16: =D6/C6-1 -> 0.50711744 | E16: =E6/D6-1 -> 0.32903057 | F16: =F6/E6-1 -> -0.024153111 | G16: =G6/F6-1 -> -0.3285288 | H16: =$C$27 -> 0.04 | I16: =$C$27 -> 0.04 | J16: =$C$27 -> 0.04 | K16: =$C$27 -> 0.04 | L16: =$C$27 -> 0.04 | M16: =$C$27 -> 0.04 | N16: =$C$27 -> 0.04 | O16: =$C$27 -> 0.04 | ... Q16: =$C$27 -> 0.04
B17: Tesla Model Y | C17: n.a. | D17: n.a. | E17: n.a. | F17: n.a. | G17: n.a. | H17: n.a. | I17: =F15 -> 81.797619 | J17: =G15 -> 1.0596008 | K17: =H15 -> 0.6 | L17: =I15 -> 0.1 | M17: =J15 -> 0.1 | N17: =K15 -> 0.08 | O17: =L15 -> 0.08 | P17: =M15 -> 0.04 | Q17: =N15 -> 0.04
B18: Tesla Roadster 2 | C18: n.a. | D18: n.a. | E18: n.a. | F18: n.a. | G18: n.a. | H18: n.a. | I18: n.a. | J18: n.a. | K18: 1 | L18: 0.5 | M18: =$C$25 -> 0.1 | N18: =$C$25 -> 0.1 | O18: =$C$26 -> 0.08 | P18: =$C$26 -> 0.08 | Q18: =$C$27 -> 0.04
B19: Tesla Pickup | C19: n.a. | D19: n.a. | E19: n.a. | F19: n.a. | G19: n.a. | H19: n.a. | I19: n.a. | J19: =F$15 -> 81.797619 | K19: =G$15 -> 1.0596008 | L19: =H$15 -> 0.6 | M19: =$C$25 -> 0.1 | N19: =$C$25 -> 0.1 | O19: =$C$26 -> 0.08 | P19: =$C$26 -> 0.08 | Q19: =$C$27 -> 0.04
B20: Tesla Semi | C20: n.a. | D20: n.a. | E20: n.a. | F20: n.a. | G20: n.a. | H20: n.a. | I20: n.a. | J20: =F$15 -> 81.797619 | K20: =G$15 -> 1.0596008 | L20: =H$15 -> 0.6 | M20: =$C$25 -> 0.1 | N20: =$C$25 -> 0.1 | O20: =$C$26 -> 0.08 | P20: =$C$26 -> 0.08 | Q20: =$C$27 -> 0.04
B24: Assumed growth after introduction:
B25: 2 years | C25: 0.1
B26: 2 years | C26: 0.08
B27: onwards | C27: 0.04

Sheet  Automotive Deliveries Chart
B1: Tesla Automotive Deliveries Chart

Sheet Automotive Deliverie comparable
B1: Tesla Deliveries comparables
B3: Comparables 2015-2019
B5: Vehicle Sales 2015-2019 - average | C5: Average | D5: Adj. Average
B6: GM | C6: 9600340 | D6: =C6 -> 9600340
B7: Ford | C7: 6607000 | D7: =C7 -> 6607000
B8: Fiat Chrysler | C8: 4740000 | D8: =C8 -> 4740000
B9: BMW | C9: 2460000 | D9: =C9 -> 2460000
B10: Volkswagen | C10: 10700000 | D10: =C10 -> 10700000
B11: Average | D11: =AVERAGE(D6:D10) -> 6821468
B15: Tesla Expected Deliveries
B16: 2020 | C16: ='Tesla Automotive Deliveries'!H11 -> 552108.4
B17: 2025 | C17: ='Tesla Automotive Deliveries'!M11 -> 1524549.4
B18: 2029 | C18: ='Tesla Automotive Deliveries'!Q11 -> 1861880.5

Sheet Average Automotive Model Prices
B1: Average Tesla Automative Model prices
B3: Model and Version | C3: Range | D3: Base price | E3: Fully loaded | F3: Average Price per Model
B4: Model 3 Standard Range Plus | C4: 250 miles | D4: 39990 | E4: 51490
B5: Model 3 Long Range | C5: 322 miles | D5: 48990 | E5: 60490
B6: Model 3 Performance | C6: 322 miles | D6: 56990 | E6: 66990
B7: Average Model 3 | F7: =AVERAGE(D4:E6) -> 54156.667
B8: Model S Long Range | C8: 373 miles | D8: 79990 | E8: 95490
B9: Model S Performance | C9: 348 miles | D9: 99990 | E9: 115990
B10: Model X Long Range | C10: 328 miles | D10: 84990 | E10: 106490
B11: Model X Performance | C11: 305 miles | D11: 104990 | E11: 128490
B12: Average Model S and X | F12: =AVERAGE(D8:E11) -> 102052.5
B14: Model | C14: Base price | D14: Max price
B15: CyberTruck | C15: 39900 | D15: 76900 | F15: =AVERAGE(C15:D15) -> 58400
B16: Model Y | C16: 48000 | D16: 74000 | F16: =AVERAGE(C16:D16) -> 61000
B17: Roadster 2020 | C17: 200000 | D17: 250000 | F17: =AVERAGE(C17:D17) -> 225000
B18: Semi | C18: 150000 | D18: 200000 | F18: =AVERAGE(C18:D18) -> 175000

Sheet Tesla Revenue Automotive
B1: Tesla Revenue Automotive
B3: Tesla Revenue Automotive (in mln $)
B4: Vehicle | C4: 2015 Act | D4: 2016 Act | E4: 2017 Act | F4: 2018 Act | G4: 2019 Act | H4: 2020 Fcst | I4: 2021 Fcst | J4: 2022 Fcst | K4: 2023 Fcst | L4: 2024 Fcst | M4: 2025 Fcst | N4: 2026 Fcst | O4: 2027 Fcst | P4: 2028 Fcst | Q4: 2029 Fcst | R4: Average Price ($)
B5: Tesla Model 3 | E5: 88.268789 | F5: 8136.483 | G5: 14705.599 | H5: =($R5*'Tesla Automotive Deliveries'!H5)*H14/1000000 -> 26587.137 | I5: =($R$5*'Tesla Automotive Deliveries'!I5)*I14/1000000 -> 29245.85 | J5: =($R$5*'Tesla Automotive Deliveries'!J5)*J14/1000000 -> 32170.435 | K5: =($R$5*'Tesla Automotive Deliveries'!K5)*K14/1000000 -> 34744.07 | L5: =($R$5*'Tesla Automotive Deliveries'!L5)*L14/1000000 -> 37523.596 | M5: =($R$5*'Tesla Automotive Deliveries'!M5)*M14/1000000 -> 39024.54 | N5: =($R$5*'Tesla Automotive Deliveries'!N5)*N14/1000000 -> 40585.521 | O5: =($R$5*'Tesla Automotive Deliveries'!O5)*O14/1000000 -> 42208.942 | P5: =($R$5*'Tesla Automotive Deliveries'!P5)*P14/1000000 -> 43897.3 | Q5: =($R$5*'Tesla Automotive Deliveries'!Q5)*Q14/1000000 -> 45653.192 | R5: =AVERAGE('Average Automotive Model Prices'!$F$7) -> 54156.667
B6: Tesla Model S and X | C6: 3740.973 | D6: 6350.766 | E6: 9553.0312 | F6: 10378.5 | G6: 6115.4007 | H6: =($R6*'Tesla Automotive Deliveries'!H6)*H15/1000000 -> 7186.6603 | I6: =($R6*'Tesla Automotive Deliveries'!I6)*I15/1000000 -> 7474.1267 | J6: =($R6*'Tesla Automotive Deliveries'!J6)*J15/1000000 -> 7773.0918 | K6: =($R6*'Tesla Automotive Deliveries'!K6)*K15/1000000 -> 8084.0155 | L6: =($R6*'Tesla Automotive Deliveries'!L6)*L15/1000000 -> 8407.3761 | M6: =($R6*'Tesla Automotive Deliveries'!M6)*M15/1000000 -> 8743.6711 | N6: =($R6*'Tesla Automotive Deliveries'!N6)*N15/1000000 -> 9093.418 | O6: =($R6*'Tesla Automotive Deliveries'!O6)*O15/1000000 -> 9457.1547 | ... Q6: =($R6*'Tesla Automotive Deliveries'!Q6)*Q15/1000000 -> 10228.859 | R6: =AVERAGE('Average Automotive Model Prices'!$F$12) -> 102052.5
B7: Tesla Model Y | C7: =($R7*'Tesla Automotive Deliveries'!C7)*C16/1000000 -> 0 | D7: =($R7*'Tesla Automotive Deliveries'!D7)*D16/1000000 -> 0 | E7: =($R7*'Tesla Automotive Deliveries'!E7)*E16/1000000 -> 0 | F7: =($R7*'Tesla Automotive Deliveries'!F7)*F16/1000000 -> 0 | G7: =($R7*'Tesla Automotive Deliveries'!G7)*G16/1000000 -> 0 | H7: =($R7*'Tesla Automotive Deliveries'!H7)*H16/1000000 -> 109.75608 | I7: =($R7*'Tesla Automotive Deliveries'!I7)*I16/1000000 -> 9087.5421 | J7: =($R7*'Tesla Automotive Deliveries'!J7)*J16/1000000 -> 18716.709 | ... Q7: =($R7*'Tesla Automotive Deliveries'!Q7)*Q16/1000000 -> 45713.98 | R7: =AVERAGE('Average Automotive Model Prices'!$F$16) -> 61000
B8: Tesla Roadster 2 | C8: =($R8*'Tesla Automotive Deliveries'!C8)*C17/1000000 -> 0 | D8: =($R8*'Tesla Automotive Deliveries'!D8)*D17/1000000 -> 0 | E8: =($R8*'Tesla Automotive Deliveries'!E8)*E17/1000000 -> 0 | F8: =($R8*'Tesla Automotive Deliveries'!F8)*F17/1000000 -> 0 | G8: =($R8*'Tesla Automotive Deliveries'!G8)*G17/1000000 -> 0 | H8: - | I8: - | J8: =($R8*'Tesla Automotive Deliveries'!J8)*J17/1000000 -> 114.75 | K8: =($R8*'Tesla Automotive Deliveries'!K8)*K17/1000000 -> 229.5 | L8: =($R8*'Tesla Automotive Deliveries'!L8)*L17/1000000 -> 344.25 | M8: =($R8*'Tesla Automotive Deliveries'!M8)*M17/1000000 -> 378.675 | N8: =($R8*'Tesla Automotive Deliveries'!N8)*N17/1000000 -> 416.5425 | O8: =($R8*'Tesla Automotive Deliveries'!O8)*O17/1000000 -> 449.8659 | P8: =($R8*'Tesla Automotive Deliveries'!P8)*P17/1000000 -> 485.85517 | Q8: =($R8*'Tesla Automotive Deliveries'!Q8)*Q17/1000000 -> 505.28938 | R8: =AVERAGE('Average Automotive Model Prices'!$F$17) -> 225000
B9: Tesla Pickup | C9: =($R9*'Tesla Automotive Deliveries'!C9)*C18/1000000 -> 0 | D9: =($R9*'Tesla Automotive Deliveries'!D9)*D18/1000000 -> 0 | E9: =($R9*'Tesla Automotive Deliveries'!E9)*E18/1000000 -> 0 | F9: =($R9*'Tesla Automotive Deliveries'!F9)*F18/1000000 -> 0 | G9: =($R9*'Tesla Automotive Deliveries'!G9)*G18/1000000 -> 0 | H9: - | I9: =($R9*'Tesla Automotive Deliveries'!I9)*I18/1000000 -> 14.892 | J9: =($R9*'Tesla Automotive Deliveries'!J9)*J18/1000000 -> 1233.0221 | K9: =($R9*'Tesla Automotive Deliveries'!K9)*K18/1000000 -> 2539.5334 | L9: =($R9*'Tesla Automotive Deliveries'!L9)*L18/1000000 -> 4063.2535 | M9: =($R9*'Tesla Automotive Deliveries'!M9)*M18/1000000 -> 4469.5788 | N9: =($R9*'Tesla Automotive Deliveries'!N9)*N18/1000000 -> 4916.5367 | O9: =($R9*'Tesla Automotive Deliveries'!O9)*O18/1000000 -> 5309.8597 | P9: =($R9*'Tesla Automotive Deliveries'!P9)*P18/1000000 -> 5734.6484 | Q9: =($R9*'Tesla Automotive Deliveries'!Q9)*Q18/1000000 -> 5964.0344 | R9: =AVERAGE('Average Automotive Model Prices'!$F$15) -> 58400
B10: Tesla Semi | C10: =($R10*'Tesla Automotive Deliveries'!C10)*C19/1000000 -> 0 | D10: =($R10*'Tesla Automotive Deliveries'!D10)*D19/1000000 -> 0 | E10: =($R10*'Tesla Automotive Deliveries'!E10)*E19/1000000 -> 0 | F10: =($R10*'Tesla Automotive Deliveries'!F10)*F19/1000000 -> 0 | G10: =($R10*'Tesla Automotive Deliveries'!G10)*G19/1000000 -> 0 | H10: - | I10: =($R10*'Tesla Automotive Deliveries'!I10)*I19/1000000 -> 44.625 | J10: =($R10*'Tesla Automotive Deliveries'!J10)*J19/1000000 -> 3694.8438 | K10: =($R10*'Tesla Automotive Deliveries'!K10)*K19/1000000 -> 7609.9033 | L10: =($R10*'Tesla Automotive Deliveries'!L10)*L19/1000000 -> 12175.845 | M10: =($R10*'Tesla Automotive Deliveries'!M10)*M19/1000000 -> 13393.43 | N10: =($R10*'Tesla Automotive Deliveries'!N10)*N19/1000000 -> 14732.773 | O10: =($R10*'Tesla Automotive Deliveries'!O10)*O19/1000000 -> 15911.395 | P10: =($R10*'Tesla Automotive Deliveries'!P10)*P19/1000000 -> 17184.306 | Q10: =($R10*'Tesla Automotive Deliveries'!Q10)*Q19/1000000 -> 17871.678 | R10: =AVERAGE('Average Automotive Model Prices'!$F$18) -> 175000
B11: Total | C11: =SUM(C5:C10) -> 3740.973 | D11: =SUM(D5:D10) -> 6350.766 | E11: =SUM(E5:E10) -> 9641.3 | F11: =SUM(F5:F10) -> 18514.983 | G11: =SUM(G5:G10) -> 20821 | H11: =SUM(H5:H10) -> 33883.553 | I11: =SUM(I5:I10) -> 45867.036 | J11: =SUM(J5:J10) -> 63702.852 | ... Q11: =SUM(Q5:Q10) -> 125937.03
B13: Selected case
B14: Tesla Model 3 | H14: =CHOOSE(Drivers!$C$3,'Tesla Revenue Automotive'!H22,'Tesla Revenue Automotive'!H30,'Tesla Revenue Automotive'!H38) -> 1.02 | I14: =CHOOSE(Drivers!$C$3,'Tesla Revenue Automotive'!I22,'Tesla Revenue Automotive'!I30,'Tesla Revenue Automotive'!I38) -> 1.02 | J14: =CHOOSE(Drivers!$C$3,'Tesla Revenue Automotive'!J22,'Tesla Revenue Automotive'!J30,'Tesla Revenue Automotive'!J38) -> 1.02 | K14: =CHOOSE(Drivers!$C$3,'Tesla Revenue Automotive'!K22,'Tesla Revenue Automotive'!K30,'Tesla Revenue Automotive'!K38) -> 1.02 | L14: =CHOOSE(Drivers!$C$3,'Tesla Revenue Automotive'!L22,'Tesla Revenue Automotive'!L30,'Tesla Revenue Automotive'!L38) -> 1.02 | M14: =CHOOSE(Drivers!$C$3,'Tesla Revenue Automotive'!M22,'Tesla Revenue Automotive'!M30,'Tesla Revenue Automotive'!M38) -> 1.02 | N14: =CHOOSE(Drivers!$C$3,'Tesla Revenue Automotive'!N22,'Tesla Revenue Automotive'!N30,'Tesla Revenue Automotive'!N38) -> 1.02 | O14: =CHOOSE(Drivers!$C$3,'Tesla Revenue Automotive'!O22,'Tesla Revenue Automotive'!O30,'Tesla Revenue Automotive'!O38) -> 1.02 | ... Q14: =CHOOSE(Drivers!$C$3,'Tesla Revenue Automotive'!Q22,'Tesla Revenue Automotive'!Q30,'Tesla Revenue Automotive'!Q38) -> 1.02
B15: Tesla Model S and X | H15: =CHOOSE(Drivers!$C$3,'Tesla Revenue Automotive'!H23,'Tesla Revenue Automotive'!H31,'Tesla Revenue Automotive'!H39) -> 1.02 | I15: =CHOOSE(Drivers!$C$3,'Tesla Revenue Automotive'!I23,'Tesla Revenue Automotive'!I31,'Tesla Revenue Automotive'!I39) -> 1.02 | J15: =CHOOSE(Drivers!$C$3,'Tesla Revenue Automotive'!J23,'Tesla Revenue Automotive'!J31,'Tesla Revenue Automotive'!J39) -> 1.02 | K15: =CHOOSE(Drivers!$C$3,'Tesla Revenue Automotive'!K23,'Tesla Revenue Automotive'!K31,'Tesla Revenue Automotive'!K39) -> 1.02 | L15: =CHOOSE(Drivers!$C$3,'Tesla Revenue Automotive'!L23,'Tesla Revenue Automotive'!L31,'Tesla Revenue Automotive'!L39) -> 1.02 | M15: =CHOOSE(Drivers!$C$3,'Tesla Revenue Automotive'!M23,'Tesla Revenue Automotive'!M31,'Tesla Revenue Automotive'!M39) -> 1.02 | N15: =CHOOSE(Drivers!$C$3,'Tesla Revenue Automotive'!N23,'Tesla Revenue Automotive'!N31,'Tesla Revenue Automotive'!N39) -> 1.02 | O15: =CHOOSE(Drivers!$C$3,'Tesla Revenue Automotive'!O23,'Tesla Revenue Automotive'!O31,'Tesla Revenue Automotive'!O39) -> 1.02 | ... Q15: =CHOOSE(Drivers!$C$3,'Tesla Revenue Automotive'!Q23,'Tesla Revenue Automotive'!Q31,'Tesla Revenue Automotive'!Q39) -> 1.02
B16: Tesla Model Y | H16: =CHOOSE(Drivers!$C$3,'Tesla Revenue Automotive'!H24,'Tesla Revenue Automotive'!H32,'Tesla Revenue Automotive'!H40) -> 1.02 | I16: =CHOOSE(Drivers!$C$3,'Tesla Revenue Automotive'!I24,'Tesla Revenue Automotive'!I32,'Tesla Revenue Automotive'!I40) -> 1.02 | J16: =CHOOSE(Drivers!$C$3,'Tesla Revenue Automotive'!J24,'Tesla Revenue Automotive'!J32,'Tesla Revenue Automotive'!J40) -> 1.02 | K16: =CHOOSE(Drivers!$C$3,'Tesla Revenue Automotive'!K24,'Tesla Revenue Automotive'!K32,'Tesla Revenue Automotive'!K40) -> 1.02 | L16: =CHOOSE(Drivers!$C$3,'Tesla Revenue Automotive'!L24,'Tesla Revenue Automotive'!L32,'Tesla Revenue Automotive'!L40) -> 1.02 | M16: =CHOOSE(Drivers!$C$3,'Tesla Revenue Automotive'!M24,'Tesla Revenue Automotive'!M32,'Tesla Revenue Automotive'!M40) -> 1.02 | N16: =CHOOSE(Drivers!$C$3,'Tesla Revenue Automotive'!N24,'Tesla Revenue Automotive'!N32,'Tesla Revenue Automotive'!N40) -> 1.02 | O16: =CHOOSE(Drivers!$C$3,'Tesla Revenue Automotive'!O24,'Tesla Revenue Automotive'!O32,'Tesla Revenue Automotive'!O40) -> 1.02 | ... Q16: =CHOOSE(Drivers!$C$3,'Tesla Revenue Automotive'!Q24,'Tesla Revenue Automotive'!Q32,'Tesla Revenue Automotive'!Q40) -> 1.02
B17: Tesla Roadster 2 | H17: =CHOOSE(Drivers!$C$3,'Tesla Revenue Automotive'!H25,'Tesla Revenue Automotive'!H33,'Tesla Revenue Automotive'!H41) -> 1.02 | I17: =CHOOSE(Drivers!$C$3,'Tesla Revenue Automotive'!I25,'Tesla Revenue Automotive'!I33,'Tesla Revenue Automotive'!I41) -> 1.02 | J17: =CHOOSE(Drivers!$C$3,'Tesla Revenue Automotive'!J25,'Tesla Revenue Automotive'!J33,'Tesla Revenue Automotive'!J41) -> 1.02 | K17: =CHOOSE(Drivers!$C$3,'Tesla Revenue Automotive'!K25,'Tesla Revenue Automotive'!K33,'Tesla Revenue Automotive'!K41) -> 1.02 | L17: =CHOOSE(Drivers!$C$3,'Tesla Revenue Automotive'!L25,'Tesla Revenue Automotive'!L33,'Tesla Revenue Automotive'!L41) -> 1.02 | M17: =CHOOSE(Drivers!$C$3,'Tesla Revenue Automotive'!M25,'Tesla Revenue Automotive'!M33,'Tesla Revenue Automotive'!M41) -> 1.02 | N17: =CHOOSE(Drivers!$C$3,'Tesla Revenue Automotive'!N25,'Tesla Revenue Automotive'!N33,'Tesla Revenue Automotive'!N41) -> 1.02 | O17: =CHOOSE(Drivers!$C$3,'Tesla Revenue Automotive'!O25,'Tesla Revenue Automotive'!O33,'Tesla Revenue Automotive'!O41) -> 1.02 | ... Q17: =CHOOSE(Drivers!$C$3,'Tesla Revenue Automotive'!Q25,'Tesla Revenue Automotive'!Q33,'Tesla Revenue Automotive'!Q41) -> 1.02
B18: Tesla Pickup | H18: =CHOOSE(Drivers!$C$3,'Tesla Revenue Automotive'!H26,'Tesla Revenue Automotive'!H34,'Tesla Revenue Automotive'!H42) -> 1.02 | I18: =CHOOSE(Drivers!$C$3,'Tesla Revenue Automotive'!I26,'Tesla Revenue Automotive'!I34,'Tesla Revenue Automotive'!I42) -> 1.02 | J18: =CHOOSE(Drivers!$C$3,'Tesla Revenue Automotive'!J26,'Tesla Revenue Automotive'!J34,'Tesla Revenue Automotive'!J42) -> 1.02 | K18: =CHOOSE(Drivers!$C$3,'Tesla Revenue Automotive'!K26,'Tesla Revenue Automotive'!K34,'Tesla Revenue Automotive'!K42) -> 1.02 | L18: =CHOOSE(Drivers!$C$3,'Tesla Revenue Automotive'!L26,'Tesla Revenue Automotive'!L34,'Tesla Revenue Automotive'!L42) -> 1.02 | M18: =CHOOSE(Drivers!$C$3,'Tesla Revenue Automotive'!M26,'Tesla Revenue Automotive'!M34,'Tesla Revenue Automotive'!M42) -> 1.02 | N18: =CHOOSE(Drivers!$C$3,'Tesla Revenue Automotive'!N26,'Tesla Revenue Automotive'!N34,'Tesla Revenue Automotive'!N42) -> 1.02 | O18: =CHOOSE(Drivers!$C$3,'Tesla Revenue Automotive'!O26,'Tesla Revenue Automotive'!O34,'Tesla Revenue Automotive'!O42) -> 1.02 | ... Q18: =CHOOSE(Drivers!$C$3,'Tesla Revenue Automotive'!Q26,'Tesla Revenue Automotive'!Q34,'Tesla Revenue Automotive'!Q42) -> 1.02
B19: Tesla Semi | H19: =CHOOSE(Drivers!$C$3,'Tesla Revenue Automotive'!H27,'Tesla Revenue Automotive'!H35,'Tesla Revenue Automotive'!H43) -> 1.02 | I19: =CHOOSE(Drivers!$C$3,'Tesla Revenue Automotive'!I27,'Tesla Revenue Automotive'!I35,'Tesla Revenue Automotive'!I43) -> 1.02 | J19: =CHOOSE(Drivers!$C$3,'Tesla Revenue Automotive'!J27,'Tesla Revenue Automotive'!J35,'Tesla Revenue Automotive'!J43) -> 1.02 | K19: =CHOOSE(Drivers!$C$3,'Tesla Revenue Automotive'!K27,'Tesla Revenue Automotive'!K35,'Tesla Revenue Automotive'!K43) -> 1.02 | L19: =CHOOSE(Drivers!$C$3,'Tesla Revenue Automotive'!L27,'Tesla Revenue Automotive'!L35,'Tesla Revenue Automotive'!L43) -> 1.02 | M19: =CHOOSE(Drivers!$C$3,'Tesla Revenue Automotive'!M27,'Tesla Revenue Automotive'!M35,'Tesla Revenue Automotive'!M43) -> 1.02 | N19: =CHOOSE(Drivers!$C$3,'Tesla Revenue Automotive'!N27,'Tesla Revenue Automotive'!N35,'Tesla Revenue Automotive'!N43) -> 1.02 | O19: =CHOOSE(Drivers!$C$3,'Tesla Revenue Automotive'!O27,'Tesla Revenue Automotive'!O35,'Tesla Revenue Automotive'!O43) -> 1.02 | ... Q19: =CHOOSE(Drivers!$C$3,'Tesla Revenue Automotive'!Q27,'Tesla Revenue Automotive'!Q35,'Tesla Revenue Automotive'!Q43) -> 1.02
B21: Best case
B22: Tesla Model 3 | H22: 1.02 | I22: 1.02 | J22: 1.02 | K22: 1.02 | L22: 1.02 | M22: 1.02 | N22: 1.02 | O22: 1.02 | P22: 1.02 | Q22: 1.02
B23: Tesla Model S and X | H23: 1.02 | I23: 1.02 | J23: 1.02 | K23: 1.02 | L23: 1.02 | M23: 1.02 | N23: 1.02 | O23: 1.02 | P23: 1.02 | Q23: 1.02
B24: Tesla Model Y | H24: 1.02 | I24: 1.02 | J24: 1.02 | K24: 1.02 | L24: 1.02 | M24: 1.02 | N24: 1.02 | O24: 1.02 | P24: 1.02 | Q24: 1.02
B25: Tesla Roadster 2 | H25: 1.02 | I25: 1.02 | J25: 1.02 | K25: 1.02 | L25: 1.02 | M25: 1.02 | N25: 1.02 | O25: 1.02 | P25: 1.02 | Q25: 1.02
B26: Tesla Pickup | H26: 1.02 | I26: 1.02 | J26: 1.02 | K26: 1.02 | L26: 1.02 | M26: 1.02 | N26: 1.02 | O26: 1.02 | P26: 1.02 | Q26: 1.02
B27: Tesla Semi | H27: 1.02 | I27: 1.02 | J27: 1.02 | K27: 1.02 | L27: 1.02 | M27: 1.02 | N27: 1.02 | O27: 1.02 | P27: 1.02 | Q27: 1.02
B29: Base case
B30: Tesla Model 3 | H30: 1 | I30: 1 | J30: 1 | K30: 1 | L30: 1 | M30: 1 | N30: 1 | O30: 1 | P30: 1 | Q30: 1
B31: Tesla Model S and X | H31: 1 | I31: 1 | J31: 1 | K31: 1 | L31: 1 | M31: 1 | N31: 1 | O31: 1 | P31: 1 | Q31: 1
B32: Tesla Model Y | H32: 1 | I32: 1 | J32: 1 | K32: 1 | L32: 1 | M32: 1 | N32: 1 | O32: 1 | P32: 1 | Q32: 1
B33: Tesla Roadster 2 | H33: 1 | I33: 1 | J33: 1 | K33: 1 | L33: 1 | M33: 1 | N33: 1 | O33: 1 | P33: 1 | Q33: 1
B34: Tesla Pickup | H34: 1 | I34: 1 | J34: 1 | K34: 1 | L34: 1 | M34: 1 | N34: 1 | O34: 1 | P34: 1 | Q34: 1
B35: Tesla Semi | H35: 1 | I35: 1 | J35: 1 | K35: 1 | L35: 1 | M35: 1 | N35: 1 | O35: 1 | P35: 1 | Q35: 1
B37: Worst case
B38: Tesla Model 3 | H38: 0.98 | I38: 0.98 | J38: 0.98 | K38: 0.98 | L38: 0.98 | M38: 0.98 | N38: 0.98 | O38: 0.98 | P38: 0.98 | Q38: 0.98
B39: Tesla Model S and X | H39: 0.98 | I39: 0.98 | J39: 0.98 | K39: 0.98 | L39: 0.98 | M39: 0.98 | N39: 0.98 | O39: 0.98 | P39: 0.98 | Q39: 0.98
B40: Tesla Model Y | H40: 0.98 | I40: 0.98 | J40: 0.98 | K40: 0.98 | L40: 0.98 | M40: 0.98 | N40: 0.98 | O40: 0.98 | P40: 0.98 | Q40: 0.98
B41: Tesla Roadster 2 | H41: 0.98 | I41: 0.98 | J41: 0.98 | K41: 0.98 | L41: 0.98 | M41: 0.98 | N41: 0.98 | O41: 0.98 | P41: 0.98 | Q41: 0.98
B42: Tesla Pickup | H42: 0.98 | I42: 0.98 | J42: 0.98 | K42: 0.98 | L42: 0.98 | M42: 0.98 | N42: 0.98 | O42: 0.98 | P42: 0.98 | Q42: 0.98
B43: Tesla Semi | H43: 0.98 | I43: 0.98 | J43: 0.98 | K43: 0.98 | L43: 0.98 | M43: 0.98 | N43: 0.98 | O43: 0.98 | P43: 0.98 | Q43: 0.98

Sheet Tesla Automotivo GP% 
B1: Tesla Automotive Gross Profit Margin %
B3: Comparables 2019
B5: Vehicle | C5: Comparable companies | D5: GP % Comp. 1 | E5: GP % Comp. 2 | F5: GP % Comp. 3 | H5: Average
B6: Tesla Model 3 | C6: GM, Ford, Fiat Chrysler | D6: 0.187 | E6: =(((155900-134693)/155900)+((160338-136269)/160338))/2 -> 0.14307182 | F6: =(((108187-93164)/108187)+((110412-95011)/110412))/2 -> 0.13917403 | H6: =C16 -> 0.22344388 | I6: Historic
B7: Tesla Model S and X | C7: BMW, Mercedes Cars, Volkswagen | D7: =((13620/91682)+(13928/85846))/2 -> 0.15540049 | E7: =((33067/167362)+(29165/172745))/2 -> 0.18320519 | F7: 0.172 | H7: =C17 -> 0.22344388 | I7: Historic
B8: Tesla Model Y | C8: GM, Ford, Fiat Chrysler | D8: 0.187 | E8: =(((155900-134693)/155900)+((160338-136269)/160338))/2 -> 0.14307182 | F8: =(((108187-93164)/108187)+((110412-95011)/110412))/2 -> 0.13917403 | H8: =AVERAGE(D8:F8) -> 0.15641528 | I8: Comparables
B9: Tesla Roadster 2 | C9: Jaguar, Porsche, Ferrari | D9: =(((24214-15670)/24214)+((25786-16328)/25786))/2 -> 0.35982095 | E9: 0.44 | F9: =(((3766-1805)/3766)+((3420-1623)/3420))/2 -> 0.52307511 | H9: =AVERAGE(D9:F9) -> 0.44096535 | I9: Comparables
B10: Tesla Pickup | C10: GM, Ford, Fiat Chrysler | D10: =D6 -> 0.187 | E10: =E6 -> 0.14307182 | F10: =F6 -> 0.13917403 | H10: =AVERAGE(D10:F10) -> 0.15641528 | I10: Comparables
B11: Tesla Semi | C11: Scania, MAN, Paccar | D11: 0.23 | E11: 0.23 | F11: =(((24120-20556)/24120)+((22139-18925)/22139))/2 -> 0.14646743 | H11: =AVERAGE(D11:F11) -> 0.20215581 | I11: Comparables
B13: Historical
B15: Vehicle | C15: Historic Average GP%
B16: Tesla Model 3 | C16: =AVERAGE('P&L Input'!F29:G29) -> 0.22344388
B17: Tesla Model S and X | C17: =AVERAGE('P&L Input'!F29:G29) -> 0.22344388
B18: Tesla Model Y | C18: n.a.
B19: Tesla Roadster 2 | C19: n.a.
B20: Tesla Pickup | C20: n.a.
B21: Tesla Semi | C21: n.a.

Sheet Tesla Automotive GP 
B1: Tesla Automotive Gross Profit
B3: Tesla Gross Profit (in mln $)
B4: Vehicle | C4: 2015 Act | D4: 2016 Act | E4: 2017 Act | F4: 2018 Act | G4: 2019 Act | H4: 2020 Fcst | I4: 2021 Fcst | J4: 2022 Fcst | K4: 2023 Fcst | L4: 2024 Fcst | M4: 2025 Fcst | N4: 2026 Fcst | O4: 2027 Fcst | P4: 2028 Fcst | Q4: 2029 Fcst
B5: Tesla Model 3 | C5: n.a. | D5: n.a. | E5: n.a. | F5: n.a. | G5: n.a. | H5: =H14*'Tesla Revenue Automotive'!H5 -> 6339.5401 | I5: =I14*'Tesla Revenue Automotive'!I5 -> 6973.4941 | J5: =J14*'Tesla Revenue Automotive'!J5 -> 7670.8435 | K5: =K14*'Tesla Revenue Automotive'!K5 -> 8284.511 | L5: =L14*'Tesla Revenue Automotive'!L5 -> 8947.2719 | M5: =M14*'Tesla Revenue Automotive'!M5 -> 9305.1628 | N5: =N14*'Tesla Revenue Automotive'!N5 -> 9677.3693 | O5: =O14*'Tesla Revenue Automotive'!O5 -> 10064.464 | ... Q5: =Q14*'Tesla Revenue Automotive'!Q5 -> 10885.724
B6: Tesla Model S and X | C6: n.a. | D6: n.a. | E6: n.a. | F6: n.a. | G6: n.a. | H6: =H15*'Tesla Revenue Automotive'!H6 -> 1713.6152 | I6: =I15*'Tesla Revenue Automotive'!I6 -> 1782.1598 | J6: =J15*'Tesla Revenue Automotive'!J6 -> 1853.4462 | K6: =K15*'Tesla Revenue Automotive'!K6 -> 1927.584 | L6: =L15*'Tesla Revenue Automotive'!L6 -> 2004.6874 | M6: =M15*'Tesla Revenue Automotive'!M6 -> 2084.8749 | N6: =N15*'Tesla Revenue Automotive'!N6 -> 2168.2699 | O6: =O15*'Tesla Revenue Automotive'!O6 -> 2255.0007 | ... Q6: =Q15*'Tesla Revenue Automotive'!Q6 -> 2439.0087
B7: Tesla Model Y | C7: 0 | D7: 0 | E7: 0 | F7: 0 | G7: =G16*'Tesla Revenue Automotive'!G7 -> 0 | H7: =H16*'Tesla Revenue Automotive'!H7 -> 18.81387 | I7: =I16*'Tesla Revenue Automotive'!I7 -> 1557.7436 | J7: =J16*'Tesla Revenue Automotive'!J7 -> 3208.33 | K7: =K16*'Tesla Revenue Automotive'!K7 -> 5133.3281 | L7: =L16*'Tesla Revenue Automotive'!L7 -> 5646.6609 | M7: =M16*'Tesla Revenue Automotive'!M7 -> 6211.327 | N7: =N16*'Tesla Revenue Automotive'!N7 -> 6708.2331 | ... Q7: =Q16*'Tesla Revenue Automotive'!Q7 -> 7836.0749
B8: Tesla Roadster 2 | C8: 0 | D8: 0 | E8: 0 | F8: 0 | G8: =G17*'Tesla Revenue Automotive'!G8 -> 0 | H8: - | I8: - | J8: =J17*'Tesla Revenue Automotive'!J8 -> 52.322024 | K8: =K17*'Tesla Revenue Automotive'!K8 -> 104.64405 | L8: =L17*'Tesla Revenue Automotive'!L8 -> 156.96607 | M8: =M17*'Tesla Revenue Automotive'!M8 -> 172.66268 | N8: =N17*'Tesla Revenue Automotive'!N8 -> 189.92895 | O8: =O17*'Tesla Revenue Automotive'!O8 -> 205.12326 | P8: =P17*'Tesla Revenue Automotive'!P8 -> 221.53313 | Q8: =Q17*'Tesla Revenue Automotive'!Q8 -> 230.39445
B9: Tesla Pickup | C9: 0 | D9: 0 | E9: 0 | F9: 0 | G9: =G18*'Tesla Revenue Automotive'!G9 -> 0 | H9: - | I9: =I18*'Tesla Revenue Automotive'!I9 -> 2.5527164 | J9: =J18*'Tesla Revenue Automotive'!J9 -> 211.35884 | K9: =K18*'Tesla Revenue Automotive'!K9 -> 435.31485 | L9: =L18*'Tesla Revenue Automotive'!L9 -> 696.50375 | M9: =M18*'Tesla Revenue Automotive'!M9 -> 766.15413 | N9: =N18*'Tesla Revenue Automotive'!N9 -> 842.76954 | O9: =O18*'Tesla Revenue Automotive'!O9 -> 910.1911 | P9: =P18*'Tesla Revenue Automotive'!P9 -> 983.00639 | Q9: =Q18*'Tesla Revenue Automotive'!Q9 -> 1022.3266
B10: Tesla Semi | C10: 0 | D10: 0 | E10: 0 | F10: 0 | G10: =G19*'Tesla Revenue Automotive'!G10 -> 0 | H10: - | I10: =I19*'Tesla Revenue Automotive'!I10 -> 9.6905781 | J10: =J19*'Tesla Revenue Automotive'!J10 -> 802.35679 | K10: =K19*'Tesla Revenue Automotive'!K10 -> 1652.5347 | L10: =L19*'Tesla Revenue Automotive'!L10 -> 2644.0556 | M10: =M19*'Tesla Revenue Automotive'!M10 -> 2908.4611 | N10: =N19*'Tesla Revenue Automotive'!N10 -> 3199.3072 | O10: =O19*'Tesla Revenue Automotive'!O10 -> 3455.2518 | P10: =P19*'Tesla Revenue Automotive'!P10 -> 3731.6719 | Q10: =Q19*'Tesla Revenue Automotive'!Q10 -> 3880.9388
B11: Total | C11: =('P&L Input'!C4+'P&L Input'!C8)/1000 -> 917.671 | D11: =('P&L Input'!D4+'P&L Input'!D8)/1000 -> 1600.685 | E11: =('P&L Input'!E4+'P&L Input'!E8)/1000 -> 2208.596 | F11: =('P&L Input'!F4+'P&L Input'!F8)/1000 -> 4340.986 | G11: =('P&L Input'!G4+'P&L Input'!G8)/1000 -> 4423 | H11: =SUM(H5:H10) -> 8071.9692 | I11: =SUM(I5:I10) -> 10325.641 | J11: =SUM(J5:J10) -> 13798.657 | K11: =SUM(K5:K10) -> 17537.917 | L11: =SUM(L5:L10) -> 20096.146 | M11: =SUM(M5:M10) -> 21448.643 | N11: =SUM(N5:N10) -> 22785.878 | O11: =SUM(O5:O10) -> 24134.923 | ... Q11: =SUM(Q5:Q10) -> 26294.468
B13: Selected case
B14: Tesla Model 3 | G14: =CHOOSE(Drivers!$C$3,'Tesla Automotive GP '!G22,'Tesla Automotive GP '!G30,'Tesla Automotive GP '!G38) -> 0.23844388 | H14: =CHOOSE(Drivers!$C$3,'Tesla Automotive GP '!H22,'Tesla Automotive GP '!H30,'Tesla Automotive GP '!H38) -> 0.23844388 | I14: =CHOOSE(Drivers!$C$3,'Tesla Automotive GP '!I22,'Tesla Automotive GP '!I30,'Tesla Automotive GP '!I38) -> 0.23844388 | J14: =CHOOSE(Drivers!$C$3,'Tesla Automotive GP '!J22,'Tesla Automotive GP '!J30,'Tesla Automotive GP '!J38) -> 0.23844388 | K14: =CHOOSE(Drivers!$C$3,'Tesla Automotive GP '!K22,'Tesla Automotive GP '!K30,'Tesla Automotive GP '!K38) -> 0.23844388 | L14: =CHOOSE(Drivers!$C$3,'Tesla Automotive GP '!L22,'Tesla Automotive GP '!L30,'Tesla Automotive GP '!L38) -> 0.23844388 | M14: =CHOOSE(Drivers!$C$3,'Tesla Automotive GP '!M22,'Tesla Automotive GP '!M30,'Tesla Automotive GP '!M38) -> 0.23844388 | N14: =CHOOSE(Drivers!$C$3,'Tesla Automotive GP '!N22,'Tesla Automotive GP '!N30,'Tesla Automotive GP '!N38) -> 0.23844388 | ... Q14: =CHOOSE(Drivers!$C$3,'Tesla Automotive GP '!Q22,'Tesla Automotive GP '!Q30,'Tesla Automotive GP '!Q38) -> 0.23844388
B15: Tesla Model S and X | G15: =CHOOSE(Drivers!$C$3,'Tesla Automotive GP '!G23,'Tesla Automotive GP '!G31,'Tesla Automotive GP '!G39) -> 0.23844388 | H15: =CHOOSE(Drivers!$C$3,'Tesla Automotive GP '!H23,'Tesla Automotive GP '!H31,'Tesla Automotive GP '!H39) -> 0.23844388 | I15: =CHOOSE(Drivers!$C$3,'Tesla Automotive GP '!I23,'Tesla Automotive GP '!I31,'Tesla Automotive GP '!I39) -> 0.23844388 | J15: =CHOOSE(Drivers!$C$3,'Tesla Automotive GP '!J23,'Tesla Automotive GP '!J31,'Tesla Automotive GP '!J39) -> 0.23844388 | K15: =CHOOSE(Drivers!$C$3,'Tesla Automotive GP '!K23,'Tesla Automotive GP '!K31,'Tesla Automotive GP '!K39) -> 0.23844388 | L15: =CHOOSE(Drivers!$C$3,'Tesla Automotive GP '!L23,'Tesla Automotive GP '!L31,'Tesla Automotive GP '!L39) -> 0.23844388 | M15: =CHOOSE(Drivers!$C$3,'Tesla Automotive GP '!M23,'Tesla Automotive GP '!M31,'Tesla Automotive GP '!M39) -> 0.23844388 | N15: =CHOOSE(Drivers!$C$3,'Tesla Automotive GP '!N23,'Tesla Automotive GP '!N31,'Tesla Automotive GP '!N39) -> 0.23844388 | ... Q15: =CHOOSE(Drivers!$C$3,'Tesla Automotive GP '!Q23,'Tesla Automotive GP '!Q31,'Tesla Automotive GP '!Q39) -> 0.23844388
B16: Tesla Model Y | G16: =CHOOSE(Drivers!$C$3,'Tesla Automotive GP '!G24,'Tesla Automotive GP '!G32,'Tesla Automotive GP '!G40) -> 0.17141528 | H16: =CHOOSE(Drivers!$C$3,'Tesla Automotive GP '!H24,'Tesla Automotive GP '!H32,'Tesla Automotive GP '!H40) -> 0.17141528 | I16: =CHOOSE(Drivers!$C$3,'Tesla Automotive GP '!I24,'Tesla Automotive GP '!I32,'Tesla Automotive GP '!I40) -> 0.17141528 | J16: =CHOOSE(Drivers!$C$3,'Tesla Automotive GP '!J24,'Tesla Automotive GP '!J32,'Tesla Automotive GP '!J40) -> 0.17141528 | K16: =CHOOSE(Drivers!$C$3,'Tesla Automotive GP '!K24,'Tesla Automotive GP '!K32,'Tesla Automotive GP '!K40) -> 0.17141528 | L16: =CHOOSE(Drivers!$C$3,'Tesla Automotive GP '!L24,'Tesla Automotive GP '!L32,'Tesla Automotive GP '!L40) -> 0.17141528 | M16: =CHOOSE(Drivers!$C$3,'Tesla Automotive GP '!M24,'Tesla Automotive GP '!M32,'Tesla Automotive GP '!M40) -> 0.17141528 | N16: =CHOOSE(Drivers!$C$3,'Tesla Automotive GP '!N24,'Tesla Automotive GP '!N32,'Tesla Automotive GP '!N40) -> 0.17141528 | ... Q16: =CHOOSE(Drivers!$C$3,'Tesla Automotive GP '!Q24,'Tesla Automotive GP '!Q32,'Tesla Automotive GP '!Q40) -> 0.17141528
B17: Tesla Roadster 2 | G17: =CHOOSE(Drivers!$C$3,'Tesla Automotive GP '!G25,'Tesla Automotive GP '!G33,'Tesla Automotive GP '!G41) -> 0.45596535 | H17: =CHOOSE(Drivers!$C$3,'Tesla Automotive GP '!H25,'Tesla Automotive GP '!H33,'Tesla Automotive GP '!H41) -> 0.45596535 | I17: =CHOOSE(Drivers!$C$3,'Tesla Automotive GP '!I25,'Tesla Automotive GP '!I33,'Tesla Automotive GP '!I41) -> 0.45596535 | J17: =CHOOSE(Drivers!$C$3,'Tesla Automotive GP '!J25,'Tesla Automotive GP '!J33,'Tesla Automotive GP '!J41) -> 0.45596535 | K17: =CHOOSE(Drivers!$C$3,'Tesla Automotive GP '!K25,'Tesla Automotive GP '!K33,'Tesla Automotive GP '!K41) -> 0.45596535 | L17: =CHOOSE(Drivers!$C$3,'Tesla Automotive GP '!L25,'Tesla Automotive GP '!L33,'Tesla Automotive GP '!L41) -> 0.45596535 | M17: =CHOOSE(Drivers!$C$3,'Tesla Automotive GP '!M25,'Tesla Automotive GP '!M33,'Tesla Automotive GP '!M41) -> 0.45596535 | N17: =CHOOSE(Drivers!$C$3,'Tesla Automotive GP '!N25,'Tesla Automotive GP '!N33,'Tesla Automotive GP '!N41) -> 0.45596535 | ... Q17: =CHOOSE(Drivers!$C$3,'Tesla Automotive GP '!Q25,'Tesla Automotive GP '!Q33,'Tesla Automotive GP '!Q41) -> 0.45596535
B18: Tesla Pickup | G18: =CHOOSE(Drivers!$C$3,'Tesla Automotive GP '!G26,'Tesla Automotive GP '!G34,'Tesla Automotive GP '!G42) -> 0.17141528 | H18: =CHOOSE(Drivers!$C$3,'Tesla Automotive GP '!H26,'Tesla Automotive GP '!H34,'Tesla Automotive GP '!H42) -> 0.17141528 | I18: =CHOOSE(Drivers!$C$3,'Tesla Automotive GP '!I26,'Tesla Automotive GP '!I34,'Tesla Automotive GP '!I42) -> 0.17141528 | J18: =CHOOSE(Drivers!$C$3,'Tesla Automotive GP '!J26,'Tesla Automotive GP '!J34,'Tesla Automotive GP '!J42) -> 0.17141528 | K18: =CHOOSE(Drivers!$C$3,'Tesla Automotive GP '!K26,'Tesla Automotive GP '!K34,'Tesla Automotive GP '!K42) -> 0.17141528 | L18: =CHOOSE(Drivers!$C$3,'Tesla Automotive GP '!L26,'Tesla Automotive GP '!L34,'Tesla Automotive GP '!L42) -> 0.17141528 | M18: =CHOOSE(Drivers!$C$3,'Tesla Automotive GP '!M26,'Tesla Automotive GP '!M34,'Tesla Automotive GP '!M42) -> 0.17141528 | N18: =CHOOSE(Drivers!$C$3,'Tesla Automotive GP '!N26,'Tesla Automotive GP '!N34,'Tesla Automotive GP '!N42) -> 0.17141528 | ... Q18: =CHOOSE(Drivers!$C$3,'Tesla Automotive GP '!Q26,'Tesla Automotive GP '!Q34,'Tesla Automotive GP '!Q42) -> 0.17141528
B19: Tesla Semi | G19: =CHOOSE(Drivers!$C$3,'Tesla Automotive GP '!G27,'Tesla Automotive GP '!G35,'Tesla Automotive GP '!G43) -> 0.21715581 | H19: =CHOOSE(Drivers!$C$3,'Tesla Automotive GP '!H27,'Tesla Automotive GP '!H35,'Tesla Automotive GP '!H43) -> 0.21715581 | I19: =CHOOSE(Drivers!$C$3,'Tesla Automotive GP '!I27,'Tesla Automotive GP '!I35,'Tesla Automotive GP '!I43) -> 0.21715581 | J19: =CHOOSE(Drivers!$C$3,'Tesla Automotive GP '!J27,'Tesla Automotive GP '!J35,'Tesla Automotive GP '!J43) -> 0.21715581 | K19: =CHOOSE(Drivers!$C$3,'Tesla Automotive GP '!K27,'Tesla Automotive GP '!K35,'Tesla Automotive GP '!K43) -> 0.21715581 | L19: =CHOOSE(Drivers!$C$3,'Tesla Automotive GP '!L27,'Tesla Automotive GP '!L35,'Tesla Automotive GP '!L43) -> 0.21715581 | M19: =CHOOSE(Drivers!$C$3,'Tesla Automotive GP '!M27,'Tesla Automotive GP '!M35,'Tesla Automotive GP '!M43) -> 0.21715581 | N19: =CHOOSE(Drivers!$C$3,'Tesla Automotive GP '!N27,'Tesla Automotive GP '!N35,'Tesla Automotive GP '!N43) -> 0.21715581 | ... Q19: =CHOOSE(Drivers!$C$3,'Tesla Automotive GP '!Q27,'Tesla Automotive GP '!Q35,'Tesla Automotive GP '!Q43) -> 0.21715581
B21: Best case
B22: Tesla Model 3 | G22: =G30+1.5% -> 0.23844388 | H22: =H30+1.5% -> 0.23844388 | I22: =I30+1.5% -> 0.23844388 | J22: =J30+1.5% -> 0.23844388 | K22: =K30+1.5% -> 0.23844388 | L22: =L30+1.5% -> 0.23844388 | M22: =M30+1.5% -> 0.23844388 | N22: =N30+1.5% -> 0.23844388 | ... Q22: =Q30+1.5% -> 0.23844388
B23: Tesla Model S and X | G23: =G31+1.5% -> 0.23844388 | H23: =H31+1.5% -> 0.23844388 | I23: =I31+1.5% -> 0.23844388 | J23: =J31+1.5% -> 0.23844388 | K23: =K31+1.5% -> 0.23844388 | L23: =L31+1.5% -> 0.23844388 | M23: =M31+1.5% -> 0.23844388 | N23: =N31+1.5% -> 0.23844388 | ... Q23: =Q31+1.5% -> 0.23844388
B24: Tesla Model Y | G24: =G32+1.5% -> 0.17141528 | H24: =H32+1.5% -> 0.17141528 | I24: =I32+1.5% -> 0.17141528 | J24: =J32+1.5% -> 0.17141528 | K24: =K32+1.5% -> 0.17141528 | L24: =L32+1.5% -> 0.17141528 | M24: =M32+1.5% -> 0.17141528 | N24: =N32+1.5% -> 0.17141528 | ... Q24: =Q32+1.5% -> 0.17141528
B25: Tesla Roadster 2 | G25: =G33+1.5% -> 0.45596535 | H25: =H33+1.5% -> 0.45596535 | I25: =I33+1.5% -> 0.45596535 | J25: =J33+1.5% -> 0.45596535 | K25: =K33+1.5% -> 0.45596535 | L25: =L33+1.5% -> 0.45596535 | M25: =M33+1.5% -> 0.45596535 | N25: =N33+1.5% -> 0.45596535 | ... Q25: =Q33+1.5% -> 0.45596535
B26: Tesla Pickup | G26: =G34+1.5% -> 0.17141528 | H26: =H34+1.5% -> 0.17141528 | I26: =I34+1.5% -> 0.17141528 | J26: =J34+1.5% -> 0.17141528 | K26: =K34+1.5% -> 0.17141528 | L26: =L34+1.5% -> 0.17141528 | M26: =M34+1.5% -> 0.17141528 | N26: =N34+1.5% -> 0.17141528 | ... Q26: =Q34+1.5% -> 0.17141528
B27: Tesla Semi | G27: =G35+1.5% -> 0.21715581 | H27: =H35+1.5% -> 0.21715581 | I27: =I35+1.5% -> 0.21715581 | J27: =J35+1.5% -> 0.21715581 | K27: =K35+1.5% -> 0.21715581 | L27: =L35+1.5% -> 0.21715581 | M27: =M35+1.5% -> 0.21715581 | N27: =N35+1.5% -> 0.21715581 | ... Q27: =Q35+1.5% -> 0.21715581
B29: Base case
B30: Tesla Model 3 | G30: ='Tesla Automotivo GP% '!$H6 -> 0.22344388 | H30: ='Tesla Automotivo GP% '!$H6 -> 0.22344388 | I30: ='Tesla Automotivo GP% '!$H6 -> 0.22344388 | J30: ='Tesla Automotivo GP% '!$H6 -> 0.22344388 | K30: ='Tesla Automotivo GP% '!$H6 -> 0.22344388 | L30: ='Tesla Automotivo GP% '!$H6 -> 0.22344388 | M30: ='Tesla Automotivo GP% '!$H6 -> 0.22344388 | N30: ='Tesla Automotivo GP% '!$H6 -> 0.22344388 | ... Q30: ='Tesla Automotivo GP% '!$H6 -> 0.22344388
B31: Tesla Model S and X | G31: ='Tesla Automotivo GP% '!$H7 -> 0.22344388 | H31: ='Tesla Automotivo GP% '!$H7 -> 0.22344388 | I31: ='Tesla Automotivo GP% '!$H7 -> 0.22344388 | J31: ='Tesla Automotivo GP% '!$H7 -> 0.22344388 | K31: ='Tesla Automotivo GP% '!$H7 -> 0.22344388 | L31: ='Tesla Automotivo GP% '!$H7 -> 0.22344388 | M31: ='Tesla Automotivo GP% '!$H7 -> 0.22344388 | N31: ='Tesla Automotivo GP% '!$H7 -> 0.22344388 | ... Q31: ='Tesla Automotivo GP% '!$H7 -> 0.22344388
B32: Tesla Model Y | G32: ='Tesla Automotivo GP% '!$H8 -> 0.15641528 | H32: ='Tesla Automotivo GP% '!$H8 -> 0.15641528 | I32: ='Tesla Automotivo GP% '!$H8 -> 0.15641528 | J32: ='Tesla Automotivo GP% '!$H8 -> 0.15641528 | K32: ='Tesla Automotivo GP% '!$H8 -> 0.15641528 | L32: ='Tesla Automotivo GP% '!$H8 -> 0.15641528 | M32: ='Tesla Automotivo GP% '!$H8 -> 0.15641528 | N32: ='Tesla Automotivo GP% '!$H8 -> 0.15641528 | ... Q32: ='Tesla Automotivo GP% '!$H8 -> 0.15641528
B33: Tesla Roadster 2 | G33: ='Tesla Automotivo GP% '!$H9 -> 0.44096535 | H33: ='Tesla Automotivo GP% '!$H9 -> 0.44096535 | I33: ='Tesla Automotivo GP% '!$H9 -> 0.44096535 | J33: ='Tesla Automotivo GP% '!$H9 -> 0.44096535 | K33: ='Tesla Automotivo GP% '!$H9 -> 0.44096535 | L33: ='Tesla Automotivo GP% '!$H9 -> 0.44096535 | M33: ='Tesla Automotivo GP% '!$H9 -> 0.44096535 | N33: ='Tesla Automotivo GP% '!$H9 -> 0.44096535 | ... Q33: ='Tesla Automotivo GP% '!$H9 -> 0.44096535
B34: Tesla Pickup | G34: ='Tesla Automotivo GP% '!$H10 -> 0.15641528 | H34: ='Tesla Automotivo GP% '!$H10 -> 0.15641528 | I34: ='Tesla Automotivo GP% '!$H10 -> 0.15641528 | J34: ='Tesla Automotivo GP% '!$H10 -> 0.15641528 | K34: ='Tesla Automotivo GP% '!$H10 -> 0.15641528 | L34: ='Tesla Automotivo GP% '!$H10 -> 0.15641528 | M34: ='Tesla Automotivo GP% '!$H10 -> 0.15641528 | N34: ='Tesla Automotivo GP% '!$H10 -> 0.15641528 | ... Q34: ='Tesla Automotivo GP% '!$H10 -> 0.15641528
B35: Tesla Semi | G35: ='Tesla Automotivo GP% '!$H11 -> 0.20215581 | H35: ='Tesla Automotivo GP% '!$H11 -> 0.20215581 | I35: ='Tesla Automotivo GP% '!$H11 -> 0.20215581 | J35: ='Tesla Automotivo GP% '!$H11 -> 0.20215581 | K35: ='Tesla Automotivo GP% '!$H11 -> 0.20215581 | L35: ='Tesla Automotivo GP% '!$H11 -> 0.20215581 | M35: ='Tesla Automotivo GP% '!$H11 -> 0.20215581 | N35: ='Tesla Automotivo GP% '!$H11 -> 0.20215581 | ... Q35: ='Tesla Automotivo GP% '!$H11 -> 0.20215581
B37: Worst case
B38: Tesla Model 3 | G38: =G30-1.5% -> 0.20844388 | H38: =H30-1.5% -> 0.20844388 | I38: =I30-1.5% -> 0.20844388 | J38: =J30-1.5% -> 0.20844388 | K38: =K30-1.5% -> 0.20844388 | L38: =L30-1.5% -> 0.20844388 | M38: =M30-1.5% -> 0.20844388 | N38: =N30-1.5% -> 0.20844388 | ... Q38: =Q30-1.5% -> 0.20844388
B39: Tesla Model S and X | G39: =G31-1.5% -> 0.20844388 | H39: =H31-1.5% -> 0.20844388 | I39: =I31-1.5% -> 0.20844388 | J39: =J31-1.5% -> 0.20844388 | K39: =K31-1.5% -> 0.20844388 | L39: =L31-1.5% -> 0.20844388 | M39: =M31-1.5% -> 0.20844388 | N39: =N31-1.5% -> 0.20844388 | ... Q39: =Q31-1.5% -> 0.20844388
B40: Tesla Model Y | G40: =G32-1.5% -> 0.14141528 | H40: =H32-1.5% -> 0.14141528 | I40: =I32-1.5% -> 0.14141528 | J40: =J32-1.5% -> 0.14141528 | K40: =K32-1.5% -> 0.14141528 | L40: =L32-1.5% -> 0.14141528 | M40: =M32-1.5% -> 0.14141528 | N40: =N32-1.5% -> 0.14141528 | ... Q40: =Q32-1.5% -> 0.14141528
B41: Tesla Roadster 2 | G41: =G33-1.5% -> 0.42596535 | H41: =H33-1.5% -> 0.42596535 | I41: =I33-1.5% -> 0.42596535 | J41: =J33-1.5% -> 0.42596535 | K41: =K33-1.5% -> 0.42596535 | L41: =L33-1.5% -> 0.42596535 | M41: =M33-1.5% -> 0.42596535 | N41: =N33-1.5% -> 0.42596535 | ... Q41: =Q33-1.5% -> 0.42596535
B42: Tesla Pickup | G42: =G34-1.5% -> 0.14141528 | H42: =H34-1.5% -> 0.14141528 | I42: =I34-1.5% -> 0.14141528 | J42: =J34-1.5% -> 0.14141528 | K42: =K34-1.5% -> 0.14141528 | L42: =L34-1.5% -> 0.14141528 | M42: =M34-1.5% -> 0.14141528 | N42: =N34-1.5% -> 0.14141528 | ... Q42: =Q34-1.5% -> 0.14141528
B43: Tesla Semi | G43: =G35-1.5% -> 0.18715581 | H43: =H35-1.5% -> 0.18715581 | I43: =I35-1.5% -> 0.18715581 | J43: =J35-1.5% -> 0.18715581 | K43: =K35-1.5% -> 0.18715581 | L43: =L35-1.5% -> 0.18715581 | M43: =M35-1.5% -> 0.18715581 | N43: =N35-1.5% -> 0.18715581 | ... Q43: =Q35-1.5% -> 0.18715581

Sheet Tesla Cost of sales Automotive
B1: Tesla Cost of sales Automotive
B3: Tesla Cost of sales (in mln $)
B4: Vehicle | C4: 2015 Act | D4: 2016 Act | E4: 2017 Act | F4: 2018 Act | G4: 2019 Act | H4: 2020 Fcst | I4: 2021 Fcst | J4: 2022 Fcst | K4: 2023 Fcst | L4: 2024 Fcst | M4: 2025 Fcst | N4: 2026 Fcst | O4: 2027 Fcst | P4: 2028 Fcst | Q4: 2029 Fcst
B5: Tesla Model 3 | C5: n.a. | D5: n.a. | E5: n.a. | F5: n.a. | G5: n.a. | H5: =-('Tesla Revenue Automotive'!H5-'Tesla Automotive GP '!H5) -> -20247.597 | I5: =-('Tesla Revenue Automotive'!I5-'Tesla Automotive GP '!I5) -> -22272.356 | J5: =-('Tesla Revenue Automotive'!J5-'Tesla Automotive GP '!J5) -> -24499.592 | K5: =-('Tesla Revenue Automotive'!K5-'Tesla Automotive GP '!K5) -> -26459.559 | L5: =-('Tesla Revenue Automotive'!L5-'Tesla Automotive GP '!L5) -> -28576.324 | M5: =-('Tesla Revenue Automotive'!M5-'Tesla Automotive GP '!M5) -> -29719.377 | N5: =-('Tesla Revenue Automotive'!N5-'Tesla Automotive GP '!N5) -> -30908.152 | O5: =-('Tesla Revenue Automotive'!O5-'Tesla Automotive GP '!O5) -> -32144.478 | ... Q5: =-('Tesla Revenue Automotive'!Q5-'Tesla Automotive GP '!Q5) -> -34767.468
B6: Tesla Model S and X | C6: n.a. | D6: n.a. | E6: n.a. | F6: n.a. | G6: n.a. | H6: =-('Tesla Revenue Automotive'!H6-'Tesla Automotive GP '!H6) -> -5473.0451 | I6: =-('Tesla Revenue Automotive'!I6-'Tesla Automotive GP '!I6) -> -5691.9669 | J6: =-('Tesla Revenue Automotive'!J6-'Tesla Automotive GP '!J6) -> -5919.6456 | K6: =-('Tesla Revenue Automotive'!K6-'Tesla Automotive GP '!K6) -> -6156.4314 | L6: =-('Tesla Revenue Automotive'!L6-'Tesla Automotive GP '!L6) -> -6402.6887 | M6: =-('Tesla Revenue Automotive'!M6-'Tesla Automotive GP '!M6) -> -6658.7963 | N6: =-('Tesla Revenue Automotive'!N6-'Tesla Automotive GP '!N6) -> -6925.1481 | O6: =-('Tesla Revenue Automotive'!O6-'Tesla Automotive GP '!O6) -> -7202.154 | ... Q6: =-('Tesla Revenue Automotive'!Q6-'Tesla Automotive GP '!Q6) -> -7789.8498
B7: Tesla Model Y | C7: 0 | D7: 0 | E7: 0 | F7: 0 | G7: =-('Tesla Revenue Automotive'!G7-'Tesla Automotive GP '!G7) -> 0 | H7: =-('Tesla Revenue Automotive'!H7-'Tesla Automotive GP '!H7) -> -90.94221 | I7: =-('Tesla Revenue Automotive'!I7-'Tesla Automotive GP '!I7) -> -7529.7985 | J7: =-('Tesla Revenue Automotive'!J7-'Tesla Automotive GP '!J7) -> -15508.379 | K7: =-('Tesla Revenue Automotive'!K7-'Tesla Automotive GP '!K7) -> -24813.407 | L7: =-('Tesla Revenue Automotive'!L7-'Tesla Automotive GP '!L7) -> -27294.747 | M7: =-('Tesla Revenue Automotive'!M7-'Tesla Automotive GP '!M7) -> -30024.222 | N7: =-('Tesla Revenue Automotive'!N7-'Tesla Automotive GP '!N7) -> -32426.16 | ... Q7: =-('Tesla Revenue Automotive'!Q7-'Tesla Automotive GP '!Q7) -> -37877.905
B8: Tesla Roadster 2 | C8: 0 | D8: 0 | E8: 0 | F8: 0 | G8: =-('Tesla Revenue Automotive'!G8-'Tesla Automotive GP '!G8) -> 0 | H8: - | I8: - | J8: =-('Tesla Revenue Automotive'!J8-'Tesla Automotive GP '!J8) -> -62.427976 | K8: =-('Tesla Revenue Automotive'!K8-'Tesla Automotive GP '!K8) -> -124.85595 | L8: =-('Tesla Revenue Automotive'!L8-'Tesla Automotive GP '!L8) -> -187.28393 | M8: =-('Tesla Revenue Automotive'!M8-'Tesla Automotive GP '!M8) -> -206.01232 | N8: =-('Tesla Revenue Automotive'!N8-'Tesla Automotive GP '!N8) -> -226.61355 | O8: =-('Tesla Revenue Automotive'!O8-'Tesla Automotive GP '!O8) -> -244.74264 | P8: =-('Tesla Revenue Automotive'!P8-'Tesla Automotive GP '!P8) -> -264.32205 | Q8: =-('Tesla Revenue Automotive'!Q8-'Tesla Automotive GP '!Q8) -> -274.89493
B9: Tesla Pickup | C9: 0 | D9: 0 | E9: 0 | F9: 0 | G9: =-('Tesla Revenue Automotive'!G9-'Tesla Automotive GP '!G9) -> 0 | H9: - | I9: =-('Tesla Revenue Automotive'!I9-'Tesla Automotive GP '!I9) -> -12.339284 | J9: =-('Tesla Revenue Automotive'!J9-'Tesla Automotive GP '!J9) -> -1021.6633 | K9: =-('Tesla Revenue Automotive'!K9-'Tesla Automotive GP '!K9) -> -2104.2186 | L9: =-('Tesla Revenue Automotive'!L9-'Tesla Automotive GP '!L9) -> -3366.7497 | M9: =-('Tesla Revenue Automotive'!M9-'Tesla Automotive GP '!M9) -> -3703.4247 | N9: =-('Tesla Revenue Automotive'!N9-'Tesla Automotive GP '!N9) -> -4073.7672 | O9: =-('Tesla Revenue Automotive'!O9-'Tesla Automotive GP '!O9) -> -4399.6686 | P9: =-('Tesla Revenue Automotive'!P9-'Tesla Automotive GP '!P9) -> -4751.642 | Q9: =-('Tesla Revenue Automotive'!Q9-'Tesla Automotive GP '!Q9) -> -4941.7077
B10: Tesla Semi | C10: 0 | D10: 0 | E10: 0 | F10: 0 | G10: =-('Tesla Revenue Automotive'!G10-'Tesla Automotive GP '!G10) -> 0 | H10: - | I10: =-('Tesla Revenue Automotive'!I10-'Tesla Automotive GP '!I10) -> -34.934422 | J10: =-('Tesla Revenue Automotive'!J10-'Tesla Automotive GP '!J10) -> -2892.487 | K10: =-('Tesla Revenue Automotive'!K10-'Tesla Automotive GP '!K10) -> -5957.3686 | L10: =-('Tesla Revenue Automotive'!L10-'Tesla Automotive GP '!L10) -> -9531.7897 | M10: =-('Tesla Revenue Automotive'!M10-'Tesla Automotive GP '!M10) -> -10484.969 | N10: =-('Tesla Revenue Automotive'!N10-'Tesla Automotive GP '!N10) -> -11533.466 | O10: =-('Tesla Revenue Automotive'!O10-'Tesla Automotive GP '!O10) -> -12456.143 | P10: =-('Tesla Revenue Automotive'!P10-'Tesla Automotive GP '!P10) -> -13452.634 | Q10: =-('Tesla Revenue Automotive'!Q10-'Tesla Automotive GP '!Q10) -> -13990.74
B11: Total | C11: ='P&L Input'!C8/1000 -> -2823.302 | D11: ='P&L Input'!D8/1000 -> -4750.081 | E11: ='P&L Input'!E8/1000 -> -7432.704 | F11: ='P&L Input'!F8/1000 -> -14173.997 | G11: ='P&L Input'!G8/1000 -> -16398 | H11: =SUM(H5:H10) -> -25811.584 | I11: =SUM(I5:I10) -> -35541.395 | J11: =SUM(J5:J10) -> -49904.195 | K11: =SUM(K5:K10) -> -65615.841 | L11: =SUM(L5:L10) -> -75359.584 | M11: =SUM(M5:M10) -> -80796.801 | N11: =SUM(N5:N10) -> -86093.306 | O11: =SUM(O5:O10) -> -91467.439 | ... Q11: =SUM(Q5:Q10) -> -99642.565

Sheet Revenue and GP Automative Chart
B1: Revenue and Gross Profit automotive
B3: Vehicle | C3: 2016 Act | D3: 2017 Act | E3: 2018 Act | F3: 2019 Act | G3: 2020 Fcst | H3: 2021 Fcst | I3: 2022 Fcst | J3: 2023 Fcst | K3: 2024 Fcst | L3: 2025 Fcst | M3: 2026 Fcst | N3: 2027 Fcst | O3: 2028 Fcst | P3: 2029 Fcst
B4: Revenue automotive | C4: ='Tesla Revenue Automotive'!D11 -> 6350.766 | D4: ='Tesla Revenue Automotive'!E11 -> 9641.3 | E4: ='Tesla Revenue Automotive'!F11 -> 18514.983 | F4: ='Tesla Revenue Automotive'!G11 -> 20821 | G4: ='Tesla Revenue Automotive'!H11 -> 33883.553 | H4: ='Tesla Revenue Automotive'!I11 -> 45867.036 | I4: ='Tesla Revenue Automotive'!J11 -> 63702.852 | J4: ='Tesla Revenue Automotive'!K11 -> 83153.757 | ... P4: ='Tesla Revenue Automotive'!Q11 -> 125937.03
B5: Gross Profit automotive | C5: ='Tesla Automotive GP '!D11 -> 1600.685 | D5: ='Tesla Automotive GP '!E11 -> 2208.596 | E5: ='Tesla Automotive GP '!F11 -> 4340.986 | F5: ='Tesla Automotive GP '!G11 -> 4423 | G5: ='Tesla Automotive GP '!H11 -> 8071.9692 | H5: ='Tesla Automotive GP '!I11 -> 10325.641 | I5: ='Tesla Automotive GP '!J11 -> 13798.657 | J5: ='Tesla Automotive GP '!K11 -> 17537.917 | ... P5: ='Tesla Automotive GP '!Q11 -> 26294.468
B6: GP% | C6: =C5/C4 -> 0.25204597 | D6: =D5/D4 -> 0.22907658 | E6: =E5/E4 -> 0.23445801 | F6: =F5/F4 -> 0.21242976 | G6: =G5/G4 -> 0.23822676 | H6: =H5/H4 -> 0.22512117 | I6: =I5/I4 -> 0.21660973 | J6: =J5/J4 -> 0.21090949 | ... P6: =P5/P4 -> 0.20879059

Sheet 2.Tesla Energy,Services & Other
A13: 2. Tesla Energy, Services & Other

Sheet Revenue Energy, service & Other
B1: Tesla Revenue Energy, Serivice & Other
B3: Tesla Revenue Energy & Other (in mln $)
B4: ($ in million) | C4: 2015 Act | D4: 2016 Act | E4: 2017 Act | F4: 2018 Act | G4: 2019 Act | H4: 2020 Fcst | I4: 2021 Fcst | J4: 2022 Fcst | K4: 2023 Fcst | L4: 2024 Fcst | M4: 2025 Fcst | N4: 2026 Fcst | O4: 2027 Fcst | P4: 2028 Fcst | Q4: 2029 Fcst
B5: Energy generation and storage | C5: ='P&L Input'!C5/1000 -> 14.477 | D5: ='P&L Input'!D5/1000 -> 181.394 | E5: ='P&L Input'!E5/1000 -> 1116.266 | F5: ='P&L Input'!F5/1000 -> 1555.244 | G5: ='P&L Input'!G5/1000 -> 1531 | H5: n.a. | I5: n.a. | J5: n.a. | K5: n.a. | L5: n.a. | M5: n.a. | N5: n.a. | O5: n.a. | P5: n.a. | Q5: n.a.
B6: Services and other | C6: ='P&L Input'!C6/1000 -> 290.575 | D6: ='P&L Input'!D6/1000 -> 467.972 | E6: ='P&L Input'!E6/1000 -> 1001.185 | F6: ='P&L Input'!F6/1000 -> 1391.041 | G6: ='P&L Input'!G6/1000 -> 2226 | H6: n.a. | I6: n.a. | J6: n.a. | K6: n.a. | L6: n.a. | M6: n.a. | N6: n.a. | O6: n.a. | P6: n.a. | Q6: n.a.
B7: Total Energy and Other | C7: =SUM(C5:C6) -> 305.052 | D7: =SUM(D5:D6) -> 649.366 | E7: =SUM(E5:E6) -> 2117.451 | F7: =SUM(F5:F6) -> 2946.285 | G7: =SUM(G5:G6) -> 3757 | H7: =G7*(1+H10) -> 4508.4 | I7: =H7*(1+I10) -> 5139.576 | J7: =I7*(1+J10) -> 5653.5336 | K7: =J7*(1+K10) -> 6105.8163 | L7: =K7*(1+L10) -> 6594.2816 | M7: =L7*(1+M10) -> 7121.8241 | N7: =M7*(1+N10) -> 7691.57 | O7: =N7*(1+O10) -> 8306.8957 | ... Q7: =P7*(1+Q10) -> 9689.1631
B9: Selected case
B10: Total Energy and Other | H10: =CHOOSE(Drivers!$C$3,H14,H17,H20) -> 0.2 | I10: =CHOOSE(Drivers!$C$3,I14,I17,I20) -> 0.14 | J10: =CHOOSE(Drivers!$C$3,J14,J17,J20) -> 0.1 | K10: =CHOOSE(Drivers!$C$3,K14,K17,K20) -> 0.08 | L10: =CHOOSE(Drivers!$C$3,L14,L17,L20) -> 0.08 | M10: =CHOOSE(Drivers!$C$3,M14,M17,M20) -> 0.08 | N10: =CHOOSE(Drivers!$C$3,N14,N17,N20) -> 0.08 | O10: =CHOOSE(Drivers!$C$3,O14,O17,O20) -> 0.08 | ... Q10: =CHOOSE(Drivers!$C$3,Q14,Q17,Q20) -> 0.08
B12: Y-o-Y %
B13: Best case
B14: Total Energy and Other | H14: =H17+Drivers!$C$13 -> 0.2 | I14: =I17+Drivers!$C$13 -> 0.14 | J14: =J17+Drivers!$C$13 -> 0.1 | K14: =K17+Drivers!$C$13 -> 0.08 | L14: =L17+Drivers!$C$13 -> 0.08 | M14: =M17+Drivers!$C$13 -> 0.08 | N14: =N17+Drivers!$C$13 -> 0.08 | O14: =O17+Drivers!$C$13 -> 0.08 | ... Q14: =Q17+Drivers!$C$13 -> 0.08
B16: Base case
B17: Total Energy and Other | D17: =D7/C7-1 -> 1.1287059 | E17: =E7/D7-1 -> 2.2607975 | F17: =F7/E7-1 -> 0.39143007 | G17: =G7/F7-1 -> 0.27516517 | H17: 0.18 | I17: 0.12 | J17: 0.08 | K17: 0.06 | L17: 0.06 | M17: 0.06 | N17: 0.06 | O17: 0.06 | P17: 0.06 | Q17: 0.06
B19: Worst case
B20: Total Energy and Other | H20: =H17-Drivers!$C$13 -> 0.16 | I20: =I17-Drivers!$C$13 -> 0.1 | J20: =J17-Drivers!$C$13 -> 0.06 | K20: =K17-Drivers!$C$13 -> 0.04 | L20: =L17-Drivers!$C$13 -> 0.04 | M20: =M17-Drivers!$C$13 -> 0.04 | N20: =N17-Drivers!$C$13 -> 0.04 | O20: =O17-Drivers!$C$13 -> 0.04 | ... Q20: =Q17-Drivers!$C$13 -> 0.04

Sheet Energy, services & Other GP
B1: Tesla Energy, Sevices & Other Gross Profit
B3: Tesla GP% Energy and Other (in mln $)
B4: ($ in million) | C4: 2015 Act | D4: 2016 Act | E4: 2017 Act | F4: 2018 Act | G4: 2019 Act | H4: 2019 Fcst | I4: 2021 Fcst | J4: 2022 Fcst | K4: 2023 Fcst | L4: 2024 Fcst | M4: 2025 Fcst | N4: 2025 Fcst | O4: 2027 Fcst | P4: 2028 Fcst | Q4: 2029 Fcst
B5: Energy generation and storage | C5: =('P&L Input'!C5+'P&L Input'!C9)/1000 -> 2.19 | D5: =('P&L Input'!D5+'P&L Input'!D9)/1000 -> 3.062 | E5: =('P&L Input'!E5+'P&L Input'!E9)/1000 -> 241.728 | F5: =('P&L Input'!F5+'P&L Input'!F9)/1000 -> 190.348 | G5: =('P&L Input'!G5+'P&L Input'!G9)/1000 -> 190 | H5: n.a. | I5: n.a. | J5: n.a. | K5: n.a. | L5: n.a. | M5: n.a. | N5: n.a. | O5: n.a. | P5: n.a. | Q5: n.a.
B6: Services and other | C6: =('P&L Input'!C6+'P&L Input'!C10)/1000 -> 3.642 | D6: =('P&L Input'!D6+'P&L Input'!D10)/1000 -> -4.49 | E6: =('P&L Input'!E6+'P&L Input'!E10)/1000 -> -227.837 | F6: =('P&L Input'!F6+'P&L Input'!F10)/1000 -> -489.313 | G6: =('P&L Input'!G6+'P&L Input'!G10)/1000 -> -544 | H6: n.a. | I6: n.a. | J6: n.a. | K6: n.a. | L6: n.a. | M6: n.a. | N6: n.a. | O6: n.a. | P6: n.a. | Q6: n.a.
B7: Total Energy and Other | C7: =SUM(C5:C6) -> 5.832 | D7: =SUM(D5:D6) -> -1.428 | E7: =SUM(E5:E6) -> 13.891 | F7: =SUM(F5:F6) -> -298.965 | G7: =SUM(G5:G6) -> -354 | H7: ='Revenue Energy, service & Other'!H7*'Energy, services & Other GP'!H11 -> 90.168 | I7: ='Revenue Energy, service & Other'!I7*'Energy, services & Other GP'!I11 -> 102.79152 | J7: ='Revenue Energy, service & Other'!J7*'Energy, services & Other GP'!J11 -> 113.07067 | K7: ='Revenue Energy, service & Other'!K7*'Energy, services & Other GP'!K11 -> 122.11633 | L7: ='Revenue Energy, service & Other'!L7*'Energy, services & Other GP'!L11 -> 131.88563 | M7: ='Revenue Energy, service & Other'!M7*'Energy, services & Other GP'!M11 -> 142.43648 | N7: ='Revenue Energy, service & Other'!N7*'Energy, services & Other GP'!N11 -> 153.8314 | O7: ='Revenue Energy, service & Other'!O7*'Energy, services & Other GP'!O11 -> 166.13791 | ... Q7: ='Revenue Energy, service & Other'!Q7*'Energy, services & Other GP'!Q11 -> 193.78326
B10: Selected case
B11: Total Energy and Other | C11: =C7/'Revenue Energy, service & Other'!C7 -> 0.019118052 | D11: =D7/'Revenue Energy, service & Other'!D7 -> -0.002199068 | E11: =E7/'Revenue Energy, service & Other'!E7 -> 0.0065602463 | F11: =F7/'Revenue Energy, service & Other'!F7 -> -0.10147185 | G11: =G7/'Revenue Energy, service & Other'!G7 -> -0.094224115 | H11: =CHOOSE(Drivers!$C$3,H14,H17,H21) -> 0.02 | I11: =CHOOSE(Drivers!$C$3,I14,I17,I21) -> 0.02 | J11: =CHOOSE(Drivers!$C$3,J14,J17,J21) -> 0.02 | K11: =CHOOSE(Drivers!$C$3,K14,K17,K21) -> 0.02 | L11: =CHOOSE(Drivers!$C$3,L14,L17,L21) -> 0.02 | M11: =CHOOSE(Drivers!$C$3,M14,M17,M21) -> 0.02 | N11: =CHOOSE(Drivers!$C$3,N14,N17,N21) -> 0.02 | O11: =CHOOSE(Drivers!$C$3,O14,O17,O21) -> 0.02 | ... Q11: =CHOOSE(Drivers!$C$3,Q14,Q17,Q21) -> 0.02
B13: GP%
B14: Best case | H14: =H17+Drivers!$C$13 -> 0.02 | I14: =I17+Drivers!$C$13 -> 0.02 | J14: =J17+Drivers!$C$13 -> 0.02 | K14: =K17+Drivers!$C$13 -> 0.02 | L14: =L17+Drivers!$C$13 -> 0.02 | M14: =M17+Drivers!$C$13 -> 0.02 | N14: =N17+Drivers!$C$13 -> 0.02 | O14: =O17+Drivers!$C$13 -> 0.02 | ... Q14: =Q17+Drivers!$C$13 -> 0.02
B15: Total Energy and Other
B17: Base case | H17: 0 | I17: =$H$17 -> 0 | J17: =$H$17 -> 0 | K17: =$H$17 -> 0 | L17: =$H$17 -> 0 | M17: =$H$17 -> 0 | N17: =$H$17 -> 0 | O17: =$H$17 -> 0 | P17: =$H$17 -> 0 | Q17: =$H$17 -> 0
B18: Total Energy and Other
B20: Worst case
B21: Total Energy and Other | H21: =H17-Drivers!$C$13 -> -0.02 | I21: =I17-Drivers!$C$13 -> -0.02 | J21: =J17-Drivers!$C$13 -> -0.02 | K21: =K17-Drivers!$C$13 -> -0.02 | L21: =L17-Drivers!$C$13 -> -0.02 | M21: =M17-Drivers!$C$13 -> -0.02 | N21: =N17-Drivers!$C$13 -> -0.02 | O21: =O17-Drivers!$C$13 -> -0.02 | ... Q21: =Q17-Drivers!$C$13 -> -0.02

Sheet COGS Energy, Services & Other
B1: Tesla Cost of sales Energy, Services & Other
B3: Tesla Cost of sales Energy & Other (in mln $)
B4: ($ in million) | C4: 2015 Act | D4: 2016 Act | E4: 2017 Act | F4: 2018 Act | G4: 2019 Act | H4: 2019 Fcst | I4: 2021 Fcst | J4: 2022 Fcst | K4: 2023 Fcst | L4: 2024 Fcst | M4: 2025 Fcst | N4: 2026 Fcst | O4: 2027 Fcst | P4: 2028 Fcst | Q4: 2029 Fcst
B5: Energy generation and storage | C5: =-('Revenue Energy, service & Other'!C5-'Energy, services & Other GP'!C5) -> -12.287 | D5: =-('Revenue Energy, service & Other'!D5-'Energy, services & Other GP'!D5) -> -178.332 | E5: =-('Revenue Energy, service & Other'!E5-'Energy, services & Other GP'!E5) -> -874.538 | F5: =-('Revenue Energy, service & Other'!F5-'Energy, services & Other GP'!F5) -> -1364.896 | G5: =-('Revenue Energy, service & Other'!G5-'Energy, services & Other GP'!G5) -> -1341 | H5: n.a. | I5: n.a. | J5: n.a. | K5: n.a. | L5: n.a. | M5: n.a. | N5: n.a. | O5: n.a. | P5: n.a. | Q5: n.a.
B6: Services and other | C6: =-('Revenue Energy, service & Other'!C6-'Energy, services & Other GP'!C6) -> -286.933 | D6: =-('Revenue Energy, service & Other'!D6-'Energy, services & Other GP'!D6) -> -472.462 | E6: =-('Revenue Energy, service & Other'!E6-'Energy, services & Other GP'!E6) -> -1229.022 | F6: =-('Revenue Energy, service & Other'!F6-'Energy, services & Other GP'!F6) -> -1880.354 | G6: =-('Revenue Energy, service & Other'!G6-'Energy, services & Other GP'!G6) -> -2770 | H6: n.a. | I6: n.a. | J6: n.a. | K6: n.a. | L6: n.a. | M6: n.a. | N6: n.a. | O6: n.a. | P6: n.a. | Q6: n.a.
B7: Total Energy and Other | C7: =SUM(C5:C6) -> -299.22 | D7: =SUM(D5:D6) -> -650.794 | E7: =SUM(E5:E6) -> -2103.56 | F7: =SUM(F5:F6) -> -3245.25 | G7: =SUM(G5:G6) -> -4111 | H7: =-('Revenue Energy, service & Other'!H7-'Energy, services & Other GP'!H7) -> -4418.232 | I7: =-('Revenue Energy, service & Other'!I7-'Energy, services & Other GP'!I7) -> -5036.7845 | J7: =-('Revenue Energy, service & Other'!J7-'Energy, services & Other GP'!J7) -> -5540.4629 | K7: =-('Revenue Energy, service & Other'!K7-'Energy, services & Other GP'!K7) -> -5983.7 | L7: =-('Revenue Energy, service & Other'!L7-'Energy, services & Other GP'!L7) -> -6462.396 | M7: =-('Revenue Energy, service & Other'!M7-'Energy, services & Other GP'!M7) -> -6979.3876 | N7: =-('Revenue Energy, service & Other'!N7-'Energy, services & Other GP'!N7) -> -7537.7386 | O7: =-('Revenue Energy, service & Other'!O7-'Energy, services & Other GP'!O7) -> -8140.7577 | ... Q7: =-('Revenue Energy, service & Other'!Q7-'Energy, services & Other GP'!Q7) -> -9495.3798

Sheet Operating Expenses --->
B13: Operating Expenses --->

Sheet Tesla Opex comparables
B1: Tesla Opex comparables
B3: Comparables - 2019
B6: Company | C6: Average | D6: Adj. Average
B7: GM | C7: 0.152 | D7: =C7 -> 0.152
B8: Ford | C8: 0.13234766 | D8: =C8 -> 0.13234766
B9: Fiat Chrysler | C9: 0.093051845 | D9: =C9 -> 0.093051845
B10: BMW | C10: 0.099485177 | D10: =C10 -> 0.099485177
B11: Volkswagen | C11: 0.11 | D11: =C11 -> 0.11
B12: Jaguar | C12: 0.37065334
B13: Porsche | C13: 0.30660065 | D13: =C13 -> 0.30660065
B14: Ferrari | C14: 0.2767445
B15: Scania | C15: 0.15 | D15: =C15 -> 0.15
B16: MAN | C16: 0.15 | D16: =C16 -> 0.15
B17: Paccar | C17: 0.03685738 | D17: =C17 -> 0.03685738
B18: Average | C18: =AVERAGE(C7:C17) -> 0.17070369 | D18: =AVERAGE(D7:D17) -> 0.13670475

Sheet Tesla Opex
B1: Tesla Opex
B3: Tesla Opex (in mln $)
B4: ($ in million) | C4: 2015 Act | D4: 2016 Act | E4: 2017 Act | F4: 2018 Act | G4: 2019 Act | H4: 2020 Fcst | I4: 2021 Fcst | J4: 2022 Fcst | K4: 2023 Fcst | L4: 2024 Fcst | M4: 2025 Fcst | N4: 2026 Fcst | O4: 2027 Fcst | P4: 2028 Fcst | Q4: 2029 Fcst
B5: Revenues | C5: ='[1]Revenue Energy & Other'!C7+'[1]Revenue automotive'!C11 -> 4046.025 | D5: ='[1]Revenue Energy & Other'!D7+'[1]Revenue automotive'!D11 -> 7000.132 | E5: ='[1]Revenue Energy & Other'!E7+'[1]Revenue automotive'!E11 -> 11758.751 | F5: ='[1]Revenue Energy & Other'!F7+'[1]Revenue automotive'!F11 -> 21461.268 | G5: ='[1]Revenue Energy & Other'!G7+'[1]Revenue automotive'!G11 -> 24578 | H5: ='Tesla Revenue Automotive'!H11+'Revenue Energy, service & Other'!H7 -> 38391.953 | I5: ='Tesla Revenue Automotive'!I11+'Revenue Energy, service & Other'!I7 -> 51006.612 | J5: ='Tesla Revenue Automotive'!J11+'Revenue Energy, service & Other'!J7 -> 69356.386 | K5: ='Tesla Revenue Automotive'!K11+'Revenue Energy, service & Other'!K7 -> 89259.574 | L5: ='Tesla Revenue Automotive'!L11+'Revenue Energy, service & Other'!L7 -> 102050.01 | M5: ='Tesla Revenue Automotive'!M11+'Revenue Energy, service & Other'!M7 -> 109367.27 | N5: ='Tesla Revenue Automotive'!N11+'Revenue Energy, service & Other'!N7 -> 116570.75 | O5: ='Tesla Revenue Automotive'!O11+'Revenue Energy, service & Other'!O7 -> 123909.26 | ... Q5: ='Tesla Revenue Automotive'!Q11+'Revenue Energy, service & Other'!Q7 -> 135626.2
B6: Opex as a % of revenues | C6: =C7/C5 -> -0.40536873 | D6: =D7/D5 -> -0.32379347 | E6: =E7/E5 -> -0.32780463 | F6: =F7/F5 -> -0.20642275 | G6: =G7/G5 -> -0.16836195 | H6: =H10 -> -0.11670475 | I6: =I10 -> -0.11670475 | J6: =J10 -> -0.11670475 | K6: =K10 -> -0.11670475 | L6: =L10 -> -0.11670475 | M6: =M10 -> -0.11670475 | N6: =N10 -> -0.11670475 | O6: =O10 -> -0.11670475 | ... Q6: =Q10 -> -0.11670475
B7: Opex | C7: =('[1]P&L Input'!C12+'[1]P&L Input'!C13+'[1]P&L Input'!C14)/1000 -> -1640.132 | D7: =('[1]P&L Input'!D12+'[1]P&L Input'!D13+'[1]P&L Input'!D14)/1000 -> -2266.597 | E7: =('[1]P&L Input'!E12+'[1]P&L Input'!E13+'[1]P&L Input'!E14)/1000 -> -3854.573 | F7: =('[1]P&L Input'!F12+'[1]P&L Input'!F13+'[1]P&L Input'!F14)/1000 -> -4430.094 | G7: =('[1]P&L Input'!G12+'[1]P&L Input'!G13+'[1]P&L Input'!G14)/1000 -> -4138 | H7: =H5*H6 -> -4480.5231 | I7: =I5*I6 -> -5952.7137 | J7: =J5*J6 -> -8094.2194 | K7: =K5*K6 -> -10417.016 | L7: =L5*L6 -> -11909.721 | M7: =M5*M6 -> -12763.679 | N7: =N5*N6 -> -13604.36 | O7: =O5*O6 -> -14460.798 | ... Q7: =Q5*Q6 -> -15828.221
B9: Selected case
B10: Opex as a % of revenue | H10: =CHOOSE(Drivers!$C$3,H14,H17,H20) -> -0.11670475 | I10: =CHOOSE(Drivers!$C$3,I14,I17,I20) -> -0.11670475 | J10: =CHOOSE(Drivers!$C$3,J14,J17,J20) -> -0.11670475 | K10: =CHOOSE(Drivers!$C$3,K14,K17,K20) -> -0.11670475 | L10: =CHOOSE(Drivers!$C$3,L14,L17,L20) -> -0.11670475 | M10: =CHOOSE(Drivers!$C$3,M14,M17,M20) -> -0.11670475 | N10: =CHOOSE(Drivers!$C$3,N14,N17,N20) -> -0.11670475 | O10: =CHOOSE(Drivers!$C$3,O14,O17,O20) -> -0.11670475 | ... Q10: =CHOOSE(Drivers!$C$3,Q14,Q17,Q20) -> -0.11670475
B12: Opex %
B13: Best case
B14: Opex as a % of revenue | H14: =H17+2% -> -0.11670475 | I14: =I17+2% -> -0.11670475 | J14: =J17+2% -> -0.11670475 | K14: =K17+2% -> -0.11670475 | L14: =L17+2% -> -0.11670475 | M14: =M17+2% -> -0.11670475 | N14: =N17+2% -> -0.11670475 | O14: =O17+2% -> -0.11670475 | ... Q14: =Q17+2% -> -0.11670475
B16: Base case
B17: Opex as a % of revenue | H17: =-'Tesla Opex comparables'!$D$18 -> -0.13670475 | I17: =-'Tesla Opex comparables'!$D$18 -> -0.13670475 | J17: =-'Tesla Opex comparables'!$D$18 -> -0.13670475 | K17: =-'Tesla Opex comparables'!$D$18 -> -0.13670475 | L17: =-'Tesla Opex comparables'!$D$18 -> -0.13670475 | M17: =-'Tesla Opex comparables'!$D$18 -> -0.13670475 | N17: =-'Tesla Opex comparables'!$D$18 -> -0.13670475 | O17: =-'Tesla Opex comparables'!$D$18 -> -0.13670475 | ... Q17: =-'Tesla Opex comparables'!$D$18 -> -0.13670475
B19: Worst case
B20: Opex as a % of revenue | H20: =H17-2% -> -0.15670475 | I20: =I17-2% -> -0.15670475 | J20: =J17-2% -> -0.15670475 | K20: =K17-2% -> -0.15670475 | L20: =L17-2% -> -0.15670475 | M20: =M17-2% -> -0.15670475 | N20: =N17-2% -> -0.15670475 | O20: =O17-2% -> -0.15670475 | ... Q20: =Q17-2% -> -0.15670475

Sheet PP&E --->
B13: Property, Plant & Equipment --->

Sheet Tesla PP&E
B1: Tesla Fixed Asset Movement Schedule
B3: ="Selected case:"&CHOOSE(C3,"as a % of PPE", "as a % of revenue") -> Selected case:as a % of PPE | C3: 1
B5: Tesla PP&E (in mln $)
B6: ($ in million) | C6: 31Dec2015 Act | D6: 31Dec2016 Act | E6: 31Dec2017 Act | F6: 31Dec2018 Act | G6: 31Dec2019 Act | H6: 31Dec2020 Fcst | I6: 31Dec2021 Fcst | J6: 31Dec2022 Fcst | K6: 31Dec2023 Fcst | L6: 31Dec2024 Fcst | M6: 31Dec2025 Fcst | N6: 31Dec2026 Fcst | O6: 31Dec2027 Fcst | P6: 31Dec2028 Fcst | Q6: 31Dec2029 Fcst
B7: Beginning PP&E | C7: =738494/1000 -> 738.494 | D7: =C10 -> 3403.334 | E7: =D10 -> 5982.957 | F7: =E10 -> 10027.522 | G7: =F10 -> 11330.077 | H7: =G10 -> 10396 | I7: =H10 -> 11153.095 | J7: =I10 -> 11841.403 | K7: =J10 -> 12434.497 | ... Q7: =P10 -> 12102.729
B8: Capex | C8: =C10-C7-C9 -> 3087.84 | D8: =D10-D7-D9 -> 3526.623 | E8: =E10-E7-E9 -> 5680.565 | F8: =F10-F7-F9 -> 3203.555 | G8: =G10-G7-G9 -> 1219.923 | H8: =CHOOSE($C$3,H32*H7,H33*'Tesla Opex'!H5) -> 1996.328 | I8: =CHOOSE($C$3,I32*I7,I33*'Tesla Opex'!I5) -> 2141.7118 | J8: =CHOOSE($C$3,J32*J7,J33*'Tesla Opex'!J5) -> 2273.8865 | K8: =CHOOSE($C$3,K32*K7,K33*'Tesla Opex'!K5) -> 2387.7775 | L8: =CHOOSE($C$3,L32*L7,L33*'Tesla Opex'!L5) -> 2477.6866 | M8: =CHOOSE($C$3,M32*M7,M33*'Tesla Opex'!M5) -> 2537.2821 | N8: =CHOOSE($C$3,N32*N7,N33*'Tesla Opex'!N5) -> 2559.5987 | O8: =CHOOSE($C$3,O32*O7,O33*'Tesla Opex'!O5) -> 2537.0491 | ... Q8: =CHOOSE($C$3,Q32*Q7,Q33*'Tesla Opex'!Q5) -> 3534.3414
B9: D&A | C9: -423 | D9: -947 | E9: -1636 | F9: -1901 | G9: -2154 | H9: =H28 -> -1239.2328 | I9: =I28 -> -1453.404 | J9: =J28 -> -1680.7926 | K9: =K28 -> -1919.5704 | L9: =L28 -> -2167.339 | M9: =M28 -> -2421.0673 | N9: =N28 -> -2677.0271 | O9: =O28 -> -2930.732 | ... Q9: =Q28 -> -3530.3112
B10: Ending PP&E | C10: ='Balance Sheet Input'!C12/1000 -> 3403.334 | D10: ='Balance Sheet Input'!D12/1000 -> 5982.957 | E10: ='Balance Sheet Input'!E12/1000 -> 10027.522 | F10: ='Balance Sheet Input'!F12/1000 -> 11330.077 | G10: ='Balance Sheet Input'!G12/1000 -> 10396 | H10: =SUM(H7:H9) -> 11153.095 | I10: =SUM(I7:I9) -> 11841.403 | J10: =SUM(J7:J9) -> 12434.497 | K10: =SUM(K7:K9) -> 12902.704 | L10: =SUM(L7:L9) -> 13213.052 | M10: =SUM(M7:M9) -> 13329.266 | N10: =SUM(N7:N9) -> 13211.838 | O10: =SUM(O7:O9) -> 12818.155 | ... Q10: =SUM(Q7:Q9) -> 12106.759
B12: Useful life Capex | C12: 10
B13: Useful life historical assets | C13: 10
B15: Tesla D&A (in mln $)
B16: ($ in million) | C16: 31Dec2015 Act | D16: 31Dec2016 Act | E16: 31Dec2017 Act | F16: 31Dec2018 Act | G16: 31Dec2019 Act | H16: 31Dec2020 Fcst | I16: 31Dec2021 Fcst | J16: 31Dec2022 Fcst | K16: 31Dec2023 Fcst | L16: 31Dec2024 Fcst | M16: 31Dec2025 Fcst | N16: 31Dec2026 Fcst | O16: 31Dec2027 Fcst | P16: 31Dec2028 Fcst | Q16: 31Dec2029 Fcst
H17: =-$H$7/$C$13 -> -1039.6 | I17: =-$H$7/$C$13 -> -1039.6 | J17: =-$H$7/$C$13 -> -1039.6 | K17: =-$H$7/$C$13 -> -1039.6 | L17: =-$H$7/$C$13 -> -1039.6 | M17: =-$H$7/$C$13 -> -1039.6 | N17: =-$H$7/$C$13 -> -1039.6 | O17: =-$H$7/$C$13 -> -1039.6 | ... Q17: =-$H$7/$C$13 -> -1039.6
H18: =-$H$8/$C$13 -> -199.6328 | I18: =-$H$8/$C$13 -> -199.6328 | J18: =-$H$8/$C$13 -> -199.6328 | K18: =-$H$8/$C$13 -> -199.6328 | L18: =-$H$8/$C$13 -> -199.6328 | M18: =-$H$8/$C$13 -> -199.6328 | N18: =-$H$8/$C$13 -> -199.6328 | O18: =-$H$8/$C$13 -> -199.6328 | ... Q18: =-$H$8/$C$13 -> -199.6328
I19: =-$I$8/$C$12 -> -214.17118 | J19: =-$I$8/$C$12 -> -214.17118 | K19: =-$I$8/$C$12 -> -214.17118 | L19: =-$I$8/$C$12 -> -214.17118 | M19: =-$I$8/$C$12 -> -214.17118 | N19: =-$I$8/$C$12 -> -214.17118 | O19: =-$I$8/$C$12 -> -214.17118 | P19: =-$I$8/$C$12 -> -214.17118 | Q19: =-$I$8/$C$12 -> -214.17118
J20: =-$J$8/$C$13 -> -227.38865 | K20: =-$J$8/$C$13 -> -227.38865 | L20: =-$J$8/$C$13 -> -227.38865 | M20: =-$J$8/$C$13 -> -227.38865 | N20: =-$J$8/$C$13 -> -227.38865 | O20: =-$J$8/$C$13 -> -227.38865 | P20: =-$J$8/$C$13 -> -227.38865 | Q20: =-$J$8/$C$13 -> -227.38865
K21: =-$K$8/$C$12 -> -238.77775 | L21: =-$K$8/$C$12 -> -238.77775 | M21: =-$K$8/$C$12 -> -238.77775 | N21: =-$K$8/$C$12 -> -238.77775 | O21: =-$K$8/$C$12 -> -238.77775 | P21: =-$K$8/$C$12 -> -238.77775 | Q21: =-$K$8/$C$12 -> -238.77775
L22: =-$L$8/$C$12 -> -247.76866 | M22: =-$L$8/$C$12 -> -247.76866 | N22: =-$L$8/$C$12 -> -247.76866 | O22: =-$L$8/$C$12 -> -247.76866 | P22: =-$L$8/$C$12 -> -247.76866 | Q22: =-$L$8/$C$12 -> -247.76866
M23: =-$M$8/$C$12 -> -253.72821 | N23: =-$M$8/$C$12 -> -253.72821 | O23: =-$M$8/$C$12 -> -253.72821 | P23: =-$M$8/$C$12 -> -253.72821 | Q23: =-$M$8/$C$12 -> -253.72821
N24: =-$N$8/$C$12 -> -255.95987 | O24: =-$N$8/$C$12 -> -255.95987 | P24: =-$N$8/$C$12 -> -255.95987 | Q24: =-$N$8/$C$12 -> -255.95987
O25: =-$O$8/$C$12 -> -253.70491 | P25: =-$O$8/$C$12 -> -253.70491 | Q25: =-$O$8/$C$12 -> -253.70491
P26: =-$P$8/$C$12 -> -246.14507 | Q26: =-$P$8/$C$12 -> -246.14507
Q27: =-$Q$8/$C$12 -> -353.43414
B28: Total D&A | C28: =SUM(C17:C27) -> 0 | D28: =SUM(D17:D27) -> 0 | E28: =SUM(E17:E27) -> 0 | F28: =SUM(F17:F27) -> 0 | G28: =SUM(G17:G27) -> 0 | H28: =SUM(H17:H27) -> -1239.2328 | I28: =SUM(I17:I27) -> -1453.404 | J28: =SUM(J17:J27) -> -1680.7926 | ... Q28: =SUM(Q17:Q27) -> -3530.3112
B31: Selected case
B32: Capex as a % of PP&E | H32: =CHOOSE(Drivers!$C$3,H36,H39,H42) -> 0.19202847 | I32: =CHOOSE(Drivers!$C$3,I36,I39,I42) -> 0.19202847 | J32: =CHOOSE(Drivers!$C$3,J36,J39,J42) -> 0.19202847 | K32: =CHOOSE(Drivers!$C$3,K36,K39,K42) -> 0.19202847 | L32: =CHOOSE(Drivers!$C$3,L36,L39,L42) -> 0.19202847 | M32: =CHOOSE(Drivers!$C$3,M36,M39,M42) -> 0.19202847 | N32: =CHOOSE(Drivers!$C$3,N36,N39,N42) -> 0.19202847 | O32: =CHOOSE(Drivers!$C$3,O36,O39,O42) -> 0.19202847 | ... Q32: =CHOOSE(Drivers!$C$3,Q36,Q39,Q42) -> 0.29202847
B33: Capex as a % of revenue | H33: =CHOOSE(Drivers!$C$3,H37,H40,H43) -> 0.034053331 | I33: =CHOOSE(Drivers!$C$3,I37,I40,I43) -> 0.034053331 | J33: =CHOOSE(Drivers!$C$3,J37,J40,J43) -> 0.034053331 | K33: =CHOOSE(Drivers!$C$3,K37,K40,K43) -> 0.034053331 | L33: =CHOOSE(Drivers!$C$3,L37,L40,L43) -> 0.034053331 | M33: =CHOOSE(Drivers!$C$3,M37,M40,M43) -> 0.034053331 | N33: =CHOOSE(Drivers!$C$3,N37,N40,N43) -> 0.034053331 | O33: =CHOOSE(Drivers!$C$3,O37,O40,O43) -> 0.034053331 | ... Q33: =CHOOSE(Drivers!$C$3,Q37,Q40,Q43) -> 0.094053331
B34: Capex %
B35: Best case
B36: Capex as a % of PP&E | H36: =H39-5% -> 0.19202847 | I36: =I39-5% -> 0.19202847 | J36: =J39-5% -> 0.19202847 | K36: =K39-5% -> 0.19202847 | L36: =L39-5% -> 0.19202847 | M36: =M39-5% -> 0.19202847 | N36: =N39-5% -> 0.19202847 | O36: =O39-5% -> 0.19202847 | P36: =P39-5% -> 0.19202847 | Q36: =Q39+5% -> 0.29202847
B37: =B33 -> Capex as a % of revenue | H37: =H40-3% -> 0.034053331 | I37: =I40-3% -> 0.034053331 | J37: =J40-3% -> 0.034053331 | K37: =K40-3% -> 0.034053331 | L37: =L40-3% -> 0.034053331 | M37: =M40-3% -> 0.034053331 | N37: =N40-3% -> 0.034053331 | O37: =O40-3% -> 0.034053331 | P37: =P40-3% -> 0.034053331 | Q37: =Q40+3% -> 0.094053331
B38: Base case
B39: Capex as a % of PP&E | H39: =-'Tesla PP&E Comparables'!D16 -> 0.24202847 | I39: =H39 -> 0.24202847 | J39: =I39 -> 0.24202847 | K39: =J39 -> 0.24202847 | L39: =K39 -> 0.24202847 | M39: =L39 -> 0.24202847 | N39: =M39 -> 0.24202847 | O39: =N39 -> 0.24202847 | P39: =O39 -> 0.24202847 | Q39: =P39 -> 0.24202847
B40: =B33 -> Capex as a % of revenue | H40: =-'Tesla PP&E Comparables'!G16 -> 0.064053331 | I40: =H40 -> 0.064053331 | J40: =I40 -> 0.064053331 | K40: =J40 -> 0.064053331 | L40: =K40 -> 0.064053331 | M40: =L40 -> 0.064053331 | N40: =M40 -> 0.064053331 | O40: =N40 -> 0.064053331 | P40: =O40 -> 0.064053331 | Q40: =P40 -> 0.064053331
B41: Worst case
B42: Capex as a % of PP&E | H42: =H39+5% -> 0.29202847 | I42: =I39+5% -> 0.29202847 | J42: =J39+5% -> 0.29202847 | K42: =K39+5% -> 0.29202847 | L42: =L39+5% -> 0.29202847 | M42: =M39+5% -> 0.29202847 | N42: =N39+5% -> 0.29202847 | O42: =O39+5% -> 0.29202847 | P42: =P39+5% -> 0.29202847 | Q42: =Q39-5% -> 0.19202847
B43: =B33 -> Capex as a % of revenue | H43: =H40+3% -> 0.094053331 | I43: =I40+3% -> 0.094053331 | J43: =J40+3% -> 0.094053331 | K43: =K40+3% -> 0.094053331 | L43: =L40+3% -> 0.094053331 | M43: =M40+3% -> 0.094053331 | N43: =N40+3% -> 0.094053331 | O43: =O40+3% -> 0.094053331 | P43: =P40+3% -> 0.094053331 | Q43: =Q40-3% -> 0.034053331

Sheet Tesla PP&E Comparables
B1: Tesla PP&E comparables
B3: Comparables - 2019
C5: CAPEX as a % of PP&E | F5: CAPEX as a % of revenues
B6: Company | C6: Average | D6: Adj. Average | F6: Average | G6: Adj. Average
B7: GM | C7: -0.19592258 | D7: =C7 -> -0.19592258 | F7: -0.055320358 | G7: =F7 -> -0.055320358
B8: Ford | C8: -0.21112278 | D8: =C8 -> -0.21112278 | F8: -0.048992944 | G8: =F8 -> -0.048992944
B9: Fiat Chrysler | C9: -0.29309983 | D9: =C9 -> -0.29309983 | F9: -0.077504691 | G9: =F9 -> -0.077504691
B10: BMW | C10: -0.29601301 | D10: =C10 -> -0.29601301 | F10: -0.073449532 | G10: =F10 -> -0.073449532
B11: Mercedes | C11: -0.19381849 | D11: =C11 -> -0.19381849 | F11: -0.041674144 | G11: =F11 -> -0.041674144
B12: Volkswagen | C12: -0.21511065 | D12: =C12 -> -0.21511065 | F12: -0.056326989 | G12: =F12 -> -0.056326989
B13: Jaguar | C13: -0.24491682 | D13: =C13 -> -0.24491682 | F13: -0.065664492 | G13: =F13 -> -0.065664492
B14: Ferrari | C14: -0.32922296 | D14: =C14 -> -0.32922296 | F14: -0.093493495 | G14: =F14 -> -0.093493495
B15: Paccar | C15: -0.19902913 | D15: =C15 -> -0.19902913 | F15: -0.023797678
B16: Average | C16: =AVERAGE(C7:C15) -> -0.24202847 | D16: =AVERAGE(D7:D15) -> -0.24202847 | F16: =AVERAGE(F7:F15) -> -0.05958048 | G16: =AVERAGE(G7:G15) -> -0.064053331

Sheet Working Capital ---> 
B13: Working Capital --->

Sheet Tesla Working capital 
B1: Tesla Working capital
B3: Tesla Working capital (in mln $)
B4: ($ in million) | C4: 31Dec2015 Act | D4: 31Dec2016 Act | E4: 31Dec2017 Act | F4: 31Dec2018 Act | G4: 31Dec2019 Act | H4: 31Dec2020 Fcst | I4: 31Dec2021 Fcst | J4: 31Dec2022 Fcst | K4: 31Dec2023 Fcst | L4: 31Dec2024 Fcst | M4: 31Dec2025 Fcst | N4: 31Dec2026 Fcst | O4: 31Dec2027 Fcst | P4: 31Dec2028 Fcst | Q4: 31Dec2029 Fcst
B5: Trade receivables | C5: ='Balance Sheet Input'!C6/1000 -> 168.965 | D5: ='Balance Sheet Input'!D6/1000 -> 499.142 | E5: ='Balance Sheet Input'!E6/1000 -> 515.381 | F5: ='Balance Sheet Input'!F6/1000 -> 949.022 | G5: ='Balance Sheet Input'!G6/1000 -> 1324 | H5: =H11*('P&L '!H5)/360 -> 1957.8706 | I5: =I11*('P&L '!I5)/360 -> 2601.1791 | J5: =J11*('P&L '!J5)/360 -> 3536.9607 | K5: =K11*('P&L '!K5)/360 -> 4551.9616 | L5: =L11*('P&L '!L5)/360 -> 5204.2342 | M5: =M11*('P&L '!M5)/360 -> 5577.3916 | N5: =N11*('P&L '!N5)/360 -> 5944.7471 | O5: =O11*('P&L '!O5)/360 -> 6318.988 | ... Q5: =Q11*('P&L '!Q5)/360 -> 6916.5156
B6: Inventory | C6: ='Balance Sheet Input'!C7/1000 -> 1277.838 | D6: ='Balance Sheet Input'!D7/1000 -> 2067.454 | E6: ='Balance Sheet Input'!E7/1000 -> 2263.537 | F6: ='Balance Sheet Input'!F7/1000 -> 3113.446 | G6: ='Balance Sheet Input'!G7/1000 -> 3552 | H6: =-H12*('P&L '!H6)/360 -> 8351.4201 | I6: =-I12*('P&L '!I6)/360 -> 11210.304 | J6: =-J12*('P&L '!J6)/360 -> 15317.382 | K6: =-K12*('P&L '!K6)/360 -> 19780.4 | L6: =-L12*('P&L '!L6)/360 -> 22604.495 | M6: =-M12*('P&L '!M6)/360 -> 24249.431 | N6: =-N12*('P&L '!N6)/360 -> 25866.919 | O6: =-O12*('P&L '!O6)/360 -> 27518.193 | ... Q6: =-Q12*('P&L '!Q6)/360 -> 30150.922
B7: Trade payables | C7: ='Balance Sheet Input'!C19/1000 -> 916.148 | D7: ='Balance Sheet Input'!D19/1000 -> 1860.341 | E7: ='Balance Sheet Input'!E19/1000 -> 2390.25 | F7: ='Balance Sheet Input'!F19/1000 -> 3404.451 | G7: ='Balance Sheet Input'!G19/1000 -> 3771 | H7: =-H13*('P&L '!H6)/360 -> 7665.1488 | I7: =-I13*('P&L '!I6)/360 -> 10289.106 | J7: =-J13*('P&L '!J6)/360 -> 14058.688 | K7: =-K13*('P&L '!K6)/360 -> 18154.961 | L7: =-L13*('P&L '!L6)/360 -> 20746.989 | M7: =-M13*('P&L '!M6)/360 -> 22256.753 | N7: =-N13*('P&L '!N6)/360 -> 23741.325 | O7: =-O13*('P&L '!O6)/360 -> 25256.907 | ... Q7: =-Q13*('P&L '!Q6)/360 -> 27673.294
B8: Net trade cycle | C8: =C5+C6-C7 -> 530.655 | D8: =D5+D6-D7 -> 706.255 | E8: =E5+E6-E7 -> 388.668 | F8: =F5+F6-F7 -> 658.017 | G8: =G5+G6-G7 -> 1105 | H8: =H5+H6-H7 -> 2644.142 | I8: =I5+I6-I7 -> 3522.377 | J8: =J5+J6-J7 -> 4795.6545 | ... Q8: =Q5+Q6-Q7 -> 9394.1438
B10: Selected case:
B11: DSO | C11: ='Balance Sheet Input'!C40 -> 15.033867 | D11: ='Balance Sheet Input'!D40 -> 25.669676 | E11: ='Balance Sheet Input'!E40 -> 15.778645 | F11: ='Balance Sheet Input'!F40 -> 15.919279 | G11: ='Balance Sheet Input'!G40 -> 19.392953 | H11: =AVERAGE($C$11:$G$11) -> 18.358884 | I11: =AVERAGE($C$11:$G$11) -> 18.358884 | J11: =AVERAGE($C$11:$G$11) -> 18.358884 | K11: =AVERAGE($C$11:$G$11) -> 18.358884 | L11: =AVERAGE($C$11:$G$11) -> 18.358884 | M11: =AVERAGE($C$11:$G$11) -> 18.358884 | N11: =AVERAGE($C$11:$G$11) -> 18.358884 | O11: =AVERAGE($C$11:$G$11) -> 18.358884 | ... Q11: =AVERAGE($C$11:$G$11) -> 18.358884
B12: DIO | C12: ='Balance Sheet Input'!C41 -> 147.32376 | D12: ='Balance Sheet Input'!D41 -> 137.80794 | E12: ='Balance Sheet Input'!E41 -> 85.449954 | F12: ='Balance Sheet Input'!F41 -> 64.344949 | G12: ='Balance Sheet Input'!G41 -> 62.349213 | H12: =AVERAGE($C$12:$G$12) -> 99.455162 | I12: =AVERAGE($C$12:$G$12) -> 99.455162 | J12: =AVERAGE($C$12:$G$12) -> 99.455162 | K12: =AVERAGE($C$12:$G$12) -> 99.455162 | L12: =AVERAGE($C$12:$G$12) -> 99.455162 | M12: =AVERAGE($C$12:$G$12) -> 99.455162 | N12: =AVERAGE($C$12:$G$12) -> 99.455162 | O12: =AVERAGE($C$12:$G$12) -> 99.455162 | ... Q12: =AVERAGE($C$12:$G$12) -> 99.455162
B13: DPO | C13: ='Balance Sheet Input'!C42 -> 105.62401 | D13: ='Balance Sheet Input'!D42 -> 124.00264 | E13: ='Balance Sheet Input'!E42 -> 90.23345 | F13: ='Balance Sheet Input'!F42 -> 70.35909 | G13: ='Balance Sheet Input'!G42 -> 66.193379 | H13: =AVERAGE($C$13:$G$13) -> 91.282513 | I13: =AVERAGE($C$13:$G$13) -> 91.282513 | J13: =AVERAGE($C$13:$G$13) -> 91.282513 | K13: =AVERAGE($C$13:$G$13) -> 91.282513 | L13: =AVERAGE($C$13:$G$13) -> 91.282513 | M13: =AVERAGE($C$13:$G$13) -> 91.282513 | N13: =AVERAGE($C$13:$G$13) -> 91.282513 | O13: =AVERAGE($C$13:$G$13) -> 91.282513 | ... Q13: =AVERAGE($C$13:$G$13) -> 91.282513
B14: Net trade cycle | C14: =C11+C12-C13 -> 56.733621 | D14: =D11+D12-D13 -> 39.474972 | E14: =E11+E12-E13 -> 10.995149 | F14: =F11+F12-F13 -> 9.9051388 | G14: =G11+G12-G13 -> 15.548787 | H14: =H11+H12-H13 -> 26.531534 | I14: =I11+I12-I13 -> 26.531534 | J14: =J11+J12-J13 -> 26.531534 | ... Q14: =Q11+Q12-Q13 -> 26.531534

Sheet Tesla WC comparables
B1: Tesla Working Capital comparables
B3: Comparables - 2019
C5: DSO | F5: DIO | I5: DPO | L5: Net trade cycle
B6: Vehicle | C6: Average | D6: Adj. Average | F6: Average | G6: Adj. Average | I6: Average | J6: Adj. Average | L6: Average | M6: Adj. Average
B7: GM | C7: 19.942786 | D7: =C7 -> 19.942786 | F7: 33.829608 | G7: =F7 -> 33.829608 | I7: 68.381488 | J7: =I7 -> 68.381488 | L7: =C7+F7-I7 -> -14.609093 | M7: =L7 -> -14.609093
B8: Ford | C8: 25.851187 | D8: =C8 -> 25.851187 | F8: 29.988195 | G8: =F8 -> 29.988195 | I8: 57.517466 | J8: =I8 -> 57.517466 | L8: =C8+F8-I8 -> -1.6780836 | M8: =L8 -> -1.6780836
B9: Fiat Chrysler | C9: 22.055145 | D9: =C9 -> 22.055145 | F9: 37.567301 | G9: =F9 -> 37.567301 | I9: 83.527543 | J9: =I9 -> 83.527543 | L9: =C9+F9-I9 -> -23.905097 | M9: =L9 -> -23.905097
B10: BMW | C10: 8.7485003 | D10: =C10 -> 8.7485003 | F10: 66.427199 | G10: =F10 -> 66.427199 | I10: 40.64769 | J10: =I10 -> 40.64769 | L10: =C10+F10-I10 -> 34.528009 | M10: =L10 -> 34.528009
B11: Volkswagen | C11: 25.565882 | D11: =C11 -> 25.565882 | F11: 82.692614 | G11: =F11 -> 82.692614 | I11: 40.238832 | J11: =I11 -> 40.238832 | L11: =C11+F11-I11 -> 68.019664 | M11: =L11 -> 68.019664
B12: Jaguar | C12: 20.249442 | F12: 82.889598 | I12: 162.72368 | L12: =C12+F12-I12 -> -59.584635
B13: Ferrari | C13: 22.081784 | D13: =C13 -> 22.081784 | F13: 83.767313 | G13: =F13 -> 83.767313 | I13: 142.00554 | J13: =I13 -> 142.00554 | L13: =C13+F13-I13 -> -36.156443 | M13: =L13 -> -36.156443
B14: Paccar | C14: 19.492537 | D14: =C14 -> 19.492537 | F14: 20.192644 | G14: =F14 -> 20.192644 | I14: 55.936953 | J14: =I14 -> 55.936953 | L14: =C14+F14-I14 -> -16.251771 | M14: =D14+G14-J14 -> -16.251771
B15: Average | C15: =AVERAGE(C7:C14) -> 20.498408 | D15: =AVERAGE(D7:D14) -> 20.533975 | F15: =AVERAGE(F7:F14) -> 54.669309 | G15: =AVERAGE(G7:G14) -> 50.637839 | I15: =AVERAGE(I7:I14) -> 81.372398 | J15: =AVERAGE(J7:J14) -> 69.750787 | L15: =AVERAGE(L7:L14) -> -6.2046813 | M15: =AVERAGE(M7:M14) -> 1.4210264

Sheet Financing --->
B13: Financing --->

Sheet Tesla Financing 
B1: Tesla Financing
B3: Cover negative cash flows with:
B4: Debt | C4: 0.5
B5: Equity | C5: 0.5
B7: Bond Yield as of Sep. 20 | C7: =Drivers!C11 -> 0.04324
B9: Tesla Financing (in mln $)
B10: ($ in million) | C10: 31Dec2015 Act | D10: 31Dec2016 Act | E10: 31Dec2017 Act | F10: 31Dec2018 Act | G10: 31Dec2019 Act | H10: 31Dec2020 Fcst | I10: 31Dec2021 Fcst | J10: 31Dec2022 Fcst | K10: 31Dec2023 Fcst | L10: 31Dec2024 Fcst | M10: 31Dec2025 Fcst | N10: 31Dec2026 Fcst | O10: 31Dec2027 Fcst | P10: 31Dec2028 Fcst | Q10: 31Dec2029 Fcst
B11: Long-term debt and capital leases, net of current | C11: ='Balance Sheet Input'!C29/1000 -> 2021.093 | D11: ='Balance Sheet Input'!D29/1000 -> 5860.049 | E11: ='Balance Sheet Input'!E29/1000 -> 9415.7 | F11: ='Balance Sheet Input'!F29/1000 -> 9403.672 | G11: ='Balance Sheet Input'!G29/1000 -> 11634 | H11: =G11+G19 -> 11634 | I11: =H11+H19 -> 11634 | J11: =I11+I19 -> 11634 | K11: =J11+J19 -> 11634 | L11: =K11+K19 -> 11634 | M11: =L11+L19 -> 11634 | N11: =M11+M19 -> 11634 | O11: =N11+N19 -> 11634 | ... Q11: =P11+P19 -> 11634
B12: ='[1]P&L Input'!B17 -> Interest expense | C12: ='P&L Input'!C17/1000 -> -118.851 | D12: ='P&L Input'!D17/1000 -> -198.81 | E12: ='P&L Input'!E17/1000 -> -471.259 | F12: ='P&L Input'!F17/1000 -> -663.071 | G12: ='P&L Input'!G17/1000 -> -685 | H12: =-G11*H13 -> -503.05416 | I12: =-H11*I13 -> -503.05416 | J12: =-I11*J13 -> -503.05416 | K12: =-J11*K13 -> -503.05416 | L12: =-K11*L13 -> -503.05416 | M12: =-L11*M13 -> -503.05416 | N12: =-M11*N13 -> -503.05416 | O12: =-N11*O13 -> -503.05416 | ... Q12: =-P11*Q13 -> -503.05416
B13: Interest rate | C13: =C12/C11 -> -0.05880531 | D13: =D12/D11 -> -0.033926337 | E13: =E12/E11 -> -0.050050341 | F13: =F12/F11 -> -0.070511923 | G13: =G12/G11 -> -0.058879147 | H13: =$C$7 -> 0.04324 | I13: =$C$7 -> 0.04324 | J13: =$C$7 -> 0.04324 | K13: =$C$7 -> 0.04324 | L13: =$C$7 -> 0.04324 | M13: =$C$7 -> 0.04324 | N13: =$C$7 -> 0.04324 | O13: =$C$7 -> 0.04324 | ... Q13: =$C$7 -> 0.04324
B16: Tesla Cash Flow (in mln $)
C17: 2015 Act | D17: 2016 Act | E17: 2015 Act | F17: 2016 Act | G17: 2015 Act | H17: 2016 Act | I17: 2015 Act | J17: 2016 Act | K17: 2015 Act | L17: 2016 Act | M17: 2015 Act | N17: 2016 Act | O17: 2015 Act | P17: 2016 Act | Q17: 2015 Act
B18: Unlevered Free Cash Flow | H18: ='Cash Flow '!H20 -> 5085.2111 | I18: ='Cash Flow '!I20 -> 5828.0579 | J18: ='Cash Flow '!J20 -> 8342.5964 | K18: ='Cash Flow '!K20 -> 9960.3508 | L18: ='Cash Flow '!L20 -> 9289.3304 | M18: ='Cash Flow '!M20 -> 8587.4274 | N18: ='Cash Flow '!N20 -> 9195.606 | O18: ='Cash Flow '!O20 -> 9902.3811 | ... Q18: ='Cash Flow '!Q20 -> 9732.036
B19: Debt | H19: =IF(H$18<0,-H$18*$C4,0) -> 0 | I19: =IF(I$18<0,-I$18*$C4,0) -> 0 | J19: =IF(J$18<0,-J$18*$C4,0) -> 0 | K19: =IF(K$18<0,-K$18*$C4,0) -> 0 | L19: =IF(L$18<0,-L$18*$C4,0) -> 0 | M19: =IF(M$18<0,-M$18*$C4,0) -> 0 | N19: =IF(N$18<0,-N$18*$C4,0) -> 0 | O19: =IF(O$18<0,-O$18*$C4,0) -> 0 | ... Q19: =IF(Q$18<0,-Q$18*$C4,0) -> 0
B20: Equity | H20: =IF(H$18<0,-H$18*$C5,0) -> 0 | I20: =IF(I$18<0,-I$18*$C5,0) -> 0 | J20: =IF(J$18<0,-J$18*$C5,0) -> 0 | K20: =IF(K$18<0,-K$18*$C5,0) -> 0 | L20: =IF(L$18<0,-L$18*$C5,0) -> 0 | M20: =IF(M$18<0,-M$18*$C5,0) -> 0 | N20: =IF(N$18<0,-N$18*$C5,0) -> 0 | O20: =IF(O$18<0,-O$18*$C5,0) -> 0 | ... Q20: =IF(Q$18<0,-Q$18*$C5,0) -> 0

Sheet Financial Statements --->
B13: Financial Statements --->

Sheet P&L 
B1: Tesla P&L
B3: Tesla P&L (in mln $)
B4: ($ in million) | C4: 2015 Act | D4: 2016 Act | E4: 2017 Act | F4: 2018 Act | G4: 2019 Act | H4: 2020 Fcst | I4: 2021 Fcst | J4: 2022 Fcst | K4: 2023 Fcst | L4: 2024 Fcst | M4: 2025 Fcst | N4: 2026 Fcst | O4: 2027 Fcst | P4: 2028 Fcst | Q4: 2029 Fcst
B5: Revenues | C5: ='Tesla Revenue Automotive'!C11+'Revenue Energy, service & Other'!C7 -> 4046.025 | D5: ='Tesla Revenue Automotive'!D11+'Revenue Energy, service & Other'!D7 -> 7000.132 | E5: ='Tesla Revenue Automotive'!E11+'Revenue Energy, service & Other'!E7 -> 11758.751 | F5: ='Tesla Revenue Automotive'!F11+'Revenue Energy, service & Other'!F7 -> 21461.268 | G5: ='Tesla Revenue Automotive'!G11+'Revenue Energy, service & Other'!G7 -> 24578 | H5: ='Tesla Revenue Automotive'!H11+'Revenue Energy, service & Other'!H7 -> 38391.953 | I5: ='Tesla Revenue Automotive'!I11+'Revenue Energy, service & Other'!I7 -> 51006.612 | J5: ='Tesla Revenue Automotive'!J11+'Revenue Energy, service & Other'!J7 -> 69356.386 | ... Q5: ='Tesla Revenue Automotive'!Q11+'Revenue Energy, service & Other'!Q7 -> 135626.2
B6: Cost of sales | C6: ='Tesla Cost of sales Automotive'!C11+'COGS Energy, Services & Other'!C7 -> -3122.522 | D6: ='Tesla Cost of sales Automotive'!D11+'COGS Energy, Services & Other'!D7 -> -5400.875 | E6: ='Tesla Cost of sales Automotive'!E11+'COGS Energy, Services & Other'!E7 -> -9536.264 | F6: ='Tesla Cost of sales Automotive'!F11+'COGS Energy, Services & Other'!F7 -> -17419.247 | G6: ='Tesla Cost of sales Automotive'!G11+'COGS Energy, Services & Other'!G7 -> -20509 | H6: ='Tesla Cost of sales Automotive'!H11+'COGS Energy, Services & Other'!H7 -> -30229.816 | I6: ='Tesla Cost of sales Automotive'!I11+'COGS Energy, Services & Other'!I7 -> -40578.18 | J6: ='Tesla Cost of sales Automotive'!J11+'COGS Energy, Services & Other'!J7 -> -55444.658 | ... Q6: ='Tesla Cost of sales Automotive'!Q11+'COGS Energy, Services & Other'!Q7 -> -109137.94
B7: Gross profit | C7: =SUM(C5:C6) -> 923.503 | D7: =SUM(D5:D6) -> 1599.257 | E7: =SUM(E5:E6) -> 2222.487 | F7: =SUM(F5:F6) -> 4042.021 | G7: =SUM(G5:G6) -> 4069 | H7: =SUM(H5:H6) -> 8162.1372 | I7: =SUM(I5:I6) -> 10428.432 | J7: =SUM(J5:J6) -> 13911.728 | ... Q7: =SUM(Q5:Q6) -> 26488.251
B8: Operating expenses | C8: ='Tesla Opex'!C7 -> -1640.132 | D8: ='Tesla Opex'!D7 -> -2266.597 | E8: ='Tesla Opex'!E7 -> -3854.573 | F8: ='Tesla Opex'!F7 -> -4430.094 | G8: ='Tesla Opex'!G7 -> -4138 | H8: ='Tesla Opex'!H7 -> -4480.5231 | I8: ='Tesla Opex'!I7 -> -5952.7137 | J8: ='Tesla Opex'!J7 -> -8094.2194 | ... Q8: ='Tesla Opex'!Q7 -> -15828.221
B9: EBIT | C9: =SUM(C7:C8) -> -716.629 | D9: =SUM(D7:D8) -> -667.34 | E9: =SUM(E7:E8) -> -1632.086 | F9: =SUM(F7:F8) -> -388.073 | G9: =SUM(G7:G8) -> -69 | H9: =SUM(H7:H8) -> 3681.614 | I9: =SUM(I7:I8) -> 4475.7186 | J9: =SUM(J7:J8) -> 5817.5087 | ... Q9: =SUM(Q7:Q8) -> 10660.03
B10: Interest expenses/income | C10: ='Tesla Financing '!C12+('P&L Input'!C16+'P&L Input'!C18)/1000 -> -158.995 | D10: ='Tesla Financing '!D12+('P&L Input'!D16+'P&L Input'!D18)/1000 -> -79.008 | E10: ='Tesla Financing '!E12+('P&L Input'!E16+'P&L Input'!E18)/1000 -> -576.946 | F10: ='Tesla Financing '!F12+('P&L Input'!F16+'P&L Input'!F18)/1000 -> -616.672 | G10: ='Tesla Financing '!G12+('P&L Input'!G16+'P&L Input'!G18)/1000 -> -596 | H10: ='Tesla Financing '!H12 -> -503.05416 | I10: ='Tesla Financing '!I12 -> -503.05416 | J10: ='Tesla Financing '!J12 -> -503.05416 | K10: ='Tesla Financing '!K12 -> -503.05416 | L10: ='Tesla Financing '!L12 -> -503.05416 | M10: ='Tesla Financing '!M12 -> -503.05416 | N10: ='Tesla Financing '!N12 -> -503.05416 | O10: ='Tesla Financing '!O12 -> -503.05416 | ... Q10: ='Tesla Financing '!Q12 -> -503.05416
B11: EBT | C11: =SUM(C9:C10) -> -875.624 | D11: =SUM(D9:D10) -> -746.348 | E11: =SUM(E9:E10) -> -2209.032 | F11: =SUM(F9:F10) -> -1004.745 | G11: =SUM(G9:G10) -> -665 | H11: =SUM(H9:H10) -> 3178.5599 | I11: =SUM(I9:I10) -> 3972.6645 | J11: =SUM(J9:J10) -> 5314.4545 | ... Q11: =SUM(Q9:Q10) -> 10156.976
B12: Taxes | C12: ='P&L Input'!C20/1000 -> -13.039 | D12: ='P&L Input'!D20/1000 -> -26.698 | E12: ='P&L Input'!E20/1000 -> -31.546 | F12: ='P&L Input'!F20/1000 -> -57.837 | G12: ='P&L Input'!G20/1000 -> -110 | H12: =-H11*Drivers!$C$12 -> -667.49757 | I12: =-I11*Drivers!$C$12 -> -834.25954 | J12: =-J11*Drivers!$C$12 -> -1116.0354 | K12: =-K11*Drivers!$C$12 -> -1415.3922 | L12: =-L11*Drivers!$C$12 -> -1641.2039 | M12: =-M11*Drivers!$C$12 -> -1748.1126 | N12: =-N11*Drivers!$C$12 -> -1854.7819 | O12: =-O11*Drivers!$C$12 -> -1960.8137 | ... Q12: =-Q11*Drivers!$C$12 -> -2132.965
B13: Minority interest | C13: ='P&L Input'!C22/1000 -> 0 | D13: ='P&L Input'!D22/1000 -> 98.132 | E13: ='P&L Input'!E22/1000 -> 279.178 | F13: ='P&L Input'!F22/1000 -> 86.491 | G13: ='P&L Input'!G22/1000 -> -87 | H13: 0 | I13: 0 | J13: 0 | K13: 0 | L13: 0 | M13: 0 | N13: 0 | O13: 0 | P13: 0 | Q13: 0
B14: Net Income | C14: =SUM(C11:C13) -> -888.663 | D14: =SUM(D11:D13) -> -674.914 | E14: =SUM(E11:E13) -> -1961.4 | F14: =SUM(F11:F13) -> -976.091 | G14: =SUM(G11:G13) -> -862 | H14: =SUM(H11:H12) -> 2511.0623 | I14: =SUM(I11:I12) -> 3138.4049 | J14: =SUM(J11:J12) -> 4198.4191 | K14: =SUM(K11:K12) -> 5324.5708 | L14: =SUM(L11:L12) -> 6174.0526 | M14: =SUM(M11:M12) -> 6576.2331 | N14: =SUM(N11:N12) -> 6977.513 | O14: =SUM(O11:O12) -> 7376.3944 | ... Q14: =SUM(Q11:Q12) -> 8024.0113
B16: Check
B17: Net income | C17: ='P&L Input'!C23/1000 -> -888.663 | D17: ='P&L Input'!D23/1000 -> -674.914 | E17: ='P&L Input'!E23/1000 -> -1961.4 | F17: ='P&L Input'!F23/1000 -> -976.091 | G17: ='P&L Input'!G23/1000 -> -862
C18: =C14-C17 -> 0 | D18: =D14-D17 -> 0 | E18: =E14-E17 -> 0 | F18: =F14-F17 -> -3.0695446e-12 | G18: =G14-G17 -> 0

Sheet Balance Sheet 
B1: Tesla Balance Sheet
B3: Tesla Balance Sheet (in mln $)
B4: ($ in million) | C4: 31Dec2015 Act | D4: 31Dec2016 Act | E4: 31Dec2017 Act | F4: 31Dec2018 Act | G4: 31Dec2019 Act | H4: 31Dec2020 Fcst | I4: 31Dec2021 Fcst | J4: 31Dec2022 Fcst | K4: 31Dec2023 Fcst | L4: 31Dec2024 Fcst | M4: 31Dec2025 Fcst | N4: 31Dec2026 Fcst | O4: 31Dec2027 Fcst | P4: 31Dec2028 Fcst | Q4: 31Dec2029 Fcst | S4: Assumption
B5: Cash | C5: ='Balance Sheet Input'!C4/1000 -> 1196.908 | D5: ='Balance Sheet Input'!D4/1000 -> 3393.216 | E5: ='Balance Sheet Input'!E4/1000 -> 3367.914 | F5: ='Balance Sheet Input'!F4/1000 -> 3685.618 | G5: ='Balance Sheet Input'!G4/1000 -> 6268 | H5: =G5+'Cash Flow '!H28 -> 10955.798 | I5: =H5+'Cash Flow '!I28 -> 16386.443 | J5: =I5+'Cash Flow '!J28 -> 24331.627 | K5: =J5+'Cash Flow '!K28 -> 33894.565 | L5: =K5+'Cash Flow '!L28 -> 42786.483 | M5: =L5+'Cash Flow '!M28 -> 50976.497 | N5: =M5+'Cash Flow '!N28 -> 59774.69 | O5: =N5+'Cash Flow '!O28 -> 69279.659 | ... Q5: =P5+'Cash Flow '!Q28 -> 88511.841 | S5: Cash flow sheet
B6: Restricted cash and securities | C6: ='Balance Sheet Input'!C5/1000 -> 22.628 | D6: ='Balance Sheet Input'!D5/1000 -> 105.519 | E6: ='Balance Sheet Input'!E5/1000 -> 155.323 | F6: ='Balance Sheet Input'!F5/1000 -> 192.551 | G6: ='Balance Sheet Input'!G5/1000 -> 246 | H6: =G6 -> 246 | I6: =H6 -> 246 | J6: =I6 -> 246 | K6: =J6 -> 246 | L6: =K6 -> 246 | M6: =L6 -> 246 | N6: =M6 -> 246 | O6: =N6 -> 246 | ... Q6: =P6 -> 246 | S6: Stays flat
B7: Trade receivables | C7: ='Balance Sheet Input'!C6/1000 -> 168.965 | D7: ='Balance Sheet Input'!D6/1000 -> 499.142 | E7: ='Balance Sheet Input'!E6/1000 -> 515.381 | F7: ='Balance Sheet Input'!F6/1000 -> 949.022 | G7: ='Balance Sheet Input'!G6/1000 -> 1324 | H7: ='Tesla Working capital '!H5 -> 1957.8706 | I7: ='Tesla Working capital '!I5 -> 2601.1791 | J7: ='Tesla Working capital '!J5 -> 3536.9607 | K7: ='Tesla Working capital '!K5 -> 4551.9616 | L7: ='Tesla Working capital '!L5 -> 5204.2342 | M7: ='Tesla Working capital '!M5 -> 5577.3916 | N7: ='Tesla Working capital '!N5 -> 5944.7471 | O7: ='Tesla Working capital '!O5 -> 6318.988 | ... Q7: ='Tesla Working capital '!Q5 -> 6916.5156 | S7: Working capital sheet
B8: Inventory | C8: ='Balance Sheet Input'!C7/1000 -> 1277.838 | D8: ='Balance Sheet Input'!D7/1000 -> 2067.454 | E8: ='Balance Sheet Input'!E7/1000 -> 2263.537 | F8: ='Balance Sheet Input'!F7/1000 -> 3113.446 | G8: ='Balance Sheet Input'!G7/1000 -> 3552 | H8: ='Tesla Working capital '!H6 -> 8351.4201 | I8: ='Tesla Working capital '!I6 -> 11210.304 | J8: ='Tesla Working capital '!J6 -> 15317.382 | K8: ='Tesla Working capital '!K6 -> 19780.4 | L8: ='Tesla Working capital '!L6 -> 22604.495 | M8: ='Tesla Working capital '!M6 -> 24249.431 | N8: ='Tesla Working capital '!N6 -> 25866.919 | O8: ='Tesla Working capital '!O6 -> 27518.193 | ... Q8: ='Tesla Working capital '!Q6 -> 30150.922 | S8: Working capital sheet
B9: Prepaid expenses | C9: ='Balance Sheet Input'!C8/1000 -> 115.667 | D9: ='Balance Sheet Input'!D8/1000 -> 194.465 | E9: ='Balance Sheet Input'!E8/1000 -> 268.365 | F9: ='Balance Sheet Input'!F8/1000 -> 365.671 | G9: ='Balance Sheet Input'!G8/1000 -> 713 | H9: =H10*'P&L '!H5 -> 883.9427 | I9: =I10*'P&L '!I5 -> 1174.3847 | J9: =J10*'P&L '!J5 -> 1596.8729 | K9: =K10*'P&L '!K5 -> 2055.1272 | L9: =L10*'P&L '!L5 -> 2349.6164 | M9: =M10*'P&L '!M5 -> 2518.0901 | N9: =N10*'P&L '!N5 -> 2683.9444 | O9: =O10*'P&L '!O5 -> 2852.9073 | ... Q9: =Q10*'P&L '!Q5 -> 3122.68 | S9: Grows as a % of revenues
B10: as a % of revenues | C10: =C9/'P&L '!C5 -> 0.028587811 | D10: =D9/'P&L '!D5 -> 0.02778019 | E10: =E9/'P&L '!E5 -> 0.022822577 | F10: =F9/'P&L '!F5 -> 0.017038648 | G10: =G9/'P&L '!G5 -> 0.029009683 | H10: =AVERAGE($F$10:$G$10) -> 0.023024166 | I10: =AVERAGE($F$10:$G$10) -> 0.023024166 | J10: =AVERAGE($F$10:$G$10) -> 0.023024166 | K10: =AVERAGE($F$10:$G$10) -> 0.023024166 | L10: =AVERAGE($F$10:$G$10) -> 0.023024166 | M10: =AVERAGE($F$10:$G$10) -> 0.023024166 | N10: =AVERAGE($F$10:$G$10) -> 0.023024166 | O10: =AVERAGE($F$10:$G$10) -> 0.023024166 | ... Q10: =AVERAGE($F$10:$G$10) -> 0.023024166
B11: Operating lease vehicles | C11: =('Balance Sheet Input'!C10)/1000+('Balance Sheet Input'!C13)/1000 -> 1791.403 | D11: =('Balance Sheet Input'!D10)/1000+('Balance Sheet Input'!D13)/1000 -> 3134.08 | E11: =('Balance Sheet Input'!E10)/1000+('Balance Sheet Input'!E13)/1000 -> 4116.604 | F11: =('Balance Sheet Input'!F10)/1000+('Balance Sheet Input'!F13)/1000 -> 2089.758 | G11: =('Balance Sheet Input'!G10)/1000+('Balance Sheet Input'!G13)/1000 -> 3665 | H11: =$G$11 -> 3665 | I11: =$G$11 -> 3665 | J11: =$G$11 -> 3665 | K11: =$G$11 -> 3665 | L11: =$G$11 -> 3665 | M11: =$G$11 -> 3665 | N11: =$G$11 -> 3665 | O11: =$G$11 -> 3665 | ... Q11: =$G$11 -> 3665 | S11: Stays flat
B12: Solar energy systems leased | C12: ='Balance Sheet Input'!C11/1000 -> 0 | D12: ='Balance Sheet Input'!D11/1000 -> 5919.88 | E12: ='Balance Sheet Input'!E11/1000 -> 6347.49 | F12: ='Balance Sheet Input'!F11/1000 -> 6271.396 | G12: ='Balance Sheet Input'!G11/1000 -> 6138 | H12: =$G$12 -> 6138 | I12: =$G$12 -> 6138 | J12: =$G$12 -> 6138 | K12: =$G$12 -> 6138 | L12: =$G$12 -> 6138 | M12: =$G$12 -> 6138 | N12: =$G$12 -> 6138 | O12: =$G$12 -> 6138 | ... Q12: =$G$12 -> 6138 | S12: Stays flat
B13: PP&E | C13: ='Balance Sheet Input'!C12/1000 -> 3403.334 | D13: ='Balance Sheet Input'!D12/1000 -> 5982.957 | E13: ='Balance Sheet Input'!E12/1000 -> 10027.522 | F13: ='Balance Sheet Input'!F12/1000 -> 11330.077 | G13: ='Balance Sheet Input'!G12/1000 -> 10396 | H13: ='Tesla PP&E'!H10 -> 11153.095 | I13: ='Tesla PP&E'!I10 -> 11841.403 | J13: ='Tesla PP&E'!J10 -> 12434.497 | K13: ='Tesla PP&E'!K10 -> 12902.704 | L13: ='Tesla PP&E'!L10 -> 13213.052 | M13: ='Tesla PP&E'!M10 -> 13329.266 | N13: ='Tesla PP&E'!N10 -> 13211.838 | O13: ='Tesla PP&E'!O10 -> 12818.155 | ... Q13: ='Tesla PP&E'!Q10 -> 12106.759 | S13: PP&E sheet
B14: Intangible assets | C14: ='Balance Sheet Input'!C14/1000 -> 12.816 | D14: ='Balance Sheet Input'!D14/1000 -> 376.145 | E14: ='Balance Sheet Input'!E14/1000 -> 361.502 | F14: ='Balance Sheet Input'!F14/1000 -> 282.492 | G14: ='Balance Sheet Input'!G14/1000 -> 339 | H14: =$G$14 -> 339 | I14: =$G$14 -> 339 | J14: =$G$14 -> 339 | K14: =$G$14 -> 339 | L14: =$G$14 -> 339 | M14: =$G$14 -> 339 | N14: =$G$14 -> 339 | O14: =$G$14 -> 339 | ... Q14: =$G$14 -> 339 | S14: Stays flat
B15: Other assets | C15: =('Balance Sheet Input'!C15+'Balance Sheet Input'!C16+'Balance Sheet Input'!C17)/1000 -> 78.38 | D15: =('Balance Sheet Input'!D15+'Balance Sheet Input'!D16+'Balance Sheet Input'!D17)/1000 -> 991.218 | E15: =('Balance Sheet Input'!E15+'Balance Sheet Input'!E16+'Balance Sheet Input'!E17)/1000 -> 1231.734 | F15: =('Balance Sheet Input'!F15+'Balance Sheet Input'!F16+'Balance Sheet Input'!F17)/1000 -> 1459.583 | G15: =('Balance Sheet Input'!G15+'Balance Sheet Input'!G16+'Balance Sheet Input'!G17)/1000 -> 1668 | H15: =H16*'P&L '!H5 -> 2608.2662 | I15: =I16*'P&L '!I5 -> 3465.2788 | J15: =J16*'P&L '!J5 -> 4711.9228 | K15: =K16*'P&L '!K5 -> 6064.1023 | L15: =L16*'P&L '!L5 -> 6933.0569 | M15: =M16*'P&L '!M5 -> 7430.1755 | N15: =N16*'P&L '!N5 -> 7919.5648 | O15: =O16*'P&L '!O5 -> 8418.1268 | ... Q15: =Q16*'P&L '!Q5 -> 9214.1502 | S15: Grows as a % of revenues
B16: as a % of revenues | C16: =C15/'P&L '!C5 -> 0.0193721 | D16: =D15/'P&L '!D5 -> 0.1415999 | E16: =E15/'P&L '!E5 -> 0.10475041 | F16: =F15/'P&L '!F5 -> 0.068010101 | G16: =G15/'P&L '!G5 -> 0.067865571 | H16: =AVERAGE($F$16:$G$16) -> 0.067937836 | I16: =AVERAGE($F$16:$G$16) -> 0.067937836 | J16: =AVERAGE($F$16:$G$16) -> 0.067937836 | K16: =AVERAGE($F$16:$G$16) -> 0.067937836 | L16: =AVERAGE($F$16:$G$16) -> 0.067937836 | M16: =AVERAGE($F$16:$G$16) -> 0.067937836 | N16: =AVERAGE($F$16:$G$16) -> 0.067937836 | O16: =AVERAGE($F$16:$G$16) -> 0.067937836 | ... Q16: =AVERAGE($F$16:$G$16) -> 0.067937836
B17: Total assets | C17: =C5+C6+C7+C8+C9+C11+C12+C13+C14+C15 -> 8067.939 | D17: =D5+D6+D7+D8+D9+D11+D12+D13+D14+D15 -> 22664.076 | E17: =E5+E6+E7+E8+E9+E11+E12+E13+E14+E15 -> 28655.372 | F17: =F5+F6+F7+F8+F9+F11+F12+F13+F14+F15 -> 29739.614 | G17: =G5+G6+G7+G8+G9+G11+G12+G13+G14+G15 -> 34309 | H17: =H5+H6+H7+H8+H9+H11+H12+H13+H14+H15 -> 46298.393 | I17: =I5+I6+I7+I8+I9+I11+I12+I13+I14+I15 -> 57066.993 | J17: =J5+J6+J7+J8+J9+J11+J12+J13+J14+J15 -> 72317.262 | ... Q17: =Q5+Q6+Q7+Q8+Q9+Q11+Q12+Q13+Q14+Q15 -> 160410.87
B19: Accounts payable | C19: ='Balance Sheet Input'!C19/1000 -> 916.148 | D19: ='Balance Sheet Input'!D19/1000 -> 1860.341 | E19: ='Balance Sheet Input'!E19/1000 -> 2390.25 | F19: ='Balance Sheet Input'!F19/1000 -> 3404.451 | G19: ='Balance Sheet Input'!G19/1000 -> 3771 | H19: ='Tesla Working capital '!H7 -> 7665.1488 | I19: ='Tesla Working capital '!I7 -> 10289.106 | J19: ='Tesla Working capital '!J7 -> 14058.688 | K19: ='Tesla Working capital '!K7 -> 18154.961 | L19: ='Tesla Working capital '!L7 -> 20746.989 | M19: ='Tesla Working capital '!M7 -> 22256.753 | N19: ='Tesla Working capital '!N7 -> 23741.325 | O19: ='Tesla Working capital '!O7 -> 25256.907 | ... Q19: ='Tesla Working capital '!Q7 -> 27673.294 | S19: Working capital sheet
B20: Accrued liabilities | C20: ='Balance Sheet Input'!C20/1000 -> 422.798 | D20: ='Balance Sheet Input'!D20/1000 -> 1210.028 | E20: ='Balance Sheet Input'!E20/1000 -> 1731.366 | F20: ='Balance Sheet Input'!F20/1000 -> 2094.253 | G20: ='Balance Sheet Input'!G20/1000 -> 2905 | H20: =H21*'P&L '!H5 -> 4142.0703 | I20: =I21*'P&L '!I5 -> 5503.0535 | J20: =J21*'P&L '!J5 -> 7482.7927 | K20: =K21*'P&L '!K5 -> 9630.1281 | L20: =L21*'P&L '!L5 -> 11010.076 | M20: =M21*'P&L '!M5 -> 11799.528 | N20: =N21*'P&L '!N5 -> 12576.705 | O20: =O21*'P&L '!O5 -> 13368.449 | ... Q20: =Q21*'P&L '!Q5 -> 14632.578 | S20: Grows as a % of revenues
B21: as a % of revenues | C21: =C20/'P&L '!C5 -> 0.10449713 | D21: =D20/'P&L '!D5 -> 0.17285788 | E21: =E20/'P&L '!E5 -> 0.14724064 | F21: =F20/'P&L '!F5 -> 0.097582911 | G21: =G20/'P&L '!G5 -> 0.11819513 | H21: =AVERAGE($F$21:$G$21) -> 0.10788902 | I21: =AVERAGE($F$21:$G$21) -> 0.10788902 | J21: =AVERAGE($F$21:$G$21) -> 0.10788902 | K21: =AVERAGE($F$21:$G$21) -> 0.10788902 | L21: =AVERAGE($F$21:$G$21) -> 0.10788902 | M21: =AVERAGE($F$21:$G$21) -> 0.10788902 | N21: =AVERAGE($F$21:$G$21) -> 0.10788902 | O21: =AVERAGE($F$21:$G$21) -> 0.10788902 | ... Q21: =AVERAGE($F$21:$G$21) -> 0.10788902
B22: Deferred revenue | C22: ='Balance Sheet Input'!C21/1000 -> 423.961 | D22: ='Balance Sheet Input'!D21/1000 -> 763.126 | E22: ='Balance Sheet Input'!E21/1000 -> 1015.253 | F22: ='Balance Sheet Input'!F21/1000 -> 630.292 | G22: ='Balance Sheet Input'!G21/1000 -> 1163 | H22: =H23*'P&L '!H5 -> 1472.0925 | I22: =I23*'P&L '!I5 -> 1955.7862 | J22: =J23*'P&L '!J5 -> 2659.3858 | K22: =K23*'P&L '!K5 -> 3422.5492 | L22: =L23*'P&L '!L5 -> 3912.9829 | M22: =M23*'P&L '!M5 -> 4193.5542 | N22: =N23*'P&L '!N5 -> 4469.7631 | O22: =O23*'P&L '!O5 -> 4751.149 | ... Q22: =Q23*'P&L '!Q5 -> 5200.4207 | S22: Grows as a % of revenues
B23: as a % of revenues | C23: =C22/'P&L '!C5 -> 0.10478457 | D23: =D22/'P&L '!D5 -> 0.10901594 | E23: =E22/'P&L '!E5 -> 0.086340207 | F23: =F22/'P&L '!F5 -> 0.029368815 | G23: =G22/'P&L '!G5 -> 0.04731874 | H23: =AVERAGE($F$23:$G$23) -> 0.038343777 | I23: =AVERAGE($F$23:$G$23) -> 0.038343777 | J23: =AVERAGE($F$23:$G$23) -> 0.038343777 | K23: =AVERAGE($F$23:$G$23) -> 0.038343777 | L23: =AVERAGE($F$23:$G$23) -> 0.038343777 | M23: =AVERAGE($F$23:$G$23) -> 0.038343777 | N23: =AVERAGE($F$23:$G$23) -> 0.038343777 | O23: =AVERAGE($F$23:$G$23) -> 0.038343777 | ... Q23: =AVERAGE($F$23:$G$23) -> 0.038343777
B24: Resale value guarantees | C24: ='Balance Sheet Input'!C22/1000 -> 136.831 | D24: ='Balance Sheet Input'!D22/1000 -> 179.504 | E24: ='Balance Sheet Input'!E22/1000 -> 787.333 | F24: ='Balance Sheet Input'!F22/1000 -> 502.84 | G24: ='Balance Sheet Input'!G22/1000 -> 317 | H24: =H25*'P&L '!H5 -> 697.34816 | I24: =I25*'P&L '!I5 -> 926.47975 | J24: =J25*'P&L '!J5 -> 1259.7835 | K24: =K25*'P&L '!K5 -> 1621.3033 | L24: =L25*'P&L '!L5 -> 1853.6277 | M24: =M25*'P&L '!M5 -> 1986.5377 | N24: =N25*'P&L '!N5 -> 2117.3812 | O24: =O25*'P&L '!O5 -> 2250.6772 | ... R24: =R25*'P&L '!R5 -> 0 | S24: Grows as a % of revenues
B25: as a % of revenues | C25: ='Balance Sheet '!C24/'P&L '!C5 -> 0.033818624 | D25: ='Balance Sheet '!D24/'P&L '!D5 -> 0.025642945 | E25: ='Balance Sheet '!E24/'P&L '!E5 -> 0.066957196 | F25: ='Balance Sheet '!F24/'P&L '!F5 -> 0.023430116 | G25: ='Balance Sheet '!G24/'P&L '!G5 -> 0.012897713 | H25: =AVERAGE($F$25:$G$25) -> 0.018163915 | I25: =AVERAGE($F$25:$G$25) -> 0.018163915 | J25: =AVERAGE($F$25:$G$25) -> 0.018163915 | K25: =AVERAGE($F$25:$G$25) -> 0.018163915 | L25: =AVERAGE($F$25:$G$25) -> 0.018163915 | M25: =AVERAGE($F$25:$G$25) -> 0.018163915 | N25: =AVERAGE($F$25:$G$25) -> 0.018163915 | O25: =AVERAGE($F$25:$G$25) -> 0.018163915 | ... Q25: =AVERAGE($F$25:$G$25) -> 0.018163915
B26: Customer deposits | C26: ='Balance Sheet Input'!C23/1000 -> 283.37 | D26: ='Balance Sheet Input'!D23/1000 -> 663.859 | E26: ='Balance Sheet Input'!E23/1000 -> 853.919 | F26: ='Balance Sheet Input'!F23/1000 -> 792.601 | G26: ='Balance Sheet Input'!G23/1000 -> 726 | H26: =H27*'P&L '!H5 -> 1275.9624 | I26: =I27*'P&L '!I5 -> 1695.2126 | J26: =J27*'P&L '!J5 -> 2305.0701 | K26: =K27*'P&L '!K5 -> 2966.5556 | L26: =L27*'P&L '!L5 -> 3391.6477 | M26: =M27*'P&L '!M5 -> 3634.8379 | N26: =N27*'P&L '!N5 -> 3874.2469 | O26: =O27*'P&L '!O5 -> 4118.1432 | ... Q26: =Q27*'P&L '!Q5 -> 4507.5574 | S26: Grows as a % of revenues
B27: as a % of revenues | C27: =C26/'P&L '!C5 -> 0.070036641 | D27: =D26/'P&L '!D5 -> 0.094835212 | E27: =E26/'P&L '!E5 -> 0.072619873 | F27: =F26/'P&L '!F5 -> 0.036931695 | G27: =G26/'P&L '!G5 -> 0.029538612 | H27: =AVERAGE($F$27:$G$27) -> 0.033235153 | I27: =AVERAGE($F$27:$G$27) -> 0.033235153 | J27: =AVERAGE($F$27:$G$27) -> 0.033235153 | K27: =AVERAGE($F$27:$G$27) -> 0.033235153 | L27: =AVERAGE($F$27:$G$27) -> 0.033235153 | M27: =AVERAGE($F$27:$G$27) -> 0.033235153 | N27: =AVERAGE($F$27:$G$27) -> 0.033235153 | O27: =AVERAGE($F$27:$G$27) -> 0.033235153 | ... Q27: =AVERAGE($F$27:$G$27) -> 0.033235153
B28: Long-term debt | C28: =('Balance Sheet Input'!C24+'Balance Sheet Input'!C29)/1000 -> 2649.02 | D28: =('Balance Sheet Input'!D24+'Balance Sheet Input'!D29)/1000 -> 6844.26 | E28: =('Balance Sheet Input'!E24+'Balance Sheet Input'!E29)/1000 -> 10212.249 | F28: =('Balance Sheet Input'!F24+'Balance Sheet Input'!F29)/1000 -> 11971.371 | G28: =('Balance Sheet Input'!G24+'Balance Sheet Input'!G29)/1000 -> 13419 | H28: =G28+'Tesla Financing '!H19 -> 13419 | I28: =H28+'Tesla Financing '!I19 -> 13419 | J28: =I28+'Tesla Financing '!J19 -> 13419 | K28: =J28+'Tesla Financing '!K19 -> 13419 | L28: =K28+'Tesla Financing '!L19 -> 13419 | M28: =L28+'Tesla Financing '!M19 -> 13419 | N28: =M28+'Tesla Financing '!N19 -> 13419 | O28: =N28+'Tesla Financing '!O19 -> 13419 | ... Q28: =P28+'Tesla Financing '!Q19 -> 13419 | S28: Financing sheet
B29: Other liabilities | C29: =('Balance Sheet Input'!C30+'Balance Sheet Input'!C26)/1000 -> 2152.107 | D29: =('Balance Sheet Input'!D30+'Balance Sheet Input'!D26)/1000 -> 5604.872 | E29: =('Balance Sheet Input'!E30+'Balance Sheet Input'!E26)/1000 -> 6430.414 | F29: =('Balance Sheet Input'!F30+'Balance Sheet Input'!F26)/1000 -> 4586.166 | G29: =('Balance Sheet Input'!G30+'Balance Sheet Input'!G26)/1000 -> 4541 | H29: =H30*'P&L '!H5 -> 7648.7087 | I29: =I30*'P&L '!I5 -> 10161.888 | J29: =J30*'P&L '!J5 -> 13817.656 | K29: =K30*'P&L '!K5 -> 17782.906 | L29: =L30*'P&L '!L5 -> 20331.104 | M29: =M30*'P&L '!M5 -> 21788.899 | N29: =N30*'P&L '!N5 -> 23224.027 | O29: =O30*'P&L '!O5 -> 24686.054 | ... Q29: =Q30*'P&L '!Q5 -> 27020.383 | S29: Grows as a % of revenues
B30: as a % of revenues | C30: =C29/'P&L '!C5 -> 0.5319065 | D30: =D29/'P&L '!D5 -> 0.8006809 | E30: =E29/'P&L '!E5 -> 0.54686199 | F30: =F29/'P&L '!F5 -> 0.21369502 | G30: =G29/'P&L '!G5 -> 0.18475873 | H30: =AVERAGE($F$30:$G$30) -> 0.19922687 | I30: =AVERAGE($F$30:$G$30) -> 0.19922687 | J30: =AVERAGE($F$30:$G$30) -> 0.19922687 | K30: =AVERAGE($F$30:$G$30) -> 0.19922687 | L30: =AVERAGE($F$30:$G$30) -> 0.19922687 | M30: =AVERAGE($F$30:$G$30) -> 0.19922687 | N30: =AVERAGE($F$30:$G$30) -> 0.19922687 | O30: =AVERAGE($F$30:$G$30) -> 0.19922687 | ... Q30: =AVERAGE($F$30:$G$30) -> 0.19922687
B31: Total liabilities | C31: =C19+C20+C22+C24+C26+C28+C29 -> 6984.235 | D31: =D19+D20+D22+D24+D26+D28+D29 -> 17125.99 | E31: =E19+E20+E22+E24+E26+E28+E29 -> 23420.784 | F31: =F19+F20+F22+F24+F26+F28+F29 -> 23981.974 | G31: =G19+G20+G22+G24+G26+G28+G29 -> 26842 | H31: =H19+H20+H22+H24+H26+H28+H29 -> 36320.331 | I31: =I19+I20+I22+I24+I26+I28+I29 -> 43950.526 | J31: =J19+J20+J22+J24+J26+J28+J29 -> 55002.376 | ... Q31: =Q19+Q20+Q22+Q24+Q26+Q28+Q29 -> 94916.735
B32: Equity | C32: =('Balance Sheet Input'!C32+'Balance Sheet Input'!C33)/1000 -> 1083.704 | D32: =('Balance Sheet Input'!D32+'Balance Sheet Input'!D33)/1000 -> 5538.086 | E32: =('Balance Sheet Input'!E32+'Balance Sheet Input'!E33)/1000 -> 5234.588 | F32: =('Balance Sheet Input'!F32+'Balance Sheet Input'!F33)/1000 -> 5757.64 | G32: =('Balance Sheet Input'!G32+'Balance Sheet Input'!G33)/1000 -> 7467 | H32: =G32+'Tesla Financing '!H20+'P&L '!H14 -> 9978.0623 | I32: =H32+'Tesla Financing '!I20+'P&L '!I14 -> 13116.467 | J32: =I32+'Tesla Financing '!J20+'P&L '!J14 -> 17314.886 | K32: =J32+'Tesla Financing '!K20+'P&L '!K14 -> 22639.457 | L32: =K32+'Tesla Financing '!L20+'P&L '!L14 -> 28813.51 | M32: =L32+'Tesla Financing '!M20+'P&L '!M14 -> 35389.743 | N32: =M32+'Tesla Financing '!N20+'P&L '!N14 -> 42367.256 | O32: =N32+'Tesla Financing '!O20+'P&L '!O14 -> 49743.65 | ... Q32: =P32+'Tesla Financing '!Q20+'P&L '!Q14 -> 65494.133
B34: Total liabilities & equity | C34: =C31+C32 -> 8067.939 | D34: =D31+D32 -> 22664.076 | E34: =E31+E32 -> 28655.372 | F34: =F31+F32 -> 29739.614 | G34: =G31+G32 -> 34309 | H34: =H31+H32 -> 46298.393 | I34: =I31+I32 -> 57066.993 | J34: =J31+J32 -> 72317.262 | ... Q34: =Q31+Q32 -> 160410.87
B36: Check | C36: =C17-C34 -> 0 | D36: =D17-D34 -> 0 | E36: =E17-E34 -> 0 | F36: =F17-F34 -> 0 | G36: =G17-G34 -> 0 | H36: =H17-H34 -> 0 | I36: =I17-I34 -> 0 | J36: =J17-J34 -> 0 | ... Q36: =Q17-Q34 -> 0

Sheet Cash Flow 
B1: Tesla Cash Flow
B3: Tesla Cash Flow (in mln $)
B4: ($ in million) | C4: 2015 Act | D4: 2016 Act | E4: 2017 Act | F4: 2018 Act | G4: 2019 Act | H4: 2020 Fcst | I4: 2021 Fcst | J4: 2022 Fcst | K4: 2023 Fcst | L4: 2024 Fcst | M4: 2025 Fcst | N4: 2026 Fcst | O4: 2027 Fcst | P4: 2028 Fcst | Q4: 2029 Fcst
B5: EBIT | D5: ='P&L '!D9 -> -667.34 | E5: ='P&L '!E9 -> -1632.086 | F5: ='P&L '!F9 -> -388.073 | G5: ='P&L '!G9 -> -69 | H5: ='P&L '!H9 -> 3681.614 | I5: ='P&L '!I9 -> 4475.7186 | J5: ='P&L '!J9 -> 5817.5087 | K5: ='P&L '!K9 -> 7243.0172 | ... Q5: ='P&L '!Q9 -> 10660.03
B6: =CONCATENATE("Operating taxes (",([1]Drivers!$C$12*100),"%)") -> Operating taxes (21%) | D6: ='P&L '!D12 -> -26.698 | E6: ='P&L '!E12 -> -31.546 | F6: ='P&L '!F12 -> -57.837 | G6: ='P&L '!G12 -> -110 | H6: =-H5*Drivers!$C$12 -> -773.13895 | I6: =-I5*Drivers!$C$12 -> -939.90091 | J6: =-J5*Drivers!$C$12 -> -1221.6768 | K6: =-K5*Drivers!$C$12 -> -1521.0336 | L6: =-L5*Drivers!$C$12 -> -1746.8452 | M6: =-M5*Drivers!$C$12 -> -1853.754 | N6: =-N5*Drivers!$C$12 -> -1960.4233 | O6: =-O5*Drivers!$C$12 -> -2066.4551 | ... Q6: =-Q5*Drivers!$C$12 -> -2238.6064
B7: NOPAT | D7: =SUM(D5:D6) -> -694.038 | E7: =SUM(E5:E6) -> -1663.632 | F7: =SUM(F5:F6) -> -445.91 | G7: =SUM(G5:G6) -> -179 | H7: =SUM(H5:H6) -> 2908.4751 | I7: =SUM(I5:I6) -> 3535.8177 | J7: =SUM(J5:J6) -> 4595.8319 | K7: =SUM(K5:K6) -> 5721.9836 | ... Q7: =SUM(Q5:Q6) -> 8421.424
B8: Add-back D&A | D8: =-'Tesla PP&E'!D9 -> 947 | E8: =-'Tesla PP&E'!E9 -> 1636 | F8: =-'Tesla PP&E'!F9 -> 1901 | G8: =-'Tesla PP&E'!G9 -> 2154 | H8: =-'Tesla PP&E'!H9 -> 1239.2328 | I8: =-'Tesla PP&E'!I9 -> 1453.404 | J8: =-'Tesla PP&E'!J9 -> 1680.7926 | K8: =-'Tesla PP&E'!K9 -> 1919.5704 | ... Q8: =-'Tesla PP&E'!Q9 -> 3530.3112
B9: Gross Cash Flow | D9: =SUM(D7:D8) -> 252.962 | E9: =SUM(E7:E8) -> -27.632 | F9: =SUM(F7:F8) -> 1455.09 | G9: =SUM(G7:G8) -> 1975 | H9: =SUM(H7:H8) -> 4147.7079 | I9: =SUM(I7:I8) -> 4989.2217 | J9: =SUM(J7:J8) -> 6276.6245 | K9: =SUM(K7:K8) -> 7641.554 | ... Q9: =SUM(Q7:Q8) -> 11951.735
B11: Trade receivables | D11: =-('Balance Sheet '!D7-'Balance Sheet '!C7) -> -330.177 | E11: =-('Balance Sheet '!E7-'Balance Sheet '!D7) -> -16.239 | F11: =-('Balance Sheet '!F7-'Balance Sheet '!E7) -> -433.641 | G11: =-('Balance Sheet '!G7-'Balance Sheet '!F7) -> -374.978 | H11: =-('Balance Sheet '!H7-'Balance Sheet '!G7) -> -633.8706 | I11: =-('Balance Sheet '!I7-'Balance Sheet '!H7) -> -643.30851 | J11: =-('Balance Sheet '!J7-'Balance Sheet '!I7) -> -935.78158 | K11: =-('Balance Sheet '!K7-'Balance Sheet '!J7) -> -1015.0009 | ... Q11: =-('Balance Sheet '!Q7-'Balance Sheet '!P7) -> -283.6166
B12: Inventory | D12: =-('Balance Sheet '!D8-'Balance Sheet '!C8) -> -789.616 | E12: =-('Balance Sheet '!E8-'Balance Sheet '!D8) -> -196.083 | F12: =-('Balance Sheet '!F8-'Balance Sheet '!E8) -> -849.909 | G12: =-('Balance Sheet '!G8-'Balance Sheet '!F8) -> -438.554 | H12: =-('Balance Sheet '!H8-'Balance Sheet '!G8) -> -4799.4201 | I12: =-('Balance Sheet '!I8-'Balance Sheet '!H8) -> -2858.8839 | J12: =-('Balance Sheet '!J8-'Balance Sheet '!I8) -> -4107.0777 | K12: =-('Balance Sheet '!K8-'Balance Sheet '!J8) -> -4463.018 | ... Q12: =-('Balance Sheet '!Q8-'Balance Sheet '!P8) -> -1253.0709
B13: Accounts payable | D13: ='Balance Sheet '!D19-'Balance Sheet '!C19 -> 944.193 | E13: ='Balance Sheet '!E19-'Balance Sheet '!D19 -> 529.909 | F13: ='Balance Sheet '!F19-'Balance Sheet '!E19 -> 1014.201 | G13: ='Balance Sheet '!G19-'Balance Sheet '!F19 -> 366.549 | H13: ='Balance Sheet '!H19-'Balance Sheet '!G19 -> 3894.1488 | I13: ='Balance Sheet '!I19-'Balance Sheet '!H19 -> 2623.9574 | J13: ='Balance Sheet '!J19-'Balance Sheet '!I19 -> 3769.5819 | K13: ='Balance Sheet '!K19-'Balance Sheet '!J19 -> 4096.273 | ... Q13: ='Balance Sheet '!Q19-'Balance Sheet '!P19 -> 1150.1008
B14: Investments in Working Capital | D14: =SUM(D11:D13) -> -175.6 | E14: =SUM(E11:E13) -> 317.587 | F14: =SUM(F11:F13) -> -269.349 | G14: =SUM(G11:G13) -> -446.983 | H14: =SUM(H11:H13) -> -1539.142 | I14: =SUM(I11:I13) -> -878.23504 | J14: =SUM(J11:J13) -> -1273.2775 | K14: =SUM(K11:K13) -> -1381.7459 | ... Q14: =SUM(Q11:Q13) -> -386.58671
B16: Capex | D16: =-'Tesla PP&E'!D8 -> -3526.623 | E16: =-'Tesla PP&E'!E8 -> -5680.565 | F16: =-'Tesla PP&E'!F8 -> -3203.555 | G16: =-'Tesla PP&E'!G8 -> -1219.923 | H16: =-'Tesla PP&E'!H8 -> -1996.328 | I16: =-'Tesla PP&E'!I8 -> -2141.7118 | J16: =-'Tesla PP&E'!J8 -> -2273.8865 | K16: =-'Tesla PP&E'!K8 -> -2387.7775 | ... Q16: =-'Tesla PP&E'!Q8 -> -3534.3414
B17: Other assets | D17: =-('Balance Sheet '!D6-'Balance Sheet '!C6)-('Balance Sheet '!D9-'Balance Sheet '!C9)-('Balance Sheet '!D11-'Balance Sheet '!C11)-('Balance Sheet '!D12-'Balance Sheet '!C12)-('Balance Sheet '!D14-'Balance Sheet '!C14)-('Balance Sheet '!D15-'Balance Sheet '!C15) -> -8700.413 | E17: =-('Balance Sheet '!E6-'Balance Sheet '!D6)-('Balance Sheet '!E9-'Balance Sheet '!D9)-('Balance Sheet '!E11-'Balance Sheet '!D11)-('Balance Sheet '!E12-'Balance Sheet '!D12)-('Balance Sheet '!E14-'Balance Sheet '!D14)-('Balance Sheet '!E15-'Balance Sheet '!D15) -> -1759.711 | F17: =-('Balance Sheet '!F6-'Balance Sheet '!E6)-('Balance Sheet '!F9-'Balance Sheet '!E9)-('Balance Sheet '!F11-'Balance Sheet '!E11)-('Balance Sheet '!F12-'Balance Sheet '!E12)-('Balance Sheet '!F14-'Balance Sheet '!E14)-('Balance Sheet '!F15-'Balance Sheet '!E15) -> 1819.567 | G17: =-('Balance Sheet '!G6-'Balance Sheet '!F6)-('Balance Sheet '!G9-'Balance Sheet '!F9)-('Balance Sheet '!G11-'Balance Sheet '!F11)-('Balance Sheet '!G12-'Balance Sheet '!F12)-('Balance Sheet '!G14-'Balance Sheet '!F14)-('Balance Sheet '!G15-'Balance Sheet '!F15) -> -2107.549 | H17: =-('Balance Sheet '!H6-'Balance Sheet '!G6)-('Balance Sheet '!H9-'Balance Sheet '!G9)-('Balance Sheet '!H11-'Balance Sheet '!G11)-('Balance Sheet '!H12-'Balance Sheet '!G12)-('Balance Sheet '!H14-'Balance Sheet '!G14)-('Balance Sheet '!H15-'Balance Sheet '!G15) -> -1111.2089 | I17: =-('Balance Sheet '!I6-'Balance Sheet '!H6)-('Balance Sheet '!I9-'Balance Sheet '!H9)-('Balance Sheet '!I11-'Balance Sheet '!H11)-('Balance Sheet '!I12-'Balance Sheet '!H12)-('Balance Sheet '!I14-'Balance Sheet '!H14)-('Balance Sheet '!I15-'Balance Sheet '!H15) -> -1147.4546 | J17: =-('Balance Sheet '!J6-'Balance Sheet '!I6)-('Balance Sheet '!J9-'Balance Sheet '!I9)-('Balance Sheet '!J11-'Balance Sheet '!I11)-('Balance Sheet '!J12-'Balance Sheet '!I12)-('Balance Sheet '!J14-'Balance Sheet '!I14)-('Balance Sheet '!J15-'Balance Sheet '!I15) -> -1669.1322 | K17: =-('Balance Sheet '!K6-'Balance Sheet '!J6)-('Balance Sheet '!K9-'Balance Sheet '!J9)-('Balance Sheet '!K11-'Balance Sheet '!J11)-('Balance Sheet '!K12-'Balance Sheet '!J12)-('Balance Sheet '!K14-'Balance Sheet '!J14)-('Balance Sheet '!K15-'Balance Sheet '!J15) -> -1810.4338 | ... Q17: =-('Balance Sheet '!Q6-'Balance Sheet '!P6)-('Balance Sheet '!Q9-'Balance Sheet '!P9)-('Balance Sheet '!Q11-'Balance Sheet '!P11)-('Balance Sheet '!Q12-'Balance Sheet '!P12)-('Balance Sheet '!Q14-'Balance Sheet '!P14)-('Balance Sheet '!Q15-'Balance Sheet '!P15) -> -505.88043
B18: Other liabilties | D18: =('Balance Sheet '!D20-'Balance Sheet '!C20)+('Balance Sheet '!D22-'Balance Sheet '!C22)+('Balance Sheet '!D24-'Balance Sheet '!C24)+('Balance Sheet '!D26-'Balance Sheet '!C26)+('Balance Sheet '!D29-'Balance Sheet '!C29) -> 5002.322 | E18: =('Balance Sheet '!E20-'Balance Sheet '!D20)+('Balance Sheet '!E22-'Balance Sheet '!D22)+('Balance Sheet '!E24-'Balance Sheet '!D24)+('Balance Sheet '!E26-'Balance Sheet '!D26)+('Balance Sheet '!E29-'Balance Sheet '!D29) -> 2396.896 | F18: =('Balance Sheet '!F20-'Balance Sheet '!E20)+('Balance Sheet '!F22-'Balance Sheet '!E22)+('Balance Sheet '!F24-'Balance Sheet '!E24)+('Balance Sheet '!F26-'Balance Sheet '!E26)+('Balance Sheet '!F29-'Balance Sheet '!E29) -> -2212.133 | G18: =('Balance Sheet '!G20-'Balance Sheet '!F20)+('Balance Sheet '!G22-'Balance Sheet '!F22)+('Balance Sheet '!G24-'Balance Sheet '!F24)+('Balance Sheet '!G26-'Balance Sheet '!F26)+('Balance Sheet '!G29-'Balance Sheet '!F29) -> 1045.848 | H18: =('Balance Sheet '!H20-'Balance Sheet '!G20)+('Balance Sheet '!H22-'Balance Sheet '!G22)+('Balance Sheet '!H24-'Balance Sheet '!G24)+('Balance Sheet '!H26-'Balance Sheet '!G26)+('Balance Sheet '!H29-'Balance Sheet '!G29) -> 5584.1821 | I18: =('Balance Sheet '!I20-'Balance Sheet '!H20)+('Balance Sheet '!I22-'Balance Sheet '!H22)+('Balance Sheet '!I24-'Balance Sheet '!H24)+('Balance Sheet '!I26-'Balance Sheet '!H26)+('Balance Sheet '!I29-'Balance Sheet '!H29) -> 5006.2377 | J18: =('Balance Sheet '!J20-'Balance Sheet '!I20)+('Balance Sheet '!J22-'Balance Sheet '!I22)+('Balance Sheet '!J24-'Balance Sheet '!I24)+('Balance Sheet '!J26-'Balance Sheet '!I26)+('Balance Sheet '!J29-'Balance Sheet '!I29) -> 7282.2681 | K18: =('Balance Sheet '!K20-'Balance Sheet '!J20)+('Balance Sheet '!K22-'Balance Sheet '!J22)+('Balance Sheet '!K24-'Balance Sheet '!J24)+('Balance Sheet '!K26-'Balance Sheet '!J26)+('Balance Sheet '!K29-'Balance Sheet '!J29) -> 7898.7539 | ... Q18: =('Balance Sheet '!Q20-'Balance Sheet '!P20)+('Balance Sheet '!Q22-'Balance Sheet '!P22)+('Balance Sheet '!Q24-'Balance Sheet '!P24)+('Balance Sheet '!Q26-'Balance Sheet '!P26)+('Balance Sheet '!Q29-'Balance Sheet '!P29) -> 2207.1092
B20: Unlevered Free Cash Flow | D20: =D9+D14+D17+D18+D16 -> -7147.352 | E20: =E9+E14+E17+E18+E16 -> -4753.425 | F20: =F9+F14+F17+F18+F16 -> -2410.38 | G20: =G9+G14+G17+G18+G16 -> -753.607 | H20: =H9+H14+H17+H18+H16 -> 5085.2111 | I20: =I9+I14+I17+I18+I16 -> 5828.0579 | J20: =J9+J14+J17+J18+J16 -> 8342.5964 | K20: =K9+K14+K17+K18+K16 -> 9960.3508 | ... Q20: =Q9+Q14+Q17+Q18+Q16 -> 9732.036
B22: Interest expenses | D22: ='P&L '!D10 -> -79.008 | E22: ='P&L '!E10 -> -576.946 | F22: ='P&L '!F10 -> -616.672 | G22: ='P&L '!G10 -> -596 | H22: ='P&L '!H10 -> -503.05416 | I22: ='P&L '!I10 -> -503.05416 | J22: ='P&L '!J10 -> -503.05416 | K22: ='P&L '!K10 -> -503.05416 | ... Q22: ='P&L '!Q10 -> -503.05416
B23: Delta Financial liabilities | D23: ='Balance Sheet '!D28-'Balance Sheet '!C28 -> 4195.24 | E23: ='Balance Sheet '!E28-'Balance Sheet '!D28 -> 3367.989 | F23: ='Balance Sheet '!F28-'Balance Sheet '!E28 -> 1759.122 | G23: ='Balance Sheet '!G28-'Balance Sheet '!F28 -> 1447.629 | H23: ='Balance Sheet '!H28-'Balance Sheet '!G28 -> 0 | I23: ='Balance Sheet '!I28-'Balance Sheet '!H28 -> 0 | J23: ='Balance Sheet '!J28-'Balance Sheet '!I28 -> 0 | K23: ='Balance Sheet '!K28-'Balance Sheet '!J28 -> 0 | ... Q23: ='Balance Sheet '!Q28-'Balance Sheet '!P28 -> 0
B24: Delta equity/Other equity movements | D24: ='Balance Sheet '!D32-'Balance Sheet '!C32-'P&L '!D14 -> 5129.296 | E24: ='Balance Sheet '!E32-'Balance Sheet '!D32-'P&L '!E14 -> 1657.902 | F24: ='Balance Sheet '!F32-'Balance Sheet '!E32-'P&L '!F14 -> 1499.143 | G24: ='Balance Sheet '!G32-'Balance Sheet '!F32-'P&L '!G14 -> 2571.36 | H24: ='Balance Sheet '!H32-'Balance Sheet '!G32-'P&L '!H14 -> 0 | I24: ='Balance Sheet '!I32-'Balance Sheet '!H32-'P&L '!I14 -> 0 | J24: ='Balance Sheet '!J32-'Balance Sheet '!I32-'P&L '!J14 -> 0 | K24: ='Balance Sheet '!K32-'Balance Sheet '!J32-'P&L '!K14 -> 0 | ... Q24: ='Balance Sheet '!Q32-'Balance Sheet '!P32-'P&L '!Q14 -> 0
B25: Tax adjustment | D25: ='P&L '!D12-'Cash Flow '!D6 -> 0 | E25: ='P&L '!E12-'Cash Flow '!E6 -> 0 | F25: ='P&L '!F12-'Cash Flow '!F6 -> 0 | G25: ='P&L '!G12-'Cash Flow '!G6 -> 0 | H25: ='P&L '!H12-'Cash Flow '!H6 -> 105.64137 | I25: ='P&L '!I12-'Cash Flow '!I6 -> 105.64137 | J25: ='P&L '!J12-'Cash Flow '!J6 -> 105.64137 | K25: ='P&L '!K12-'Cash Flow '!K6 -> 105.64137 | ... Q25: ='P&L '!Q12-'Cash Flow '!Q6 -> 105.64137
B26: Minority interest | D26: ='P&L '!D13 -> 98.132 | E26: ='P&L '!E13 -> 279.178 | F26: ='P&L '!F13 -> 86.491 | G26: ='P&L '!G13 -> -87 | H26: ='P&L '!H13 -> 0 | I26: ='P&L '!I13 -> 0 | J26: ='P&L '!J13 -> 0 | K26: ='P&L '!K13 -> 0 | ... Q26: ='P&L '!Q13 -> 0
B28: Net Cash Flow | D28: =SUM(D20:D26) -> 2196.308 | E28: =SUM(E20:E26) -> -25.302 | F28: =SUM(F20:F26) -> 317.704 | G28: =SUM(G20:G26) -> 2582.382 | H28: =SUM(H20:H26) -> 4687.7983 | I28: =SUM(I20:I26) -> 5430.6451 | J28: =SUM(J20:J26) -> 7945.1836 | K28: =SUM(K20:K26) -> 9562.938 | ... Q28: =SUM(Q20:Q26) -> 9334.6232
B30: Opening cash | D30: =C32 -> 1196.908 | E30: =D32 -> 3393.216 | F30: =E32 -> 3367.914 | G30: =F32 -> 3685.618 | H30: =G32 -> 6268 | I30: =H32 -> 10955.798 | J30: =I32 -> 16386.443 | K30: =J32 -> 24331.627 | ... Q30: =P32 -> 79177.218
B31: Net Cash Flow | C31: =C28 -> 0 | D31: =D28 -> 2196.308 | E31: =E28 -> -25.302 | F31: =F28 -> 317.704 | G31: =G28 -> 2582.382 | H31: =H28 -> 4687.7983 | I31: =I28 -> 5430.6451 | J31: =J28 -> 7945.1836 | ... Q31: =Q28 -> 9334.6232
B32: Closing cash | C32: ='Balance Sheet '!C5 -> 1196.908 | D32: =D30+D31 -> 3393.216 | E32: =E30+E31 -> 3367.914 | F32: =F30+F31 -> 3685.618 | G32: =G30+G31 -> 6268 | H32: =H30+H31 -> 10955.798 | I32: =I30+I31 -> 16386.443 | J32: =J30+J31 -> 24331.627 | K32: =K30+K31 -> 33894.565 | ... Q32: =Q30+Q31 -> 88511.841

Sheet WACC --->
B13: WACC --->

Sheet WACC 
B1: Tesla WACC
B4: Risk-free rate | C4: =Drivers!C7 -> 0.00697
B5: Market risk premium | C5: =Drivers!C8 -> 0.05
B6: Beta (as of 27 Sep 2018) | C6: =Drivers!$C$9 -> 2.15
B7: Tax rate | C7: =Drivers!C12 -> 0.21
B9: Cost of equity | C9: =C4+C6*C5 -> 0.11447
B10: Current bond Yield as of 19th Sep | C10: =Drivers!C11 -> 0.04324
B13: Tesla WACC calculation (in mln $)
B14: ($ in million) | C14: 31Dec2015 Act | D14: 31Dec2016 Act | E14: 31Dec2017 Act | F14: 31Dec2018 Act | G14: 31Dec2019 Act | H14: 31Dec2020 Fcst | I14: 31Dec2021 Fcst | J14: 31Dec2022 Fcst | K14: 31Dec2023 Fcst | L14: 31Dec2024 Fcst | M14: 31Dec2025 Fcst | N14: 31Dec2026 Fcst | O14: 31Dec2027 Fcst | P14: 31Dec2028 Fcst | Q14: 31Dec2029 Fcst
B15: Debt | C15: ='Balance Sheet '!C28 -> 2649.02 | D15: ='Balance Sheet '!D28 -> 6844.26 | E15: ='Balance Sheet '!E28 -> 10212.249 | F15: ='Balance Sheet '!F28 -> 11971.371 | G15: ='Balance Sheet '!G28 -> 13419 | H15: ='Balance Sheet '!H28 -> 13419 | I15: ='Balance Sheet '!I28 -> 13419 | J15: ='Balance Sheet '!J28 -> 13419 | ... Q15: ='Balance Sheet '!Q28 -> 13419
B16: Equity | C16: ='Balance Sheet '!C32 -> 1083.704 | D16: ='Balance Sheet '!D32 -> 5538.086 | E16: ='Balance Sheet '!E32 -> 5234.588 | F16: ='Balance Sheet '!F32 -> 5757.64 | G16: ='Balance Sheet '!G32 -> 7467 | H16: ='Balance Sheet '!H32 -> 9978.0623 | I16: ='Balance Sheet '!I32 -> 13116.467 | J16: ='Balance Sheet '!J32 -> 17314.886 | ... Q16: ='Balance Sheet '!Q32 -> 65494.133
B18: Debt / (Debt + Equity) | C18: =C15/(C15+C16) -> 0.70967476 | D18: =D15/(D15+D16) -> 0.5527434 | E18: =E15/(E15+E16) -> 0.66112234 | F18: =F15/(F15+F16) -> 0.6752419 | G18: =G15/(G15+G16) -> 0.64248779 | H18: =H15/(H15+H16) -> 0.57353354 | I18: =I15/(I15+I16) -> 0.50570054 | J18: =J15/(J15+J16) -> 0.43661904 | ... Q18: =Q15/(Q15+Q16) -> 0.17004774
B19: Equity / (Debt + Equity) | C19: =C16/(C15+C16) -> 0.29032524 | D19: =D16/(D15+D16) -> 0.4472566 | E19: =E16/(E15+E16) -> 0.33887766 | F19: =F16/(F15+F16) -> 0.3247581 | G19: =G16/(G15+G16) -> 0.35751221 | H19: =H16/(H15+H16) -> 0.42646646 | I19: =I16/(I15+I16) -> 0.49429946 | J19: =J16/(J15+J16) -> 0.56338096 | ... Q19: =Q16/(Q15+Q16) -> 0.82995226
B21: Cost of equity | C21: =$C$9 -> 0.11447 | D21: =$C$9 -> 0.11447 | E21: =$C$9 -> 0.11447 | F21: =$C$9 -> 0.11447 | G21: =$C$9 -> 0.11447 | H21: =$C$9 -> 0.11447 | I21: =$C$9 -> 0.11447 | J21: =$C$9 -> 0.11447 | ... Q21: =$C$9 -> 0.11447
B22: Cost of debt | C22: =$C$10 -> 0.04324 | D22: =$C$10 -> 0.04324 | E22: =$C$10 -> 0.04324 | F22: =$C$10 -> 0.04324 | G22: =$C$10 -> 0.04324 | H22: =$C$10 -> 0.04324 | I22: =$C$10 -> 0.04324 | J22: =$C$10 -> 0.04324 | ... Q22: =$C$10 -> 0.04324
B24: WACC | C24: =C18*C22*(1-$C$7)+C19*C21 -> 0.057475736 | D24: =D18*D22*(1-$C$7)+D19*D21 -> 0.070078957 | E24: =E18*E22*(1-$C$7)+E19*E21 -> 0.061375001 | F24: =F18*F22*(1-$C$7)+F19*F21 -> 0.060241053 | G24: =G18*G22*(1-$C$7)+G19*G21 -> 0.062871549 | H24: =H18*H22*(1-$C$7)+H19*H21 -> 0.068409292 | I24: =I18*I22*(1-$C$7)+I19*I21 -> 0.073856988 | J24: =J18*J22*(1-$C$7)+J19*J21 -> 0.07940495 | ... Q24: =Q18*Q22*(1-$C$7)+Q19*Q21 -> 0.1008134

Sheet DCF Model --->
B13: DCF Model --->

Sheet DCF Valuation 
B1: Tesla DCF Valuation
B3: g (Perpetuity growth) | C3: =Drivers!$C$13 -> 0.02
G4: Year ---> | H4: 1 | I4: 2 | J4: 3 | K4: 4 | L4: 5 | M4: 6 | N4: 7 | O4: 8 | P4: 9 | Q4: 10
B5: ($ in million) | C5: 2015 Act | D5: 2016 Act | E5: 2017 Act | F5: 2018 Act | G5: 2019 Act | H5: 2020 Fcst | I5: 2021 Fcst | J5: 2022 Fcst | K5: 2023 Fcst | L5: 2024 Fcst | M5: 2025 Fcst | N5: 2026 Fcst | O5: 2027 Fcst | P5: 2028 Fcst | Q5: 2029 Fcst
B6: Unlevered Free Cash Flow | H6: ='Cash Flow '!H20 -> 5085.2111 | I6: ='Cash Flow '!I20 -> 5828.0579 | J6: ='Cash Flow '!J20 -> 8342.5964 | K6: ='Cash Flow '!K20 -> 9960.3508 | L6: ='Cash Flow '!L20 -> 9289.3304 | M6: ='Cash Flow '!M20 -> 8587.4274 | N6: ='Cash Flow '!N20 -> 9195.606 | O6: ='Cash Flow '!O20 -> 9902.3811 | ... Q6: ='Cash Flow '!Q20 -> 9732.036
B7: Terminal value | Q7: =Q6*(1+$C$3)/($Q$9-$C$3) -> 122834.54
B9: Discount factor (WACC) | H9: ='WACC '!H24 -> 0.068409292 | I9: ='WACC '!I24 -> 0.073856988 | J9: ='WACC '!J24 -> 0.07940495 | K9: ='WACC '!K24 -> 0.084582829 | L9: ='WACC '!L24 -> 0.088952093 | M9: ='WACC '!M24 -> 0.092390241 | N9: ='WACC '!N24 -> 0.095151886 | O9: ='WACC '!O24 -> 0.097407935 | ... Q9: ='WACC '!Q24 -> 0.1008134
B10: Present value of UFCF ---> | H10: =H6/(1+H9)^H4 -> 4759.6096 | I10: =I6/(1+I9)^I4 -> 5053.9502 | J10: =J6/(1+J9)^J4 -> 6633.5807 | K10: =K6/(1+K9)^K4 -> 7198.1971 | L10: =L6/(1+L9)^L4 -> 6066.5327 | M10: =M6/(1+M9)^M4 -> 5053.5458 | N10: =N6/(1+N9)^N4 -> 4866.9834 | O10: =O6/(1+O9)^O4 -> 4707.5492 | ... Q10: =Q6/(1+Q9)^Q4 -> 3724.4885
B11: Present value of TV ---> | Q11: =Q7/(1+Q9)^Q4 -> 47009.263
B13: Perpetuity Growth Rate-Based Valuation
B14: Total PV of Cash Flows | F14: =SUM(H10:Q10) -> 52456.761
B15: PV of Terminal value | F15: =Q11 -> 47009.263
B16: Enterprise Value | F16: =SUM(F14:F15) -> 99466.024
B17: +Cash | F17: ='Balance Sheet '!G5 -> 6268
B18: -Financial liabilities | F18: ='Balance Sheet '!G28 -> 13419
B19: Equity Value | F19: =F16+F17-F18 -> 92315.024
B20: Number of shares outstanding (as of 30 Sep 2020) | F20: 932
B21: Price per share | F21: =F19/F20 -> 99.050455

Sheet Charts --->
B13: Charts --->

Sheet Cash Flow WaterFall
B1: Cash flow waterfall Chart
B3: Cash Flow 2019 | C3: ='Cash Flow '!G28 -> 2582.382
B4: NOPAT | C4: ='Cash Flow '!H7-'Cash Flow '!G7 -> 3087.4751
B5: Add-back D&A | C5: ='Cash Flow '!H8-'Cash Flow '!G8 -> -914.7672
B6: Working Capital | C6: ='Cash Flow '!H14-'Cash Flow '!G14 -> -1092.159
B7: Capex | C7: ='Cash Flow '!H16-'Cash Flow '!G16 -> -776.405
B8: Other | C8: =('Cash Flow '!H17-'Cash Flow '!G17)+('Cash Flow '!H18-'Cash Flow '!G18)+('Cash Flow '!H22-'Cash Flow '!G22)+('Cash Flow '!H23-'Cash Flow '!G23)+('Cash Flow '!H24-'Cash Flow '!G24)+('Cash Flow '!H25-'Cash Flow '!G25)+('Cash Flow '!H26-'Cash Flow '!G26) -> 1801.2724
B9: Cash Flow 2020 | C9: ='Cash Flow '!H28 -> 4687.7983
B21: Cash Flow 2028 | C21: ='Cash Flow '!P28 -> 9897.5591
B22: NOPAT | C22: ='Cash Flow '!Q7-'Cash Flow '!P7 -> 297.53979
B23: Add-back D&A | C23: ='Cash Flow '!Q8-'Cash Flow '!P8 -> 353.43414
B24: Working Capital | C24: ='Cash Flow '!Q14-'Cash Flow '!P14 -> 40.696608
B25: Capex | C25: ='Cash Flow '!Q16-'Cash Flow '!P16 -> -1072.8906
B26: Other | C26: =('Cash Flow '!Q17-'Cash Flow '!P17)+('Cash Flow '!Q18-'Cash Flow '!P18)+('Cash Flow '!Q22-'Cash Flow '!P22)+('Cash Flow '!Q23-'Cash Flow '!P23)+('Cash Flow '!Q24-'Cash Flow '!P24)+('Cash Flow '!Q25-'Cash Flow '!P25) -> -181.71585
B27: Cash Flow 2029 | C27: ='Cash Flow '!Q28 -> 9334.6232

Sheet Net Income Waterfall 
B1: Tesla Net Income Waterfall Chart FY18-FY20
B3: Net Inc. FY18 | C3: ='P&L '!F14 -> -976.091
B4: Δ Revenues | C4: ='P&L '!G5-'P&L '!F5 -> 3116.732
B5: Δ Cost of sales | C5: ='P&L '!G6-'P&L '!F6 -> -3089.753
B6: Δ Operating expenses | C6: ='P&L '!G8-'P&L '!F8 -> 292.094
B7: Δ Interest expenses | C7: ='P&L '!G10-'P&L '!F10 -> 20.672
B8: Δ Taxes | C8: ='P&L '!G12-'P&L '!F12 -> -52.163
B9: Δ Minority interest | C9: ='P&L '!G13-'P&L '!F13 -> -173.491
B10: Net Inc. FY19 | C10: ='P&L '!G14 -> -862
B11: Δ Revenues | C11: ='P&L '!H5-'P&L '!G5 -> 13813.953
B12: Δ Cost of sales | C12: ='P&L '!H6-'P&L '!G6 -> -9720.816
B13: Δ Operating expenses | C13: ='P&L '!H8-'P&L '!G8 -> -342.52313
B14: Δ Interest expenses | C14: ='P&L '!H10-'P&L '!G10 -> 92.94584
B15: Δ Taxes | C15: ='P&L '!H12-'P&L '!G12 -> -557.49757
B16: Net Inc. FY20 | C16: ='P&L '!H14 -> 2511.0623

Sheet Revenue by type of car
B1: Tesla Revenue by type of car
B3: Tesla Revenue Automotive (in mln $)
B4: Vehicle | C4: 2015 Act | D4: 2016 Act | E4: 2017 Act | F4: 2018 Act | G4: 2019 Act | H4: 2020 Fcst | I4: 2021 Fcst | J4: 2022 Fcst | K4: 2023 Fcst | L4: 2024 Fcst | M4: 2025 Fcst | N4: 2026 Fcst | O4: 2027 Fcst | P4: 2028 Fcst | Q4: 2029 Fcst | S4: Vehicle type
B5: Tesla Model 3 | E5: 88.268789 | F5: 8136.483 | G5: 14705.599 | H5: ='Tesla Revenue Automotive'!H5 -> 26587.137 | I5: ='Tesla Revenue Automotive'!I5 -> 29245.85 | J5: ='Tesla Revenue Automotive'!J5 -> 32170.435 | K5: ='Tesla Revenue Automotive'!K5 -> 34744.07 | L5: ='Tesla Revenue Automotive'!L5 -> 37523.596 | M5: ='Tesla Revenue Automotive'!M5 -> 39024.54 | N5: ='Tesla Revenue Automotive'!N5 -> 40585.521 | O5: ='Tesla Revenue Automotive'!O5 -> 42208.942 | ... Q5: ='Tesla Revenue Automotive'!Q5 -> 45653.192 | S5: Car
B6: Tesla Model S and X | C6: 3740.973 | D6: 6350.766 | E6: 9553.0312 | F6: 10378.5 | G6: 6115.4007 | H6: ='Tesla Revenue Automotive'!H6 -> 7186.6603 | I6: ='Tesla Revenue Automotive'!I6 -> 7474.1267 | J6: ='Tesla Revenue Automotive'!J6 -> 7773.0918 | K6: ='Tesla Revenue Automotive'!K6 -> 8084.0155 | L6: ='Tesla Revenue Automotive'!L6 -> 8407.3761 | M6: ='Tesla Revenue Automotive'!M6 -> 8743.6711 | N6: ='Tesla Revenue Automotive'!N6 -> 9093.418 | O6: ='Tesla Revenue Automotive'!O6 -> 9457.1547 | ... Q6: ='Tesla Revenue Automotive'!Q6 -> 10228.859 | S6: Car
B7: Tesla Model Y | C7: =($R7*'Tesla Automotive Deliveries'!C7)*C16/1000000 -> 0 | D7: =($R7*'Tesla Automotive Deliveries'!D7)*D16/1000000 -> 0 | E7: =($R7*'Tesla Automotive Deliveries'!E7)*E16/1000000 -> 0 | F7: =($R7*'Tesla Automotive Deliveries'!F7)*F16/1000000 -> 0 | G7: =($R7*'Tesla Automotive Deliveries'!G7)*G16/1000000 -> 0 | H7: ='Tesla Revenue Automotive'!H7 -> 109.75608 | I7: ='Tesla Revenue Automotive'!I7 -> 9087.5421 | J7: ='Tesla Revenue Automotive'!J7 -> 18716.709 | K7: ='Tesla Revenue Automotive'!K7 -> 29946.735 | L7: ='Tesla Revenue Automotive'!L7 -> 32941.408 | M7: ='Tesla Revenue Automotive'!M7 -> 36235.549 | N7: ='Tesla Revenue Automotive'!N7 -> 39134.393 | O7: ='Tesla Revenue Automotive'!O7 -> 42265.145 | ... Q7: ='Tesla Revenue Automotive'!Q7 -> 45713.98 | S7: Car
B8: Tesla Roadster 2 | C8: =($R8*'Tesla Automotive Deliveries'!C8)*C17/1000000 -> 0 | D8: =($R8*'Tesla Automotive Deliveries'!D8)*D17/1000000 -> 0 | E8: =($R8*'Tesla Automotive Deliveries'!E8)*E17/1000000 -> 0 | F8: =($R8*'Tesla Automotive Deliveries'!F8)*F17/1000000 -> 0 | G8: =($R8*'Tesla Automotive Deliveries'!G8)*G17/1000000 -> 0 | H8: ='Tesla Revenue Automotive'!H8 -> - | I8: ='Tesla Revenue Automotive'!I8 -> - | J8: ='Tesla Revenue Automotive'!J8 -> 114.75 | K8: ='Tesla Revenue Automotive'!K8 -> 229.5 | L8: ='Tesla Revenue Automotive'!L8 -> 344.25 | M8: ='Tesla Revenue Automotive'!M8 -> 378.675 | N8: ='Tesla Revenue Automotive'!N8 -> 416.5425 | O8: ='Tesla Revenue Automotive'!O8 -> 449.8659 | ... Q8: ='Tesla Revenue Automotive'!Q8 -> 505.28938 | S8: Car
B9: Tesla Pickup | C9: =($R9*'Tesla Automotive Deliveries'!C9)*C18/1000000 -> 0 | D9: =($R9*'Tesla Automotive Deliveries'!D9)*D18/1000000 -> 0 | E9: =($R9*'Tesla Automotive Deliveries'!E9)*E18/1000000 -> 0 | F9: =($R9*'Tesla Automotive Deliveries'!F9)*F18/1000000 -> 0 | G9: =($R9*'Tesla Automotive Deliveries'!G9)*G18/1000000 -> 0 | H9: ='Tesla Revenue Automotive'!H9 -> - | I9: ='Tesla Revenue Automotive'!I9 -> 14.892 | J9: ='Tesla Revenue Automotive'!J9 -> 1233.0221 | K9: ='Tesla Revenue Automotive'!K9 -> 2539.5334 | L9: ='Tesla Revenue Automotive'!L9 -> 4063.2535 | M9: ='Tesla Revenue Automotive'!M9 -> 4469.5788 | N9: ='Tesla Revenue Automotive'!N9 -> 4916.5367 | O9: ='Tesla Revenue Automotive'!O9 -> 5309.8597 | ... Q9: ='Tesla Revenue Automotive'!Q9 -> 5964.0344 | S9: Pickup
B10: Tesla Semi | C10: =($R10*'Tesla Automotive Deliveries'!C10)*C19/1000000 -> 0 | D10: =($R10*'Tesla Automotive Deliveries'!D10)*D19/1000000 -> 0 | E10: =($R10*'Tesla Automotive Deliveries'!E10)*E19/1000000 -> 0 | F10: =($R10*'Tesla Automotive Deliveries'!F10)*F19/1000000 -> 0 | G10: =($R10*'Tesla Automotive Deliveries'!G10)*G19/1000000 -> 0 | H10: ='Tesla Revenue Automotive'!H10 -> - | I10: ='Tesla Revenue Automotive'!I10 -> 44.625 | J10: ='Tesla Revenue Automotive'!J10 -> 3694.8438 | K10: ='Tesla Revenue Automotive'!K10 -> 7609.9033 | L10: ='Tesla Revenue Automotive'!L10 -> 12175.845 | M10: ='Tesla Revenue Automotive'!M10 -> 13393.43 | N10: ='Tesla Revenue Automotive'!N10 -> 14732.773 | O10: ='Tesla Revenue Automotive'!O10 -> 15911.395 | ... Q10: ='Tesla Revenue Automotive'!Q10 -> 17871.678 | S10: Truck
B11: Total | C11: =SUM(C5:C10) -> 3740.973 | D11: =SUM(D5:D10) -> 6350.766 | E11: =SUM(E5:E10) -> 9641.3 | F11: =SUM(F5:F10) -> 18514.983 | G11: =SUM(G5:G10) -> 20821 | H11: =SUM(H5:H10) -> 33883.553 | I11: =SUM(I5:I10) -> 45867.036 | J11: =SUM(J5:J10) -> 63702.852 | ... Q11: =SUM(Q5:Q10) -> 125937.03

Sheet Types of vehicles
B1: Tesla Types of vehicles
C4: Vehicles | D4: ='[1]Types of vehicles'!C13 -> 2015 Act | E4: ='[1]Types of vehicles'!D13 -> 2016 Act | F4: ='[1]Types of vehicles'!E13 -> 2017 Act | G4: ='[1]Types of vehicles'!F13 -> 2018 Act | H4: ='[1]Types of vehicles'!G13 -> 2019 Act | I4: ='[1]Types of vehicles'!H13 -> 2020 Fcst | J4: ='[1]Types of vehicles'!I13 -> 2021 Fcst | K4: ='[1]Types of vehicles'!J13 -> 2022 Fcst | ... R4: ='[1]Types of vehicles'!Q13 -> 2029 Fcst
C5: ='[1]Types of vehicles'!B14 -> Car | I5: =SUMIF('Revenue by type of car'!$S$5:$S$10,'Types of vehicles'!$C$5,'Revenue by type of car'!H5:H10) -> 33883.553 | J5: =SUMIF('Revenue by type of car'!$S$5:$S$10,'Types of vehicles'!$C$5,'Revenue by type of car'!I5:I10) -> 45807.519 | K5: =SUMIF('Revenue by type of car'!$S$5:$S$10,'Types of vehicles'!$C$5,'Revenue by type of car'!J5:J10) -> 58774.987 | L5: =SUMIF('Revenue by type of car'!$S$5:$S$10,'Types of vehicles'!$C$5,'Revenue by type of car'!K5:K10) -> 73004.321 | M5: =SUMIF('Revenue by type of car'!$S$5:$S$10,'Types of vehicles'!$C$5,'Revenue by type of car'!L5:L10) -> 79216.63 | N5: =SUMIF('Revenue by type of car'!$S$5:$S$10,'Types of vehicles'!$C$5,'Revenue by type of car'!M5:M10) -> 84382.435 | O5: =SUMIF('Revenue by type of car'!$S$5:$S$10,'Types of vehicles'!$C$5,'Revenue by type of car'!N5:N10) -> 89229.875 | P5: =SUMIF('Revenue by type of car'!$S$5:$S$10,'Types of vehicles'!$C$5,'Revenue by type of car'!O5:O10) -> 94381.107 | ... R5: =SUMIF('Revenue by type of car'!$S$5:$S$10,'Types of vehicles'!$C$5,'Revenue by type of car'!Q5:Q10) -> 102101.32
C6: ='[1]Types of vehicles'!B15 -> Pickup | I6: =SUMIF('Revenue by type of car'!$S$5:$S$10,'Types of vehicles'!$C$6,'Revenue by type of car'!H5:H11) -> 0 | J6: =SUMIF('Revenue by type of car'!$S$5:$S$10,'Types of vehicles'!$C$6,'Revenue by type of car'!I5:I11) -> 14.892 | K6: =SUMIF('Revenue by type of car'!$S$5:$S$10,'Types of vehicles'!$C$6,'Revenue by type of car'!J5:J11) -> 1233.0221 | L6: =SUMIF('Revenue by type of car'!$S$5:$S$10,'Types of vehicles'!$C$6,'Revenue by type of car'!K5:K11) -> 2539.5334 | M6: =SUMIF('Revenue by type of car'!$S$5:$S$10,'Types of vehicles'!$C$6,'Revenue by type of car'!L5:L11) -> 4063.2535 | N6: =SUMIF('Revenue by type of car'!$S$5:$S$10,'Types of vehicles'!$C$6,'Revenue by type of car'!M5:M11) -> 4469.5788 | O6: =SUMIF('Revenue by type of car'!$S$5:$S$10,'Types of vehicles'!$C$6,'Revenue by type of car'!N5:N11) -> 4916.5367 | P6: =SUMIF('Revenue by type of car'!$S$5:$S$10,'Types of vehicles'!$C$6,'Revenue by type of car'!O5:O11) -> 5309.8597 | ... R6: =SUMIF('Revenue by type of car'!$S$5:$S$10,'Types of vehicles'!$C$6,'Revenue by type of car'!Q5:Q11) -> 5964.0344
C7: ='[1]Types of vehicles'!B16 -> Truck | I7: =SUMIF('Revenue by type of car'!$S$5:$S$10,'Types of vehicles'!$C$7,'Revenue by type of car'!H5:H12) -> 0 | J7: =SUMIF('Revenue by type of car'!$S$5:$S$10,'Types of vehicles'!$C$7,'Revenue by type of car'!I5:I12) -> 44.625 | K7: =SUMIF('Revenue by type of car'!$S$5:$S$10,'Types of vehicles'!$C$7,'Revenue by type of car'!J5:J12) -> 3694.8438 | L7: =SUMIF('Revenue by type of car'!$S$5:$S$10,'Types of vehicles'!$C$7,'Revenue by type of car'!K5:K12) -> 7609.9033 | M7: =SUMIF('Revenue by type of car'!$S$5:$S$10,'Types of vehicles'!$C$7,'Revenue by type of car'!L5:L12) -> 12175.845 | N7: =SUMIF('Revenue by type of car'!$S$5:$S$10,'Types of vehicles'!$C$7,'Revenue by type of car'!M5:M12) -> 13393.43 | O7: =SUMIF('Revenue by type of car'!$S$5:$S$10,'Types of vehicles'!$C$7,'Revenue by type of car'!N5:N12) -> 14732.773 | P7: =SUMIF('Revenue by type of car'!$S$5:$S$10,'Types of vehicles'!$C$7,'Revenue by type of car'!O5:O12) -> 15911.395 | ... R7: =SUMIF('Revenue by type of car'!$S$5:$S$10,'Types of vehicles'!$C$7,'Revenue by type of car'!Q5:Q12) -> 17871.678
C8: ='[1]Types of vehicles'!B17 -> Total | I8: =SUM(I5:I7) -> 33883.553 | J8: =SUM(J5:J7) -> 45867.036 | K8: =SUM(K5:K7) -> 63702.852 | L8: =SUM(L5:L7) -> 83153.757 | M8: =SUM(M5:M7) -> 95455.729 | N8: =SUM(N5:N7) -> 102245.44 | O8: =SUM(O5:O7) -> 108879.18 | P8: =SUM(P5:P7) -> 115602.36 | ... R8: =SUM(R5:R7) -> 125937.03
